Workbook
Name Slicer_Product_Name: #N/A

Sheet Working Sheet

Sheet Monthly Sales
B1: Product Name | C1: Jan(1) | D1: Feb(2) | E1: Mar(3) | F1: Apr(4) | G1: May(5) | H1: Jun(6) | I1: Jul(7) | J1: Aug(8) | K1: Sep(9) | L1: Oct(10) | M1: Nov(11) | N1: Dec(12) | O1: Total (Year) | P1: Type | Q1: Month Wise | R1: Month wise(No.) | S1: Average sales
B2: Iodex | C2: ='Daily Sales(JAN)'!AH3 -> 179 | D2: =Februray!AH3 -> 177 | E2: =March!AH3 -> 166 | F2: =Aprail!AH3 -> 137 | G2: =May!AH3 -> 144 | H2: =June!AH3 -> 165 | I2: =July!AH3 -> 169 | J2: =August!AH3 -> 160 | K2: =September!AH3 -> 147 | L2: =October!AH3 -> 83 | M2: =November!AH3 -> 83 | N2: =December!AH3 -> 83 | O2: =SUM(C2:N2) -> 1693 | P2: Branded | Q2: =SUM(C2:OFFSET(C2,0,$R$2-1)) -> 659 | R2: 4 | S2: =AVERAGE(C2:N2) -> 141.08333
B3: Nimocet | C3: ='Daily Sales(JAN)'!AH4 -> 179 | D3: =Februray!AH4 -> 203 | E3: =March!AH4 -> 163 | F3: =Aprail!AH4 -> 157 | G3: =May!AH4 -> 171 | H3: =June!AH4 -> 162 | I3: =July!AH4 -> 181 | J3: =August!AH4 -> 157 | K3: =September!AH4 -> 165 | L3: =October!AH4 | M3: =November!AH4 | N3: =December!AH4 | O3: =SUM(C3:N3) -> 1538 | P3: Branded | Q3: =SUM(C3:OFFSET(C3,0,$R$2-1)) -> 702 | S3: =AVERAGE(C3:N3) -> 170.88889
B4: Paracetamol | C4: ='Daily Sales(JAN)'!AH5 -> 177 | D4: =Februray!AH5 -> 161 | E4: =March!AH5 -> 182 | F4: =Aprail!AH5 -> 172 | G4: =May!AH5 -> 193 | H4: =June!AH5 -> 165 | I4: =July!AH5 -> 216 | J4: =August!AH5 -> 178 | K4: =September!AH5 -> 176 | L4: =October!AH5 | M4: =November!AH5 | N4: =December!AH5 | O4: =SUM(C4:N4) -> 1620 | P4: Generic | Q4: =SUM(C4:OFFSET(C4,0,$R$2-1)) -> 692 | S4: =AVERAGE(C4:N4) -> 180
B5: Monocef | C5: ='Daily Sales(JAN)'!AH6 -> 170 | D5: =Februray!AH6 -> 142 | E5: =March!AH6 -> 182 | F5: =Aprail!AH6 -> 167 | G5: =May!AH6 -> 163 | H5: =June!AH6 -> 152 | I5: =July!AH6 -> 177 | J5: =August!AH6 -> 186 | K5: =September!AH6 -> 159 | L5: =October!AH6 | M5: =November!AH6 | N5: =December!AH6 | O5: =SUM(C5:N5) -> 1498 | P5: Generic | Q5: =SUM(C5:OFFSET(C5,0,$R$2-1)) -> 661 | S5: =AVERAGE(C5:N5) -> 166.44444
B6: Cyclopalm | C6: ='Daily Sales(JAN)'!AH7 -> 157 | D6: =Februray!AH7 -> 157 | E6: =March!AH7 -> 181 | F6: =Aprail!AH7 -> 171 | G6: =May!AH7 -> 161 | H6: =June!AH7 -> 174 | I6: =July!AH7 -> 163 | J6: =August!AH7 -> 145 | K6: =September!AH7 -> 151 | L6: =October!AH7 | M6: =November!AH7 | N6: =December!AH7 | O6: =SUM(C6:N6) -> 1460 | P6: Branded | Q6: =SUM(C6:OFFSET(C6,0,$R$2-1)) -> 666 | S6: =AVERAGE(C6:N6) -> 162.22222
B7: Cetaphil | C7: ='Daily Sales(JAN)'!AH8 -> 167 | D7: =Februray!AH8 -> 166 | E7: =March!AH8 -> 166 | F7: =Aprail!AH8 -> 181 | G7: =May!AH8 -> 202 | H7: =June!AH8 -> 152 | I7: =July!AH8 -> 170 | J7: =August!AH8 -> 164 | K7: =September!AH8 -> 192 | L7: =October!AH8 | M7: =November!AH8 | N7: =December!AH8 | O7: =SUM(C7:N7) -> 1560 | P7: Branded | Q7: =SUM(C7:OFFSET(C7,0,$R$2-1)) -> 680 | S7: =AVERAGE(C7:N7) -> 173.33333
B8: Acetaminophen | C8: ='Daily Sales(JAN)'!AH9 -> 197 | D8: =Februray!AH9 -> 178 | E8: =March!AH9 -> 170 | F8: =Aprail!AH9 -> 174 | G8: =May!AH9 -> 160 | H8: =June!AH9 -> 164 | I8: =July!AH9 -> 194 | J8: =August!AH9 -> 180 | K8: =September!AH9 -> 170 | L8: =October!AH9 | M8: =November!AH9 | N8: =December!AH9 | O8: =SUM(C8:N8) -> 1587 | P8: Generic | Q8: =SUM(C8:OFFSET(C8,0,$R$2-1)) -> 719 | S8: =AVERAGE(C8:N8) -> 176.33333
B9: Ibuprofen | C9: ='Daily Sales(JAN)'!AH10 -> 199 | D9: =Februray!AH10 -> 159 | E9: =March!AH10 -> 177 | F9: =Aprail!AH10 -> 166 | G9: =May!AH10 -> 164 | H9: =June!AH10 -> 167 | I9: =July!AH10 -> 158 | J9: =August!AH10 -> 153 | K9: =September!AH10 -> 187 | L9: =October!AH10 | M9: =November!AH10 | N9: =December!AH10 | O9: =SUM(C9:N9) -> 1530 | P9: Generic | Q9: =SUM(C9:OFFSET(C9,0,$R$2-1)) -> 701 | S9: =AVERAGE(C9:N9) -> 170
B10: Aspirin | C10: ='Daily Sales(JAN)'!AH11 -> 147 | D10: =Februray!AH11 -> 152 | E10: =March!AH11 -> 179 | F10: =Aprail!AH11 -> 159 | G10: =May!AH11 -> 182 | H10: =June!AH11 -> 152 | I10: =July!AH11 -> 147 | J10: =August!AH11 -> 166 | K10: =September!AH11 -> 152 | L10: =October!AH11 | M10: =November!AH11 | N10: =December!AH11 | O10: =SUM(C10:N10) -> 1436 | P10: Generic | Q10: =SUM(C10:OFFSET(C10,0,$R$2-1)) -> 637 | S10: =AVERAGE(C10:N10) -> 159.55556
B11: Amoxicillin | C11: ='Daily Sales(JAN)'!AH12 -> 195 | D11: =Februray!AH12 -> 155 | E11: =March!AH12 -> 183 | F11: =Aprail!AH12 -> 155 | G11: =May!AH12 -> 196 | H11: =June!AH12 -> 167 | I11: =July!AH12 -> 167 | J11: =August!AH12 -> 151 | K11: =September!AH12 -> 146 | L11: =October!AH12 | M11: =November!AH12 | N11: =December!AH12 | O11: =SUM(C11:N11) -> 1515 | P11: Generic | Q11: =SUM(C11:OFFSET(C11,0,$R$2-1)) -> 688 | S11: =AVERAGE(C11:N11) -> 168.33333
B12: Ciprofloxacin | C12: ='Daily Sales(JAN)'!AH13 -> 156 | D12: =Februray!AH13 -> 180 | E12: =March!AH13 -> 183 | F12: =Aprail!AH13 -> 169 | G12: =May!AH13 -> 163 | H12: =June!AH13 -> 163 | I12: =July!AH13 -> 161 | J12: =August!AH13 -> 140 | K12: =September!AH13 -> 157 | L12: =October!AH13 | M12: =November!AH13 | N12: =December!AH13 | O12: =SUM(C12:N12) -> 1472 | P12: Generic | Q12: =SUM(C12:OFFSET(C12,0,$R$2-1)) -> 688 | S12: =AVERAGE(C12:N12) -> 163.55556
B13: Lisinopril | C13: ='Daily Sales(JAN)'!AH14 -> 158 | D13: =Februray!AH14 -> 156 | E13: =March!AH14 -> 166 | F13: =Aprail!AH14 -> 153 | G13: =May!AH14 -> 200 | H13: =June!AH14 -> 163 | I13: =July!AH14 -> 215 | J13: =August!AH14 -> 165 | K13: =September!AH14 -> 219 | L13: =October!AH14 | M13: =November!AH14 | N13: =December!AH14 | O13: =SUM(C13:N13) -> 1595 | P13: Generic | Q13: =SUM(C13:OFFSET(C13,0,$R$2-1)) -> 633 | S13: =AVERAGE(C13:N13) -> 177.22222
B14: Atorvastatin | C14: ='Daily Sales(JAN)'!AH15 -> 154 | D14: =Februray!AH15 -> 157 | E14: =March!AH15 -> 165 | F14: =Aprail!AH15 -> 183 | G14: =May!AH15 -> 148 | H14: =June!AH15 -> 145 | I14: =July!AH15 -> 173 | J14: =August!AH15 -> 189 | K14: =September!AH15 -> 148 | L14: =October!AH15 | M14: =November!AH15 | N14: =December!AH15 | O14: =SUM(C14:N14) -> 1462 | P14: Generic | Q14: =SUM(C14:OFFSET(C14,0,$R$2-1)) -> 659 | S14: =AVERAGE(C14:N14) -> 162.44444
... B56: Lamotrigine | C56: ='Daily Sales(JAN)'!AH57 -> 182 | D56: =Februray!AH57 -> 121 | E56: =March!AH57 -> 153 | F56: =Aprail!AH57 -> 187 | G56: =May!AH57 -> 180 | H56: =June!AH57 -> 137 | I56: =July!AH57 -> 174 | J56: =August!AH57 -> 162 | K56: =September!AH57 -> 153 | L56: =October!AH57 | M56: =November!AH57 | N56: =December!AH57 | O56: =SUM(C56:N56) -> 1449 | P56: Generic | Q56: =SUM(C56:OFFSET(C56,0,$R$2-1)) -> 643 | S56: =AVERAGE(C56:N56) -> 161

Sheet Daily Sales(JAN)
C1: =TEXT(C2,"DDD") -> Mon | D1: =TEXT(D2,"DDD") -> Tue | E1: =TEXT(E2,"DDD") -> Wed | F1: =TEXT(F2,"DDD") -> Thu | G1: =TEXT(G2,"DDD") -> Fri | H1: =TEXT(H2,"DDD") -> Sat | I1: =TEXT(I2,"DDD") -> Sun | J1: =TEXT(J2,"DDD") -> Mon | ... AG1: =TEXT(AG2,"DDD") -> Wed | AH1: Total Sales | AI1: Incoming price (Including GST) | AJ1: Sales price | AK1: Profit Margin | AL1: Total collection | AM1: Net collection | AO1: Month | AP1: January
B2: Product Name | C2: =IF(COLUMNS($C$2:C2)>DAY($AP$4),"",$AP$3+COLUMNS($C$2:C2)-1) -> 45292 | D2: =IF(COLUMNS($C$2:D2)>DAY($AP$4),"",$AP$3+COLUMNS($C$2:D2)-1) -> 45293 | E2: =IF(COLUMNS($C$2:E2)>DAY($AP$4),"",$AP$3+COLUMNS($C$2:E2)-1) -> 45294 | F2: =IF(COLUMNS($C$2:F2)>DAY($AP$4),"",$AP$3+COLUMNS($C$2:F2)-1) -> 45295 | G2: =IF(COLUMNS($C$2:G2)>DAY($AP$4),"",$AP$3+COLUMNS($C$2:G2)-1) -> 45296 | H2: =IF(COLUMNS($C$2:H2)>DAY($AP$4),"",$AP$3+COLUMNS($C$2:H2)-1) -> 45297 | I2: =IF(COLUMNS($C$2:I2)>DAY($AP$4),"",$AP$3+COLUMNS($C$2:I2)-1) -> 45298 | J2: =IF(COLUMNS($C$2:J2)>DAY($AP$4),"",$AP$3+COLUMNS($C$2:J2)-1) -> 45299 | ... AG2: =IF(COLUMNS($C$2:AG2)>DAY($AP$4),"",$AP$3+COLUMNS($C$2:AG2)-1) -> 45322 | AO2: Year | AP2: 2024
B3: Iodex | C3: =RANDBETWEEN(1,10) -> 1 | D3: =RANDBETWEEN(1,10) -> 8 | E3: =RANDBETWEEN(1,10) -> 10 | F3: =RANDBETWEEN(1,10) -> 2 | G3: =RANDBETWEEN(1,10) -> 7 | H3: =RANDBETWEEN(1,10) -> 10 | I3: =RANDBETWEEN(1,10) -> 6 | J3: =RANDBETWEEN(1,10) -> 8 | ... AG3: =RANDBETWEEN(1,10) -> 2 | AH3: =SUM($C3:$AG3) -> 179 | AI3: 40 | AJ3: 80 | AK3: =AJ3-AI3 -> 40 | AL3: =AJ3*AH3 -> 14320 | AM3: =AK3*AH3 -> 7160 | AO3: Starting Date | AP3: =DATE(AP2,MONTH(AP1&1),1) -> 45292
B4: Nimocet | C4: =RANDBETWEEN(1,10) -> 5 | D4: =RANDBETWEEN(1,10) -> 4 | E4: =RANDBETWEEN(1,10) -> 7 | F4: =RANDBETWEEN(1,10) -> 3 | G4: =RANDBETWEEN(1,10) -> 9 | H4: =RANDBETWEEN(1,10) -> 6 | I4: =RANDBETWEEN(1,10) -> 3 | J4: =RANDBETWEEN(1,10) -> 6 | ... AG4: =RANDBETWEEN(1,10) -> 1 | AH4: =SUM($C4:$AG4) -> 179 | AI4: 7 | AJ4: 15 | AK4: =AJ4-AI4 -> 8 | AL4: =AJ4*AH4 -> 2685 | AM4: =AK4*AH4 -> 1432 | AO4: Ending Date | AP4: =EOMONTH(AP3,0) -> 45322
B5: Paracetamol | C5: =RANDBETWEEN(1,10) -> 6 | D5: =RANDBETWEEN(1,10) -> 5 | E5: =RANDBETWEEN(1,10) -> 3 | F5: =RANDBETWEEN(1,10) -> 3 | G5: =RANDBETWEEN(1,10) -> 7 | H5: =RANDBETWEEN(1,10) -> 6 | I5: =RANDBETWEEN(1,10) -> 7 | J5: =RANDBETWEEN(1,10) -> 4 | ... AG5: =RANDBETWEEN(1,10) -> 2 | AH5: =SUM($C5:$AG5) -> 177 | AI5: 5 | AJ5: 10 | AK5: =AJ5-AI5 -> 5 | AL5: =AJ5*AH5 -> 1770 | AM5: =AK5*AH5 -> 885
B6: Monocef | C6: =RANDBETWEEN(1,10) -> 5 | D6: =RANDBETWEEN(1,10) -> 8 | E6: =RANDBETWEEN(1,10) -> 8 | F6: =RANDBETWEEN(1,10) -> 8 | G6: =RANDBETWEEN(1,10) -> 3 | H6: =RANDBETWEEN(1,10) -> 6 | I6: =RANDBETWEEN(1,10) -> 2 | J6: =RANDBETWEEN(1,10) -> 9 | ... AG6: =RANDBETWEEN(1,10) -> 3 | AH6: =SUM($C6:$AG6) -> 170 | AI6: 45 | AJ6: 80 | AK6: =AJ6-AI6 -> 35 | AL6: =AJ6*AH6 -> 13600 | AM6: =AK6*AH6 -> 5950
B7: Cyclopalm | C7: =RANDBETWEEN(1,10) -> 5 | D7: =RANDBETWEEN(1,10) -> 6 | E7: =RANDBETWEEN(1,10) -> 9 | F7: =RANDBETWEEN(1,10) -> 2 | G7: =RANDBETWEEN(1,10) -> 10 | H7: =RANDBETWEEN(1,10) -> 3 | I7: =RANDBETWEEN(1,10) -> 1 | J7: =RANDBETWEEN(1,10) -> 8 | ... AG7: =RANDBETWEEN(1,10) -> 1 | AH7: =SUM($C7:$AG7) -> 157 | AI7: 392 | AJ7: 420 | AK7: =AJ7-AI7 -> 28 | AL7: =AJ7*AH7 -> 65940 | AM7: =AK7*AH7 -> 4396 | AO7: Expanses
B8: Cetaphil | C8: =RANDBETWEEN(1,10) -> 6 | D8: =RANDBETWEEN(1,10) -> 2 | E8: =RANDBETWEEN(1,10) -> 2 | F8: =RANDBETWEEN(1,10) -> 10 | G8: =RANDBETWEEN(1,10) -> 9 | H8: =RANDBETWEEN(1,10) -> 4 | I8: =RANDBETWEEN(1,10) -> 8 | J8: =RANDBETWEEN(1,10) -> 3 | ... AG8: =RANDBETWEEN(1,10) -> 1 | AH8: =SUM($C8:$AG8) -> 167 | AI8: 86 | AJ8: 100 | AK8: =AJ8-AI8 -> 14 | AL8: =AJ8*AH8 -> 16700 | AM8: =AK8*AH8 -> 2338 | AO8: Employee Salary
B9: Acetaminophen | C9: =RANDBETWEEN(1,10) -> 1 | D9: =RANDBETWEEN(1,10) -> 4 | E9: =RANDBETWEEN(1,10) -> 1 | F9: =RANDBETWEEN(1,10) -> 4 | G9: =RANDBETWEEN(1,10) -> 1 | H9: =RANDBETWEEN(1,10) -> 9 | I9: =RANDBETWEEN(1,10) -> 5 | J9: =RANDBETWEEN(1,10) -> 9 | ... AG9: =RANDBETWEEN(1,10) -> 10 | AH9: =SUM($C9:$AG9) -> 197 | AI9: 271 | AJ9: 300 | AK9: =AJ9-AI9 -> 29 | AL9: =AJ9*AH9 -> 59100 | AM9: =AK9*AH9 -> 5713 | AO9: Kaishav(Owner) | AP9: ='Attendence (Jan)'!AL3 -> 50000
B10: Ibuprofen | C10: =RANDBETWEEN(1,10) -> 10 | D10: =RANDBETWEEN(1,10) -> 9 | E10: =RANDBETWEEN(1,10) -> 5 | F10: =RANDBETWEEN(1,10) -> 3 | G10: =RANDBETWEEN(1,10) -> 9 | H10: =RANDBETWEEN(1,10) -> 10 | I10: =RANDBETWEEN(1,10) -> 9 | J10: =RANDBETWEEN(1,10) -> 10 | ... AG10: =RANDBETWEEN(1,10) -> 10 | AH10: =SUM($C10:$AG10) -> 199 | AI10: 226 | AJ10: 250 | AK10: =AJ10-AI10 -> 24 | AL10: =AJ10*AH10 -> 49750 | AM10: =AK10*AH10 -> 4776 | AO10: Raman | AP10: ='Attendence (Jan)'!AL4 -> 14500
B11: Aspirin | C11: =RANDBETWEEN(1,10) -> 8 | D11: =RANDBETWEEN(1,10) -> 4 | E11: =RANDBETWEEN(1,10) -> 2 | F11: =RANDBETWEEN(1,10) -> 2 | G11: =RANDBETWEEN(1,10) -> 6 | H11: =RANDBETWEEN(1,10) -> 10 | I11: =RANDBETWEEN(1,10) -> 3 | J11: =RANDBETWEEN(1,10) -> 3 | ... AG11: =RANDBETWEEN(1,10) -> 10 | AH11: =SUM($C11:$AG11) -> 147 | AI11: 390 | AJ11: 450 | AK11: =AJ11-AI11 -> 60 | AL11: =AJ11*AH11 -> 66150 | AM11: =AK11*AH11 -> 8820 | AO11: Sohan | AP11: ='Attendence (Jan)'!AL5 -> 17400
B12: Amoxicillin | C12: =RANDBETWEEN(1,10) -> 7 | D12: =RANDBETWEEN(1,10) -> 7 | E12: =RANDBETWEEN(1,10) -> 10 | F12: =RANDBETWEEN(1,10) -> 7 | G12: =RANDBETWEEN(1,10) -> 5 | H12: =RANDBETWEEN(1,10) -> 8 | I12: =RANDBETWEEN(1,10) -> 3 | J12: =RANDBETWEEN(1,10) -> 9 | ... AG12: =RANDBETWEEN(1,10) -> 8 | AH12: =SUM($C12:$AG12) -> 195 | AI12: 379 | AJ12: 430 | AK12: =AJ12-AI12 -> 51 | AL12: =AJ12*AH12 -> 83850 | AM12: =AK12*AH12 -> 9945 | AO12: Tilak | AP12: ='Attendence (Jan)'!AL6 -> 9666.6667
B13: Ciprofloxacin | C13: =RANDBETWEEN(1,10) -> 4 | D13: =RANDBETWEEN(1,10) -> 10 | E13: =RANDBETWEEN(1,10) -> 1 | F13: =RANDBETWEEN(1,10) -> 1 | G13: =RANDBETWEEN(1,10) -> 1 | H13: =RANDBETWEEN(1,10) -> 6 | I13: =RANDBETWEEN(1,10) -> 9 | J13: =RANDBETWEEN(1,10) -> 2 | ... AG13: =RANDBETWEEN(1,10) -> 8 | AH13: =SUM($C13:$AG13) -> 156 | AI13: 368 | AJ13: 435 | AK13: =AJ13-AI13 -> 67 | AL13: =AJ13*AH13 -> 67860 | AM13: =AK13*AH13 -> 10452 | AO13: Bill to pay | AP13: 10000
B14: Lisinopril | C14: =RANDBETWEEN(1,10) -> 5 | D14: =RANDBETWEEN(1,10) -> 5 | E14: =RANDBETWEEN(1,10) -> 5 | F14: =RANDBETWEEN(1,10) -> 4 | G14: =RANDBETWEEN(1,10) -> 2 | H14: =RANDBETWEEN(1,10) -> 10 | I14: =RANDBETWEEN(1,10) -> 1 | J14: =RANDBETWEEN(1,10) -> 8 | ... AG14: =RANDBETWEEN(1,10) -> 5 | AH14: =SUM($C14:$AG14) -> 158 | AI14: 88 | AJ14: 99 | AK14: =AJ14-AI14 -> 11 | AL14: =AJ14*AH14 -> 15642 | AM14: =AK14*AH14 -> 1738 | AO14: other | AP14: 2000
B15: Atorvastatin | C15: =RANDBETWEEN(1,10) -> 6 | D15: =RANDBETWEEN(1,10) -> 8 | E15: =RANDBETWEEN(1,10) -> 3 | F15: =RANDBETWEEN(1,10) -> 10 | G15: =RANDBETWEEN(1,10) -> 4 | H15: =RANDBETWEEN(1,10) -> 6 | I15: =RANDBETWEEN(1,10) -> 7 | J15: =RANDBETWEEN(1,10) -> 1 | ... AG15: =RANDBETWEEN(1,10) -> 2 | AH15: =SUM($C15:$AG15) -> 154 | AI15: 391 | AJ15: 500 | AK15: =AJ15-AI15 -> 109 | AL15: =AJ15*AH15 -> 77000 | AM15: =AK15*AH15 -> 16786 | AO15: Net collection | AP15: =SUM(AM3:AM57) -> 293799
B16: Metformin | C16: =RANDBETWEEN(1,10) -> 7 | D16: =RANDBETWEEN(1,10) -> 1 | E16: =RANDBETWEEN(1,10) -> 1 | F16: =RANDBETWEEN(1,10) -> 6 | G16: =RANDBETWEEN(1,10) -> 9 | H16: =RANDBETWEEN(1,10) -> 3 | I16: =RANDBETWEEN(1,10) -> 1 | J16: =RANDBETWEEN(1,10) -> 1 | ... AG16: =RANDBETWEEN(1,10) -> 9 | AH16: =SUM($C16:$AG16) -> 183 | AI16: 261 | AJ16: 300 | AK16: =AJ16-AI16 -> 39 | AL16: =AJ16*AH16 -> 54900 | AM16: =AK16*AH16 -> 7137 | AO16: Net Income | AP16: =AP15-(AP9+AP10+AP11+AP12+AP13+AP14) -> 190232.33
B17: Simvastatin | C17: =RANDBETWEEN(1,10) -> 1 | D17: =RANDBETWEEN(1,10) -> 7 | E17: =RANDBETWEEN(1,10) -> 7 | F17: =RANDBETWEEN(1,10) -> 6 | G17: =RANDBETWEEN(1,10) -> 4 | H17: =RANDBETWEEN(1,10) -> 6 | I17: =RANDBETWEEN(1,10) -> 5 | J17: =RANDBETWEEN(1,10) -> 4 | ... AG17: =RANDBETWEEN(1,10) -> 4 | AH17: =SUM($C17:$AG17) -> 163 | AI17: 67 | AJ17: 99 | AK17: =AJ17-AI17 -> 32 | AL17: =AJ17*AH17 -> 16137 | AM17: =AK17*AH17 -> 5216
B18: Omeprazole | C18: =RANDBETWEEN(1,10) -> 9 | D18: =RANDBETWEEN(1,10) -> 10 | E18: =RANDBETWEEN(1,10) -> 1 | F18: =RANDBETWEEN(1,10) -> 4 | G18: =RANDBETWEEN(1,10) -> 7 | H18: =RANDBETWEEN(1,10) -> 5 | I18: =RANDBETWEEN(1,10) -> 9 | J18: =RANDBETWEEN(1,10) -> 10 | ... AG18: =RANDBETWEEN(1,10) -> 10 | AH18: =SUM($C18:$AG18) -> 187 | AI18: 138 | AJ18: 150 | AK18: =AJ18-AI18 -> 12 | AL18: =AJ18*AH18 -> 28050 | AM18: =AK18*AH18 -> 2244
B19: Clopidogrel | C19: =RANDBETWEEN(1,10) -> 6 | D19: =RANDBETWEEN(1,10) -> 2 | E19: =RANDBETWEEN(1,10) -> 3 | F19: =RANDBETWEEN(1,10) -> 9 | G19: =RANDBETWEEN(1,10) -> 7 | H19: =RANDBETWEEN(1,10) -> 8 | I19: =RANDBETWEEN(1,10) -> 7 | J19: =RANDBETWEEN(1,10) -> 7 | ... AG19: =RANDBETWEEN(1,10) -> 6 | AH19: =SUM($C19:$AG19) -> 157 | AI19: 60 | AJ19: 80 | AK19: =AJ19-AI19 -> 20 | AL19: =AJ19*AH19 -> 12560 | AM19: =AK19*AH19 -> 3140
B20: Metoprolol | C20: =RANDBETWEEN(1,10) -> 10 | D20: =RANDBETWEEN(1,10) -> 5 | E20: =RANDBETWEEN(1,10) -> 2 | F20: =RANDBETWEEN(1,10) -> 9 | G20: =RANDBETWEEN(1,10) -> 2 | H20: =RANDBETWEEN(1,10) -> 10 | I20: =RANDBETWEEN(1,10) -> 3 | J20: =RANDBETWEEN(1,10) -> 10 | ... AG20: =RANDBETWEEN(1,10) -> 7 | AH20: =SUM($C20:$AG20) -> 181 | AI20: 44 | AJ20: 50 | AK20: =AJ20-AI20 -> 6 | AL20: =AJ20*AH20 -> 9050 | AM20: =AK20*AH20 -> 1086
B21: Amlodipine | C21: =RANDBETWEEN(1,10) -> 8 | D21: =RANDBETWEEN(1,10) -> 9 | E21: =RANDBETWEEN(1,10) -> 1 | F21: =RANDBETWEEN(1,10) -> 1 | G21: =RANDBETWEEN(1,10) -> 7 | H21: =RANDBETWEEN(1,10) -> 5 | I21: =RANDBETWEEN(1,10) -> 7 | J21: =RANDBETWEEN(1,10) -> 9 | ... AG21: =RANDBETWEEN(1,10) -> 4 | AH21: =SUM($C21:$AG21) -> 179 | AI21: 308 | AJ21: 320 | AK21: =AJ21-AI21 -> 12 | AL21: =AJ21*AH21 -> 57280 | AM21: =AK21*AH21 -> 2148
B22: Alprazolam | C22: =RANDBETWEEN(1,10) -> 3 | D22: =RANDBETWEEN(1,10) -> 7 | E22: =RANDBETWEEN(1,10) -> 2 | F22: =RANDBETWEEN(1,10) -> 8 | G22: =RANDBETWEEN(1,10) -> 3 | H22: =RANDBETWEEN(1,10) -> 3 | I22: =RANDBETWEEN(1,10) -> 5 | J22: =RANDBETWEEN(1,10) -> 7 | ... AG22: =RANDBETWEEN(1,10) -> 5 | AH22: =SUM($C22:$AG22) -> 157 | AI22: 234 | AJ22: 250 | AK22: =AJ22-AI22 -> 16 | AL22: =AJ22*AH22 -> 39250 | AM22: =AK22*AH22 -> 2512
B23: Hydrocodone | C23: =RANDBETWEEN(1,10) -> 10 | D23: =RANDBETWEEN(1,10) -> 5 | E23: =RANDBETWEEN(1,10) -> 2 | F23: =RANDBETWEEN(1,10) -> 8 | G23: =RANDBETWEEN(1,10) -> 5 | H23: =RANDBETWEEN(1,10) -> 6 | I23: =RANDBETWEEN(1,10) -> 7 | J23: =RANDBETWEEN(1,10) -> 5 | ... AG23: =RANDBETWEEN(1,10) -> 5 | AH23: =SUM($C23:$AG23) -> 161 | AI23: 121 | AJ23: 140 | AK23: =AJ23-AI23 -> 19 | AL23: =AJ23*AH23 -> 22540 | AM23: =AK23*AH23 -> 3059
B24: Gabapentin | C24: =RANDBETWEEN(1,10) -> 4 | D24: =RANDBETWEEN(1,10) -> 3 | E24: =RANDBETWEEN(1,10) -> 6 | F24: =RANDBETWEEN(1,10) -> 10 | G24: =RANDBETWEEN(1,10) -> 9 | H24: =RANDBETWEEN(1,10) -> 7 | I24: =RANDBETWEEN(1,10) -> 6 | J24: =RANDBETWEEN(1,10) -> 9 | ... AG24: =RANDBETWEEN(1,10) -> 2 | AH24: =SUM($C24:$AG24) -> 159 | AI24: 350 | AJ24: 390 | AK24: =AJ24-AI24 -> 40 | AL24: =AJ24*AH24 -> 62010 | AM24: =AK24*AH24 -> 6360
B25: Levothyroxine | C25: =RANDBETWEEN(1,10) -> 7 | D25: =RANDBETWEEN(1,10) -> 8 | E25: =RANDBETWEEN(1,10) -> 9 | F25: =RANDBETWEEN(1,10) -> 6 | G25: =RANDBETWEEN(1,10) -> 4 | H25: =RANDBETWEEN(1,10) -> 2 | I25: =RANDBETWEEN(1,10) -> 9 | J25: =RANDBETWEEN(1,10) -> 5 | ... AG25: =RANDBETWEEN(1,10) -> 2 | AH25: =SUM($C25:$AG25) -> 191 | AI25: 211 | AJ25: 240 | AK25: =AJ25-AI25 -> 29 | AL25: =AJ25*AH25 -> 45840 | AM25: =AK25*AH25 -> 5539
B26: Sertraline | C26: =RANDBETWEEN(1,10) -> 9 | D26: =RANDBETWEEN(1,10) -> 5 | E26: =RANDBETWEEN(1,10) -> 2 | F26: =RANDBETWEEN(1,10) -> 6 | G26: =RANDBETWEEN(1,10) -> 9 | H26: =RANDBETWEEN(1,10) -> 3 | I26: =RANDBETWEEN(1,10) -> 1 | J26: =RANDBETWEEN(1,10) -> 10 | ... AG26: =RANDBETWEEN(1,10) -> 5 | AH26: =SUM($C26:$AG26) -> 180 | AI26: 247 | AJ26: 280 | AK26: =AJ26-AI26 -> 33 | AL26: =AJ26*AH26 -> 50400 | AM26: =AK26*AH26 -> 5940
B27: Azithromycin | C27: =RANDBETWEEN(1,10) -> 5 | D27: =RANDBETWEEN(1,10) -> 3 | E27: =RANDBETWEEN(1,10) -> 10 | F27: =RANDBETWEEN(1,10) -> 3 | G27: =RANDBETWEEN(1,10) -> 7 | H27: =RANDBETWEEN(1,10) -> 5 | I27: =RANDBETWEEN(1,10) -> 4 | J27: =RANDBETWEEN(1,10) -> 9 | ... AG27: =RANDBETWEEN(1,10) -> 3 | AH27: =SUM($C27:$AG27) -> 159 | AI27: 286 | AJ27: 320 | AK27: =AJ27-AI27 -> 34 | AL27: =AJ27*AH27 -> 50880 | AM27: =AK27*AH27 -> 5406
B28: Losartan | C28: =RANDBETWEEN(1,10) -> 9 | D28: =RANDBETWEEN(1,10) -> 6 | E28: =RANDBETWEEN(1,10) -> 1 | F28: =RANDBETWEEN(1,10) -> 6 | G28: =RANDBETWEEN(1,10) -> 2 | H28: =RANDBETWEEN(1,10) -> 1 | I28: =RANDBETWEEN(1,10) -> 1 | J28: =RANDBETWEEN(1,10) -> 9 | ... AG28: =RANDBETWEEN(1,10) -> 5 | AH28: =SUM($C28:$AG28) -> 161 | AI28: 67 | AJ28: 80 | AK28: =AJ28-AI28 -> 13 | AL28: =AJ28*AH28 -> 12880 | AM28: =AK28*AH28 -> 2093
... B57: Lamotrigine | C57: =RANDBETWEEN(1,10) -> 9 | D57: =RANDBETWEEN(1,10) -> 8 | E57: =RANDBETWEEN(1,10) -> 1 | F57: =RANDBETWEEN(1,10) -> 6 | G57: =RANDBETWEEN(1,10) -> 2 | H57: =RANDBETWEEN(1,10) -> 10 | I57: =RANDBETWEEN(1,10) -> 5 | J57: =RANDBETWEEN(1,10) -> 6 | ... AG57: =RANDBETWEEN(1,10) -> 4 | AH57: =SUM($C57:$AG57) -> 182 | AI57: 340 | AJ57: 380 | AK57: =AJ57-AI57 -> 40 | AL57: =AJ57*AH57 -> 69160 | AM57: =AK57*AH57 -> 7280

Sheet Februray
C1: =TEXT(C2,"DDD") -> Thu | D1: =TEXT(D2,"DDD") -> Fri | E1: =TEXT(E2,"DDD") -> Sat | F1: =TEXT(F2,"DDD") -> Sun | G1: =TEXT(G2,"DDD") -> Mon | H1: =TEXT(H2,"DDD") -> Tue | I1: =TEXT(I2,"DDD") -> Wed | J1: =TEXT(J2,"DDD") -> Thu | ... AG1: =TEXT(AG2,"DDD") | AH1: Total Sales | AI1: Incoming price (Including GST) | AJ1: Sales price | AK1: Profit Margin | AL1: Total collection | AM1: Net collection | AO1: Month | AP1: February
B2: Product Name | C2: =IF(COLUMNS($C$2:C2)>DAY($AP$4),"",$AP$3+COLUMNS($C$2:C2)-1) -> 45323 | D2: =IF(COLUMNS($C$2:D2)>DAY($AP$4),"",$AP$3+COLUMNS($C$2:D2)-1) -> 45324 | E2: =IF(COLUMNS($C$2:E2)>DAY($AP$4),"",$AP$3+COLUMNS($C$2:E2)-1) -> 45325 | F2: =IF(COLUMNS($C$2:F2)>DAY($AP$4),"",$AP$3+COLUMNS($C$2:F2)-1) -> 45326 | G2: =IF(COLUMNS($C$2:G2)>DAY($AP$4),"",$AP$3+COLUMNS($C$2:G2)-1) -> 45327 | H2: =IF(COLUMNS($C$2:H2)>DAY($AP$4),"",$AP$3+COLUMNS($C$2:H2)-1) -> 45328 | I2: =IF(COLUMNS($C$2:I2)>DAY($AP$4),"",$AP$3+COLUMNS($C$2:I2)-1) -> 45329 | J2: =IF(COLUMNS($C$2:J2)>DAY($AP$4),"",$AP$3+COLUMNS($C$2:J2)-1) -> 45330 | ... AG2: =IF(COLUMNS($C$2:AG2)>DAY($AP$4),"",$AP$3+COLUMNS($C$2:AG2)-1) | AO2: Year | AP2: 2024
B3: Iodex | C3: =RANDBETWEEN(1,10) -> 3 | D3: =RANDBETWEEN(1,10) -> 9 | E3: =RANDBETWEEN(1,10) -> 7 | F3: =RANDBETWEEN(1,10) -> 10 | G3: =RANDBETWEEN(1,10) -> 9 | H3: =RANDBETWEEN(1,10) -> 5 | I3: =RANDBETWEEN(1,10) -> 3 | J3: =RANDBETWEEN(1,10) -> 2 | ... AE3: =RANDBETWEEN(1,10) -> 6 | AH3: =SUM($C3:$AG3) -> 177 | AI3: 40 | AJ3: 80 | AK3: =AJ3-AI3 -> 40 | AL3: =AJ3*AH3 -> 14160 | AM3: =AK3*AH3 -> 7080 | AO3: Starting Date | AP3: =DATE(AP2,MONTH(AP1&1),1) -> 45323
B4: Nimocet | C4: =RANDBETWEEN(1,10) -> 3 | D4: =RANDBETWEEN(1,10) -> 4 | E4: =RANDBETWEEN(1,10) -> 8 | F4: =RANDBETWEEN(1,10) -> 8 | G4: =RANDBETWEEN(1,10) -> 4 | H4: =RANDBETWEEN(1,10) -> 8 | I4: =RANDBETWEEN(1,10) -> 4 | J4: =RANDBETWEEN(1,10) -> 8 | ... AE4: =RANDBETWEEN(1,10) -> 6 | AH4: =SUM($C4:$AG4) -> 203 | AI4: 7 | AJ4: 15 | AK4: =AJ4-AI4 -> 8 | AL4: =AJ4*AH4 -> 3045 | AM4: =AK4*AH4 -> 1624 | AO4: Ending Date | AP4: =EOMONTH(AP3,0) -> 45351
B5: Paracetamol | C5: =RANDBETWEEN(1,10) -> 2 | D5: =RANDBETWEEN(1,10) -> 3 | E5: =RANDBETWEEN(1,10) -> 3 | F5: =RANDBETWEEN(1,10) -> 10 | G5: =RANDBETWEEN(1,10) -> 1 | H5: =RANDBETWEEN(1,10) -> 3 | I5: =RANDBETWEEN(1,10) -> 6 | J5: =RANDBETWEEN(1,10) -> 1 | ... AE5: =RANDBETWEEN(1,10) -> 4 | AH5: =SUM($C5:$AG5) -> 161 | AI5: 5 | AJ5: 10 | AK5: =AJ5-AI5 -> 5 | AL5: =AJ5*AH5 -> 1610 | AM5: =AK5*AH5 -> 805
B6: Monocef | C6: =RANDBETWEEN(1,10) -> 5 | D6: =RANDBETWEEN(1,10) -> 2 | E6: =RANDBETWEEN(1,10) -> 1 | F6: =RANDBETWEEN(1,10) -> 3 | G6: =RANDBETWEEN(1,10) -> 3 | H6: =RANDBETWEEN(1,10) -> 5 | I6: =RANDBETWEEN(1,10) -> 8 | J6: =RANDBETWEEN(1,10) -> 6 | ... AE6: =RANDBETWEEN(1,10) -> 9 | AH6: =SUM($C6:$AG6) -> 142 | AI6: 45 | AJ6: 80 | AK6: =AJ6-AI6 -> 35 | AL6: =AJ6*AH6 -> 11360 | AM6: =AK6*AH6 -> 4970
B7: Cyclopalm | C7: =RANDBETWEEN(1,10) -> 3 | D7: =RANDBETWEEN(1,10) -> 2 | E7: =RANDBETWEEN(1,10) -> 6 | F7: =RANDBETWEEN(1,10) -> 3 | G7: =RANDBETWEEN(1,10) -> 4 | H7: =RANDBETWEEN(1,10) -> 6 | I7: =RANDBETWEEN(1,10) -> 6 | J7: =RANDBETWEEN(1,10) -> 5 | ... AE7: =RANDBETWEEN(1,10) -> 4 | AH7: =SUM($C7:$AG7) -> 157 | AI7: 392 | AJ7: 420 | AK7: =AJ7-AI7 -> 28 | AL7: =AJ7*AH7 -> 65940 | AM7: =AK7*AH7 -> 4396 | AO7: Expanses
B8: Cetaphil | C8: =RANDBETWEEN(1,10) -> 3 | D8: =RANDBETWEEN(1,10) -> 10 | E8: =RANDBETWEEN(1,10) -> 10 | F8: =RANDBETWEEN(1,10) -> 4 | G8: =RANDBETWEEN(1,10) -> 2 | H8: =RANDBETWEEN(1,10) -> 9 | I8: =RANDBETWEEN(1,10) -> 8 | J8: =RANDBETWEEN(1,10) -> 4 | ... AE8: =RANDBETWEEN(1,10) -> 8 | AH8: =SUM($C8:$AG8) -> 166 | AI8: 86 | AJ8: 100 | AK8: =AJ8-AI8 -> 14 | AL8: =AJ8*AH8 -> 16600 | AM8: =AK8*AH8 -> 2324 | AO8: Employee Salary
B9: Acetaminophen | C9: =RANDBETWEEN(1,10) -> 1 | D9: =RANDBETWEEN(1,10) -> 10 | E9: =RANDBETWEEN(1,10) -> 9 | F9: =RANDBETWEEN(1,10) -> 9 | G9: =RANDBETWEEN(1,10) -> 9 | H9: =RANDBETWEEN(1,10) -> 3 | I9: =RANDBETWEEN(1,10) -> 4 | J9: =RANDBETWEEN(1,10) -> 1 | ... AE9: =RANDBETWEEN(1,10) -> 10 | AH9: =SUM($C9:$AG9) -> 178 | AI9: 271 | AJ9: 300 | AK9: =AJ9-AI9 -> 29 | AL9: =AJ9*AH9 -> 53400 | AM9: =AK9*AH9 -> 5162 | AO9: Kaishav(Owner) | AP9: ='Attendence (Feb)'!AL3 -> 46666.667
B10: Ibuprofen | C10: =RANDBETWEEN(1,10) -> 9 | D10: =RANDBETWEEN(1,10) -> 10 | E10: =RANDBETWEEN(1,10) -> 1 | F10: =RANDBETWEEN(1,10) -> 10 | G10: =RANDBETWEEN(1,10) -> 2 | H10: =RANDBETWEEN(1,10) -> 1 | I10: =RANDBETWEEN(1,10) -> 9 | J10: =RANDBETWEEN(1,10) -> 5 | ... AE10: =RANDBETWEEN(1,10) -> 5 | AH10: =SUM($C10:$AG10) -> 159 | AI10: 226 | AJ10: 250 | AK10: =AJ10-AI10 -> 24 | AL10: =AJ10*AH10 -> 39750 | AM10: =AK10*AH10 -> 3816 | AO10: Raman | AP10: ='Attendence (Feb)'!AL4 -> 13500
B11: Aspirin | C11: =RANDBETWEEN(1,10) -> 8 | D11: =RANDBETWEEN(1,10) -> 2 | E11: =RANDBETWEEN(1,10) -> 10 | F11: =RANDBETWEEN(1,10) -> 1 | G11: =RANDBETWEEN(1,10) -> 2 | H11: =RANDBETWEEN(1,10) -> 3 | I11: =RANDBETWEEN(1,10) -> 9 | J11: =RANDBETWEEN(1,10) -> 9 | ... AE11: =RANDBETWEEN(1,10) -> 5 | AH11: =SUM($C11:$AG11) -> 152 | AI11: 390 | AJ11: 450 | AK11: =AJ11-AI11 -> 60 | AL11: =AJ11*AH11 -> 68400 | AM11: =AK11*AH11 -> 9120 | AO11: Sohan | AP11: ='Attendence (Feb)'!AL5 -> 16800
B12: Amoxicillin | C12: =RANDBETWEEN(1,10) -> 8 | D12: =RANDBETWEEN(1,10) -> 4 | E12: =RANDBETWEEN(1,10) -> 8 | F12: =RANDBETWEEN(1,10) -> 1 | G12: =RANDBETWEEN(1,10) -> 10 | H12: =RANDBETWEEN(1,10) -> 4 | I12: =RANDBETWEEN(1,10) -> 8 | J12: =RANDBETWEEN(1,10) -> 7 | ... AE12: =RANDBETWEEN(1,10) -> 4 | AH12: =SUM($C12:$AG12) -> 155 | AI12: 379 | AJ12: 430 | AK12: =AJ12-AI12 -> 51 | AL12: =AJ12*AH12 -> 66650 | AM12: =AK12*AH12 -> 7905 | AO12: Tilak | AP12: ='Attendence (Feb)'!AL6 -> 9000
B13: Ciprofloxacin | C13: =RANDBETWEEN(1,10) -> 5 | D13: =RANDBETWEEN(1,10) -> 9 | E13: =RANDBETWEEN(1,10) -> 9 | F13: =RANDBETWEEN(1,10) -> 8 | G13: =RANDBETWEEN(1,10) -> 4 | H13: =RANDBETWEEN(1,10) -> 9 | I13: =RANDBETWEEN(1,10) -> 10 | J13: =RANDBETWEEN(1,10) -> 1 | ... AE13: =RANDBETWEEN(1,10) -> 3 | AH13: =SUM($C13:$AG13) -> 180 | AI13: 368 | AJ13: 435 | AK13: =AJ13-AI13 -> 67 | AL13: =AJ13*AH13 -> 78300 | AM13: =AK13*AH13 -> 12060 | AO13: Bill to pay | AP13: 10000
B14: Lisinopril | C14: =RANDBETWEEN(1,10) -> 9 | D14: =RANDBETWEEN(1,10) -> 2 | E14: =RANDBETWEEN(1,10) -> 3 | F14: =RANDBETWEEN(1,10) -> 4 | G14: =RANDBETWEEN(1,10) -> 1 | H14: =RANDBETWEEN(1,10) -> 1 | I14: =RANDBETWEEN(1,10) -> 9 | J14: =RANDBETWEEN(1,10) -> 4 | ... AE14: =RANDBETWEEN(1,10) -> 10 | AH14: =SUM($C14:$AG14) -> 156 | AI14: 88 | AJ14: 99 | AK14: =AJ14-AI14 -> 11 | AL14: =AJ14*AH14 -> 15444 | AM14: =AK14*AH14 -> 1716 | AO14: other | AP14: 2000
B15: Atorvastatin | C15: =RANDBETWEEN(1,10) -> 9 | D15: =RANDBETWEEN(1,10) -> 8 | E15: =RANDBETWEEN(1,10) -> 9 | F15: =RANDBETWEEN(1,10) -> 7 | G15: =RANDBETWEEN(1,10) -> 3 | H15: =RANDBETWEEN(1,10) -> 1 | I15: =RANDBETWEEN(1,10) -> 4 | J15: =RANDBETWEEN(1,10) -> 5 | ... AE15: =RANDBETWEEN(1,10) -> 4 | AH15: =SUM($C15:$AG15) -> 157 | AI15: 391 | AJ15: 500 | AK15: =AJ15-AI15 -> 109 | AL15: =AJ15*AH15 -> 78500 | AM15: =AK15*AH15 -> 17113 | AO15: Net collection | AP15: =SUM(AM3:AM57) -> 280433
B16: Metformin | C16: =RANDBETWEEN(1,10) -> 7 | D16: =RANDBETWEEN(1,10) -> 5 | E16: =RANDBETWEEN(1,10) -> 1 | F16: =RANDBETWEEN(1,10) -> 6 | G16: =RANDBETWEEN(1,10) -> 7 | H16: =RANDBETWEEN(1,10) -> 8 | I16: =RANDBETWEEN(1,10) -> 8 | J16: =RANDBETWEEN(1,10) -> 9 | ... AE16: =RANDBETWEEN(1,10) -> 9 | AH16: =SUM($C16:$AG16) -> 147 | AI16: 261 | AJ16: 300 | AK16: =AJ16-AI16 -> 39 | AL16: =AJ16*AH16 -> 44100 | AM16: =AK16*AH16 -> 5733 | AO16: Net Income | AP16: =AP15-(AP9+AP10+AP11+AP12+AP13+AP14) -> 182466.33
B17: Simvastatin | C17: =RANDBETWEEN(1,10) -> 3 | D17: =RANDBETWEEN(1,10) -> 3 | E17: =RANDBETWEEN(1,10) -> 5 | F17: =RANDBETWEEN(1,10) -> 1 | G17: =RANDBETWEEN(1,10) -> 3 | H17: =RANDBETWEEN(1,10) -> 3 | I17: =RANDBETWEEN(1,10) -> 1 | J17: =RANDBETWEEN(1,10) -> 7 | ... AE17: =RANDBETWEEN(1,10) -> 1 | AH17: =SUM($C17:$AG17) -> 148 | AI17: 67 | AJ17: 99 | AK17: =AJ17-AI17 -> 32 | AL17: =AJ17*AH17 -> 14652 | AM17: =AK17*AH17 -> 4736
B18: Omeprazole | C18: =RANDBETWEEN(1,10) -> 3 | D18: =RANDBETWEEN(1,10) -> 2 | E18: =RANDBETWEEN(1,10) -> 2 | F18: =RANDBETWEEN(1,10) -> 3 | G18: =RANDBETWEEN(1,10) -> 1 | H18: =RANDBETWEEN(1,10) -> 10 | I18: =RANDBETWEEN(1,10) -> 3 | J18: =RANDBETWEEN(1,10) -> 4 | ... AE18: =RANDBETWEEN(1,10) -> 3 | AH18: =SUM($C18:$AG18) -> 140 | AI18: 138 | AJ18: 150 | AK18: =AJ18-AI18 -> 12 | AL18: =AJ18*AH18 -> 21000 | AM18: =AK18*AH18 -> 1680
B19: Clopidogrel | C19: =RANDBETWEEN(1,10) -> 4 | D19: =RANDBETWEEN(1,10) -> 8 | E19: =RANDBETWEEN(1,10) -> 5 | F19: =RANDBETWEEN(1,10) -> 7 | G19: =RANDBETWEEN(1,10) -> 3 | H19: =RANDBETWEEN(1,10) -> 9 | I19: =RANDBETWEEN(1,10) -> 9 | J19: =RANDBETWEEN(1,10) -> 3 | ... AE19: =RANDBETWEEN(1,10) -> 9 | AH19: =SUM($C19:$AG19) -> 176 | AI19: 60 | AJ19: 80 | AK19: =AJ19-AI19 -> 20 | AL19: =AJ19*AH19 -> 14080 | AM19: =AK19*AH19 -> 3520
B20: Metoprolol | C20: =RANDBETWEEN(1,10) -> 10 | D20: =RANDBETWEEN(1,10) -> 4 | E20: =RANDBETWEEN(1,10) -> 5 | F20: =RANDBETWEEN(1,10) -> 1 | G20: =RANDBETWEEN(1,10) -> 8 | H20: =RANDBETWEEN(1,10) -> 10 | I20: =RANDBETWEEN(1,10) -> 1 | J20: =RANDBETWEEN(1,10) -> 8 | ... AE20: =RANDBETWEEN(1,10) -> 6 | AH20: =SUM($C20:$AG20) -> 167 | AI20: 44 | AJ20: 50 | AK20: =AJ20-AI20 -> 6 | AL20: =AJ20*AH20 -> 8350 | AM20: =AK20*AH20 -> 1002
B21: Amlodipine | C21: =RANDBETWEEN(1,10) -> 9 | D21: =RANDBETWEEN(1,10) -> 6 | E21: =RANDBETWEEN(1,10) -> 2 | F21: =RANDBETWEEN(1,10) -> 3 | G21: =RANDBETWEEN(1,10) -> 4 | H21: =RANDBETWEEN(1,10) -> 1 | I21: =RANDBETWEEN(1,10) -> 7 | J21: =RANDBETWEEN(1,10) -> 5 | ... AE21: =RANDBETWEEN(1,10) -> 3 | AH21: =SUM($C21:$AG21) -> 147 | AI21: 308 | AJ21: 320 | AK21: =AJ21-AI21 -> 12 | AL21: =AJ21*AH21 -> 47040 | AM21: =AK21*AH21 -> 1764
B22: Alprazolam | C22: =RANDBETWEEN(1,10) -> 7 | D22: =RANDBETWEEN(1,10) -> 5 | E22: =RANDBETWEEN(1,10) -> 9 | F22: =RANDBETWEEN(1,10) -> 2 | G22: =RANDBETWEEN(1,10) -> 6 | H22: =RANDBETWEEN(1,10) -> 2 | I22: =RANDBETWEEN(1,10) -> 5 | J22: =RANDBETWEEN(1,10) -> 9 | ... AE22: =RANDBETWEEN(1,10) -> 5 | AH22: =SUM($C22:$AG22) -> 174 | AI22: 234 | AJ22: 250 | AK22: =AJ22-AI22 -> 16 | AL22: =AJ22*AH22 -> 43500 | AM22: =AK22*AH22 -> 2784
B23: Hydrocodone | C23: =RANDBETWEEN(1,10) -> 8 | D23: =RANDBETWEEN(1,10) -> 5 | E23: =RANDBETWEEN(1,10) -> 2 | F23: =RANDBETWEEN(1,10) -> 10 | G23: =RANDBETWEEN(1,10) -> 6 | H23: =RANDBETWEEN(1,10) -> 3 | I23: =RANDBETWEEN(1,10) -> 2 | J23: =RANDBETWEEN(1,10) -> 5 | ... AE23: =RANDBETWEEN(1,10) -> 9 | AH23: =SUM($C23:$AG23) -> 161 | AI23: 121 | AJ23: 140 | AK23: =AJ23-AI23 -> 19 | AL23: =AJ23*AH23 -> 22540 | AM23: =AK23*AH23 -> 3059
B24: Gabapentin | C24: =RANDBETWEEN(1,10) -> 2 | D24: =RANDBETWEEN(1,10) -> 7 | E24: =RANDBETWEEN(1,10) -> 8 | F24: =RANDBETWEEN(1,10) -> 7 | G24: =RANDBETWEEN(1,10) -> 9 | H24: =RANDBETWEEN(1,10) -> 9 | I24: =RANDBETWEEN(1,10) -> 1 | J24: =RANDBETWEEN(1,10) -> 4 | ... AE24: =RANDBETWEEN(1,10) -> 1 | AH24: =SUM($C24:$AG24) -> 124 | AI24: 350 | AJ24: 390 | AK24: =AJ24-AI24 -> 40 | AL24: =AJ24*AH24 -> 48360 | AM24: =AK24*AH24 -> 4960
B25: Levothyroxine | C25: =RANDBETWEEN(1,10) -> 8 | D25: =RANDBETWEEN(1,10) -> 8 | E25: =RANDBETWEEN(1,10) -> 6 | F25: =RANDBETWEEN(1,10) -> 2 | G25: =RANDBETWEEN(1,10) -> 5 | H25: =RANDBETWEEN(1,10) -> 2 | I25: =RANDBETWEEN(1,10) -> 5 | J25: =RANDBETWEEN(1,10) -> 2 | ... AE25: =RANDBETWEEN(1,10) -> 5 | AH25: =SUM($C25:$AG25) -> 160 | AI25: 211 | AJ25: 240 | AK25: =AJ25-AI25 -> 29 | AL25: =AJ25*AH25 -> 38400 | AM25: =AK25*AH25 -> 4640
B26: Sertraline | C26: =RANDBETWEEN(1,10) -> 4 | D26: =RANDBETWEEN(1,10) -> 1 | E26: =RANDBETWEEN(1,10) -> 9 | F26: =RANDBETWEEN(1,10) -> 9 | G26: =RANDBETWEEN(1,10) -> 5 | H26: =RANDBETWEEN(1,10) -> 10 | I26: =RANDBETWEEN(1,10) -> 2 | J26: =RANDBETWEEN(1,10) -> 9 | ... AE26: =RANDBETWEEN(1,10) -> 2 | AH26: =SUM($C26:$AG26) -> 159 | AI26: 247 | AJ26: 280 | AK26: =AJ26-AI26 -> 33 | AL26: =AJ26*AH26 -> 44520 | AM26: =AK26*AH26 -> 5247
B27: Azithromycin | C27: =RANDBETWEEN(1,10) -> 4 | D27: =RANDBETWEEN(1,10) -> 2 | E27: =RANDBETWEEN(1,10) -> 7 | F27: =RANDBETWEEN(1,10) -> 4 | G27: =RANDBETWEEN(1,10) -> 5 | H27: =RANDBETWEEN(1,10) -> 10 | I27: =RANDBETWEEN(1,10) -> 3 | J27: =RANDBETWEEN(1,10) -> 2 | ... AE27: =RANDBETWEEN(1,10) -> 10 | AH27: =SUM($C27:$AG27) -> 179 | AI27: 286 | AJ27: 320 | AK27: =AJ27-AI27 -> 34 | AL27: =AJ27*AH27 -> 57280 | AM27: =AK27*AH27 -> 6086
B28: Losartan | C28: =RANDBETWEEN(1,10) -> 4 | D28: =RANDBETWEEN(1,10) -> 1 | E28: =RANDBETWEEN(1,10) -> 7 | F28: =RANDBETWEEN(1,10) -> 7 | G28: =RANDBETWEEN(1,10) -> 1 | H28: =RANDBETWEEN(1,10) -> 6 | I28: =RANDBETWEEN(1,10) -> 8 | J28: =RANDBETWEEN(1,10) -> 7 | ... AE28: =RANDBETWEEN(1,10) -> 9 | AH28: =SUM($C28:$AG28) -> 178 | AI28: 67 | AJ28: 80 | AK28: =AJ28-AI28 -> 13 | AL28: =AJ28*AH28 -> 14240 | AM28: =AK28*AH28 -> 2314
... B57: Lamotrigine | C57: =RANDBETWEEN(1,10) -> 8 | D57: =RANDBETWEEN(1,10) -> 1 | E57: =RANDBETWEEN(1,10) -> 3 | F57: =RANDBETWEEN(1,10) -> 6 | G57: =RANDBETWEEN(1,10) -> 4 | H57: =RANDBETWEEN(1,10) -> 3 | I57: =RANDBETWEEN(1,10) -> 4 | J57: =RANDBETWEEN(1,10) -> 4 | ... AE57: =RANDBETWEEN(1,10) -> 4 | AH57: =SUM($C57:$AG57) -> 121 | AI57: 340 | AJ57: 380 | AK57: =AJ57-AI57 -> 40 | AL57: =AJ57*AH57 -> 45980 | AM57: =AK57*AH57 -> 4840

Sheet March
C1: =TEXT(C2,"DDD") -> Fri | D1: =TEXT(D2,"DDD") -> Sat | E1: =TEXT(E2,"DDD") -> Sun | F1: =TEXT(F2,"DDD") -> Mon | G1: =TEXT(G2,"DDD") -> Tue | H1: =TEXT(H2,"DDD") -> Wed | I1: =TEXT(I2,"DDD") -> Thu | J1: =TEXT(J2,"DDD") -> Fri | ... AG1: =TEXT(AG2,"DDD") -> Sun | AH1: Total Sales | AI1: Incoming price (Including GST) | AJ1: Sales price | AK1: Profit Margin | AL1: Total collection | AM1: Net collection | AO1: Month | AP1: March
B2: Product Name | C2: =IF(COLUMNS($C$2:C2)>DAY($AP$4),"",$AP$3+COLUMNS($C$2:C2)-1) -> 45352 | D2: =IF(COLUMNS($C$2:D2)>DAY($AP$4),"",$AP$3+COLUMNS($C$2:D2)-1) -> 45353 | E2: =IF(COLUMNS($C$2:E2)>DAY($AP$4),"",$AP$3+COLUMNS($C$2:E2)-1) -> 45354 | F2: =IF(COLUMNS($C$2:F2)>DAY($AP$4),"",$AP$3+COLUMNS($C$2:F2)-1) -> 45355 | G2: =IF(COLUMNS($C$2:G2)>DAY($AP$4),"",$AP$3+COLUMNS($C$2:G2)-1) -> 45356 | H2: =IF(COLUMNS($C$2:H2)>DAY($AP$4),"",$AP$3+COLUMNS($C$2:H2)-1) -> 45357 | I2: =IF(COLUMNS($C$2:I2)>DAY($AP$4),"",$AP$3+COLUMNS($C$2:I2)-1) -> 45358 | J2: =IF(COLUMNS($C$2:J2)>DAY($AP$4),"",$AP$3+COLUMNS($C$2:J2)-1) -> 45359 | ... AG2: =IF(COLUMNS($C$2:AG2)>DAY($AP$4),"",$AP$3+COLUMNS($C$2:AG2)-1) -> 45382 | AO2: Year | AP2: 2024
B3: Iodex | C3: =RANDBETWEEN(1,10) -> 3 | D3: =RANDBETWEEN(1,10) -> 3 | E3: =RANDBETWEEN(1,10) -> 1 | F3: =RANDBETWEEN(1,10) -> 1 | G3: =RANDBETWEEN(1,10) -> 5 | H3: =RANDBETWEEN(1,10) -> 7 | I3: =RANDBETWEEN(1,10) -> 7 | J3: =RANDBETWEEN(1,10) -> 10 | ... AG3: =RANDBETWEEN(1,10) -> 6 | AH3: =IF(SUM($C3:$AG3)>0,SUM($C3:$AG3),"") -> 166 | AI3: 40 | AJ3: 80 | AK3: =AJ3-AI3 -> 40 | AL3: =AJ3*AH3 -> 13280 | AM3: =AK3*AH3 -> 6640 | AO3: Starting Date | AP3: =DATE(AP2,MONTH(AP1&1),1) -> 45352
B4: Nimocet | C4: =RANDBETWEEN(1,10) -> 5 | D4: =RANDBETWEEN(1,10) -> 2 | E4: =RANDBETWEEN(1,10) -> 3 | F4: =RANDBETWEEN(1,10) -> 3 | G4: =RANDBETWEEN(1,10) -> 1 | H4: =RANDBETWEEN(1,10) -> 6 | I4: =RANDBETWEEN(1,10) -> 9 | J4: =RANDBETWEEN(1,10) -> 6 | ... AG4: =RANDBETWEEN(1,10) -> 4 | AH4: =IF(SUM($C4:$AG4)>0,SUM($C4:$AG4),"") -> 163 | AI4: 7 | AJ4: 15 | AK4: =AJ4-AI4 -> 8 | AL4: =AJ4*AH4 -> 2445 | AM4: =AK4*AH4 -> 1304 | AO4: Ending Date | AP4: =EOMONTH(AP3,0) -> 45382
B5: Paracetamol | C5: =RANDBETWEEN(1,10) -> 3 | D5: =RANDBETWEEN(1,10) -> 9 | E5: =RANDBETWEEN(1,10) -> 3 | F5: =RANDBETWEEN(1,10) -> 10 | G5: =RANDBETWEEN(1,10) -> 3 | H5: =RANDBETWEEN(1,10) -> 7 | I5: =RANDBETWEEN(1,10) -> 4 | J5: =RANDBETWEEN(1,10) -> 9 | ... AG5: =RANDBETWEEN(1,10) -> 9 | AH5: =IF(SUM($C5:$AG5)>0,SUM($C5:$AG5),"") -> 182 | AI5: 5 | AJ5: 10 | AK5: =AJ5-AI5 -> 5 | AL5: =AJ5*AH5 -> 1820 | AM5: =AK5*AH5 -> 910
B6: Monocef | C6: =RANDBETWEEN(1,10) -> 3 | D6: =RANDBETWEEN(1,10) -> 2 | E6: =RANDBETWEEN(1,10) -> 10 | F6: =RANDBETWEEN(1,10) -> 9 | G6: =RANDBETWEEN(1,10) -> 9 | H6: =RANDBETWEEN(1,10) -> 9 | I6: =RANDBETWEEN(1,10) -> 1 | J6: =RANDBETWEEN(1,10) -> 9 | ... AG6: =RANDBETWEEN(1,10) -> 4 | AH6: =IF(SUM($C6:$AG6)>0,SUM($C6:$AG6),"") -> 182 | AI6: 45 | AJ6: 80 | AK6: =AJ6-AI6 -> 35 | AL6: =AJ6*AH6 -> 14560 | AM6: =AK6*AH6 -> 6370
B7: Cyclopalm | C7: =RANDBETWEEN(1,10) -> 4 | D7: =RANDBETWEEN(1,10) -> 5 | E7: =RANDBETWEEN(1,10) -> 10 | F7: =RANDBETWEEN(1,10) -> 6 | G7: =RANDBETWEEN(1,10) -> 3 | H7: =RANDBETWEEN(1,10) -> 2 | I7: =RANDBETWEEN(1,10) -> 5 | J7: =RANDBETWEEN(1,10) -> 2 | ... AG7: =RANDBETWEEN(1,10) -> 1 | AH7: =IF(SUM($C7:$AG7)>0,SUM($C7:$AG7),"") -> 181 | AI7: 392 | AJ7: 420 | AK7: =AJ7-AI7 -> 28 | AL7: =AJ7*AH7 -> 76020 | AM7: =AK7*AH7 -> 5068 | AO7: Expanses
B8: Cetaphil | C8: =RANDBETWEEN(1,10) -> 9 | D8: =RANDBETWEEN(1,10) -> 6 | E8: =RANDBETWEEN(1,10) -> 8 | F8: =RANDBETWEEN(1,10) -> 6 | G8: =RANDBETWEEN(1,10) -> 5 | H8: =RANDBETWEEN(1,10) -> 9 | I8: =RANDBETWEEN(1,10) -> 5 | J8: =RANDBETWEEN(1,10) -> 6 | ... AG8: =RANDBETWEEN(1,10) -> 3 | AH8: =IF(SUM($C8:$AG8)>0,SUM($C8:$AG8),"") -> 166 | AI8: 86 | AJ8: 100 | AK8: =AJ8-AI8 -> 14 | AL8: =AJ8*AH8 -> 16600 | AM8: =AK8*AH8 -> 2324 | AO8: Employee Salary
B9: Acetaminophen | C9: =RANDBETWEEN(1,10) -> 7 | D9: =RANDBETWEEN(1,10) -> 9 | E9: =RANDBETWEEN(1,10) -> 7 | F9: =RANDBETWEEN(1,10) -> 1 | G9: =RANDBETWEEN(1,10) -> 9 | H9: =RANDBETWEEN(1,10) -> 4 | I9: =RANDBETWEEN(1,10) -> 7 | J9: =RANDBETWEEN(1,10) -> 10 | ... AG9: =RANDBETWEEN(1,10) -> 3 | AH9: =IF(SUM($C9:$AG9)>0,SUM($C9:$AG9),"") -> 170 | AI9: 271 | AJ9: 300 | AK9: =AJ9-AI9 -> 29 | AL9: =AJ9*AH9 -> 51000 | AM9: =AK9*AH9 -> 4930 | AO9: Kaishav(Owner) | AP9: ='Attendence (March)'!AL3 -> 48333.333
B10: Ibuprofen | C10: =RANDBETWEEN(1,10) -> 1 | D10: =RANDBETWEEN(1,10) -> 3 | E10: =RANDBETWEEN(1,10) -> 9 | F10: =RANDBETWEEN(1,10) -> 1 | G10: =RANDBETWEEN(1,10) -> 1 | H10: =RANDBETWEEN(1,10) -> 5 | I10: =RANDBETWEEN(1,10) -> 2 | J10: =RANDBETWEEN(1,10) -> 2 | ... AG10: =RANDBETWEEN(1,10) -> 9 | AH10: =IF(SUM($C10:$AG10)>0,SUM($C10:$AG10),"") -> 177 | AI10: 226 | AJ10: 250 | AK10: =AJ10-AI10 -> 24 | AL10: =AJ10*AH10 -> 44250 | AM10: =AK10*AH10 -> 4248 | AO10: Raman | AP10: ='Attendence (March)'!AL4 -> 14000
B11: Aspirin | C11: =RANDBETWEEN(1,10) -> 1 | D11: =RANDBETWEEN(1,10) -> 5 | E11: =RANDBETWEEN(1,10) -> 10 | F11: =RANDBETWEEN(1,10) -> 7 | G11: =RANDBETWEEN(1,10) -> 8 | H11: =RANDBETWEEN(1,10) -> 1 | I11: =RANDBETWEEN(1,10) -> 6 | J11: =RANDBETWEEN(1,10) -> 6 | ... AG11: =RANDBETWEEN(1,10) -> 1 | AH11: =IF(SUM($C11:$AG11)>0,SUM($C11:$AG11),"") -> 179 | AI11: 390 | AJ11: 450 | AK11: =AJ11-AI11 -> 60 | AL11: =AJ11*AH11 -> 80550 | AM11: =AK11*AH11 -> 10740 | AO11: Sohan | AP11: ='Attendence (March)'!AL5 -> 18000
B12: Amoxicillin | C12: =RANDBETWEEN(1,10) -> 6 | D12: =RANDBETWEEN(1,10) -> 5 | E12: =RANDBETWEEN(1,10) -> 3 | F12: =RANDBETWEEN(1,10) -> 3 | G12: =RANDBETWEEN(1,10) -> 8 | H12: =RANDBETWEEN(1,10) -> 6 | I12: =RANDBETWEEN(1,10) -> 7 | J12: =RANDBETWEEN(1,10) -> 9 | ... AG12: =RANDBETWEEN(1,10) -> 3 | AH12: =IF(SUM($C12:$AG12)>0,SUM($C12:$AG12),"") -> 183 | AI12: 379 | AJ12: 430 | AK12: =AJ12-AI12 -> 51 | AL12: =AJ12*AH12 -> 78690 | AM12: =AK12*AH12 -> 9333 | AO12: Tilak | AP12: ='Attendence (March)'!AL6 -> 9666.6667
B13: Ciprofloxacin | C13: =RANDBETWEEN(1,10) -> 10 | D13: =RANDBETWEEN(1,10) -> 8 | E13: =RANDBETWEEN(1,10) -> 1 | F13: =RANDBETWEEN(1,10) -> 6 | G13: =RANDBETWEEN(1,10) -> 10 | H13: =RANDBETWEEN(1,10) -> 6 | I13: =RANDBETWEEN(1,10) -> 4 | J13: =RANDBETWEEN(1,10) -> 4 | ... AG13: =RANDBETWEEN(1,10) -> 9 | AH13: =IF(SUM($C13:$AG13)>0,SUM($C13:$AG13),"") -> 183 | AI13: 368 | AJ13: 435 | AK13: =AJ13-AI13 -> 67 | AL13: =AJ13*AH13 -> 79605 | AM13: =AK13*AH13 -> 12261 | AO13: Bill to pay | AP13: 10000
B14: Lisinopril | C14: =RANDBETWEEN(1,10) -> 10 | D14: =RANDBETWEEN(1,10) -> 2 | E14: =RANDBETWEEN(1,10) -> 1 | F14: =RANDBETWEEN(1,10) -> 4 | G14: =RANDBETWEEN(1,10) -> 2 | H14: =RANDBETWEEN(1,10) -> 4 | I14: =RANDBETWEEN(1,10) -> 2 | J14: =RANDBETWEEN(1,10) -> 10 | ... AG14: =RANDBETWEEN(1,10) -> 10 | AH14: =IF(SUM($C14:$AG14)>0,SUM($C14:$AG14),"") -> 166 | AI14: 88 | AJ14: 99 | AK14: =AJ14-AI14 -> 11 | AL14: =AJ14*AH14 -> 16434 | AM14: =AK14*AH14 -> 1826 | AO14: other | AP14: 2000
B15: Atorvastatin | C15: =RANDBETWEEN(1,10) -> 1 | D15: =RANDBETWEEN(1,10) -> 6 | E15: =RANDBETWEEN(1,10) -> 8 | F15: =RANDBETWEEN(1,10) -> 4 | G15: =RANDBETWEEN(1,10) -> 6 | H15: =RANDBETWEEN(1,10) -> 6 | I15: =RANDBETWEEN(1,10) -> 2 | J15: =RANDBETWEEN(1,10) -> 5 | ... AG15: =RANDBETWEEN(1,10) -> 4 | AH15: =IF(SUM($C15:$AG15)>0,SUM($C15:$AG15),"") -> 165 | AI15: 391 | AJ15: 500 | AK15: =AJ15-AI15 -> 109 | AL15: =AJ15*AH15 -> 82500 | AM15: =AK15*AH15 -> 17985 | AO15: Net collection | AP15: =SUM(AM3:AM57) -> 295515
B16: Metformin | C16: =RANDBETWEEN(1,10) -> 9 | D16: =RANDBETWEEN(1,10) -> 8 | E16: =RANDBETWEEN(1,10) -> 10 | F16: =RANDBETWEEN(1,10) -> 8 | G16: =RANDBETWEEN(1,10) -> 3 | H16: =RANDBETWEEN(1,10) -> 3 | I16: =RANDBETWEEN(1,10) -> 2 | J16: =RANDBETWEEN(1,10) -> 7 | ... AG16: =RANDBETWEEN(1,10) -> 1 | AH16: =IF(SUM($C16:$AG16)>0,SUM($C16:$AG16),"") -> 159 | AI16: 261 | AJ16: 300 | AK16: =AJ16-AI16 -> 39 | AL16: =AJ16*AH16 -> 47700 | AM16: =AK16*AH16 -> 6201 | AO16: Net Income | AP16: =AP15-(AP9+AP10+AP11+AP12+AP13+AP14) -> 193515
B17: Simvastatin | C17: =RANDBETWEEN(1,10) -> 3 | D17: =RANDBETWEEN(1,10) -> 8 | E17: =RANDBETWEEN(1,10) -> 6 | F17: =RANDBETWEEN(1,10) -> 6 | G17: =RANDBETWEEN(1,10) -> 6 | H17: =RANDBETWEEN(1,10) -> 1 | I17: =RANDBETWEEN(1,10) -> 2 | J17: =RANDBETWEEN(1,10) -> 4 | ... AG17: =RANDBETWEEN(1,10) -> 5 | AH17: =IF(SUM($C17:$AG17)>0,SUM($C17:$AG17),"") -> 175 | AI17: 67 | AJ17: 99 | AK17: =AJ17-AI17 -> 32 | AL17: =AJ17*AH17 -> 17325 | AM17: =AK17*AH17 -> 5600
B18: Omeprazole | C18: =RANDBETWEEN(1,10) -> 1 | D18: =RANDBETWEEN(1,10) -> 10 | E18: =RANDBETWEEN(1,10) -> 9 | F18: =RANDBETWEEN(1,10) -> 8 | G18: =RANDBETWEEN(1,10) -> 6 | H18: =RANDBETWEEN(1,10) -> 5 | I18: =RANDBETWEEN(1,10) -> 1 | J18: =RANDBETWEEN(1,10) -> 9 | ... AG18: =RANDBETWEEN(1,10) -> 2 | AH18: =IF(SUM($C18:$AG18)>0,SUM($C18:$AG18),"") -> 156 | AI18: 138 | AJ18: 150 | AK18: =AJ18-AI18 -> 12 | AL18: =AJ18*AH18 -> 23400 | AM18: =AK18*AH18 -> 1872
B19: Clopidogrel | C19: =RANDBETWEEN(1,10) -> 8 | D19: =RANDBETWEEN(1,10) -> 10 | E19: =RANDBETWEEN(1,10) -> 8 | F19: =RANDBETWEEN(1,10) -> 9 | G19: =RANDBETWEEN(1,10) -> 7 | H19: =RANDBETWEEN(1,10) -> 7 | I19: =RANDBETWEEN(1,10) -> 10 | J19: =RANDBETWEEN(1,10) -> 6 | ... AG19: =RANDBETWEEN(1,10) -> 5 | AH19: =IF(SUM($C19:$AG19)>0,SUM($C19:$AG19),"") -> 182 | AI19: 60 | AJ19: 80 | AK19: =AJ19-AI19 -> 20 | AL19: =AJ19*AH19 -> 14560 | AM19: =AK19*AH19 -> 3640
B20: Metoprolol | C20: =RANDBETWEEN(1,10) -> 8 | D20: =RANDBETWEEN(1,10) -> 6 | E20: =RANDBETWEEN(1,10) -> 4 | F20: =RANDBETWEEN(1,10) -> 7 | G20: =RANDBETWEEN(1,10) -> 1 | H20: =RANDBETWEEN(1,10) -> 7 | I20: =RANDBETWEEN(1,10) -> 1 | J20: =RANDBETWEEN(1,10) -> 9 | ... AG20: =RANDBETWEEN(1,10) -> 2 | AH20: =IF(SUM($C20:$AG20)>0,SUM($C20:$AG20),"") -> 144 | AI20: 44 | AJ20: 50 | AK20: =AJ20-AI20 -> 6 | AL20: =AJ20*AH20 -> 7200 | AM20: =AK20*AH20 -> 864
B21: Amlodipine | C21: =RANDBETWEEN(1,10) -> 6 | D21: =RANDBETWEEN(1,10) -> 5 | E21: =RANDBETWEEN(1,10) -> 3 | F21: =RANDBETWEEN(1,10) -> 3 | G21: =RANDBETWEEN(1,10) -> 5 | H21: =RANDBETWEEN(1,10) -> 4 | I21: =RANDBETWEEN(1,10) -> 2 | J21: =RANDBETWEEN(1,10) -> 4 | ... AG21: =RANDBETWEEN(1,10) -> 5 | AH21: =IF(SUM($C21:$AG21)>0,SUM($C21:$AG21),"") -> 139 | AI21: 308 | AJ21: 320 | AK21: =AJ21-AI21 -> 12 | AL21: =AJ21*AH21 -> 44480 | AM21: =AK21*AH21 -> 1668
B22: Alprazolam | C22: =RANDBETWEEN(1,10) -> 7 | D22: =RANDBETWEEN(1,10) -> 7 | E22: =RANDBETWEEN(1,10) -> 5 | F22: =RANDBETWEEN(1,10) -> 10 | G22: =RANDBETWEEN(1,10) -> 5 | H22: =RANDBETWEEN(1,10) -> 6 | I22: =RANDBETWEEN(1,10) -> 3 | J22: =RANDBETWEEN(1,10) -> 6 | ... AG22: =RANDBETWEEN(1,10) -> 9 | AH22: =IF(SUM($C22:$AG22)>0,SUM($C22:$AG22),"") -> 162 | AI22: 234 | AJ22: 250 | AK22: =AJ22-AI22 -> 16 | AL22: =AJ22*AH22 -> 40500 | AM22: =AK22*AH22 -> 2592
B23: Hydrocodone | C23: =RANDBETWEEN(1,10) -> 1 | D23: =RANDBETWEEN(1,10) -> 2 | E23: =RANDBETWEEN(1,10) -> 9 | F23: =RANDBETWEEN(1,10) -> 4 | G23: =RANDBETWEEN(1,10) -> 6 | H23: =RANDBETWEEN(1,10) -> 8 | I23: =RANDBETWEEN(1,10) -> 7 | J23: =RANDBETWEEN(1,10) -> 8 | ... AG23: =RANDBETWEEN(1,10) -> 3 | AH23: =IF(SUM($C23:$AG23)>0,SUM($C23:$AG23),"") -> 156 | AI23: 121 | AJ23: 140 | AK23: =AJ23-AI23 -> 19 | AL23: =AJ23*AH23 -> 21840 | AM23: =AK23*AH23 -> 2964
B24: Gabapentin | C24: =RANDBETWEEN(1,10) -> 9 | D24: =RANDBETWEEN(1,10) -> 9 | E24: =RANDBETWEEN(1,10) -> 6 | F24: =RANDBETWEEN(1,10) -> 1 | G24: =RANDBETWEEN(1,10) -> 9 | H24: =RANDBETWEEN(1,10) -> 9 | I24: =RANDBETWEEN(1,10) -> 5 | J24: =RANDBETWEEN(1,10) -> 2 | ... AG24: =RANDBETWEEN(1,10) -> 5 | AH24: =IF(SUM($C24:$AG24)>0,SUM($C24:$AG24),"") -> 178 | AI24: 350 | AJ24: 390 | AK24: =AJ24-AI24 -> 40 | AL24: =AJ24*AH24 -> 69420 | AM24: =AK24*AH24 -> 7120
B25: Levothyroxine | C25: =RANDBETWEEN(1,10) -> 2 | D25: =RANDBETWEEN(1,10) -> 2 | E25: =RANDBETWEEN(1,10) -> 9 | F25: =RANDBETWEEN(1,10) -> 10 | G25: =RANDBETWEEN(1,10) -> 5 | H25: =RANDBETWEEN(1,10) -> 6 | I25: =RANDBETWEEN(1,10) -> 2 | J25: =RANDBETWEEN(1,10) -> 5 | ... AG25: =RANDBETWEEN(1,10) -> 2 | AH25: =IF(SUM($C25:$AG25)>0,SUM($C25:$AG25),"") -> 161 | AI25: 211 | AJ25: 240 | AK25: =AJ25-AI25 -> 29 | AL25: =AJ25*AH25 -> 38640 | AM25: =AK25*AH25 -> 4669
B26: Sertraline | C26: =RANDBETWEEN(1,10) -> 1 | D26: =RANDBETWEEN(1,10) -> 10 | E26: =RANDBETWEEN(1,10) -> 6 | F26: =RANDBETWEEN(1,10) -> 7 | G26: =RANDBETWEEN(1,10) -> 3 | H26: =RANDBETWEEN(1,10) -> 3 | I26: =RANDBETWEEN(1,10) -> 6 | J26: =RANDBETWEEN(1,10) -> 3 | ... AG26: =RANDBETWEEN(1,10) -> 8 | AH26: =IF(SUM($C26:$AG26)>0,SUM($C26:$AG26),"") -> 146 | AI26: 247 | AJ26: 280 | AK26: =AJ26-AI26 -> 33 | AL26: =AJ26*AH26 -> 40880 | AM26: =AK26*AH26 -> 4818
B27: Azithromycin | C27: =RANDBETWEEN(1,10) -> 3 | D27: =RANDBETWEEN(1,10) -> 7 | E27: =RANDBETWEEN(1,10) -> 4 | F27: =RANDBETWEEN(1,10) -> 2 | G27: =RANDBETWEEN(1,10) -> 9 | H27: =RANDBETWEEN(1,10) -> 6 | I27: =RANDBETWEEN(1,10) -> 8 | J27: =RANDBETWEEN(1,10) -> 3 | ... AG27: =RANDBETWEEN(1,10) -> 6 | AH27: =IF(SUM($C27:$AG27)>0,SUM($C27:$AG27),"") -> 178 | AI27: 286 | AJ27: 320 | AK27: =AJ27-AI27 -> 34 | AL27: =AJ27*AH27 -> 56960 | AM27: =AK27*AH27 -> 6052
B28: Losartan | C28: =RANDBETWEEN(1,10) -> 1 | D28: =RANDBETWEEN(1,10) -> 4 | E28: =RANDBETWEEN(1,10) -> 5 | F28: =RANDBETWEEN(1,10) -> 9 | G28: =RANDBETWEEN(1,10) -> 9 | H28: =RANDBETWEEN(1,10) -> 6 | I28: =RANDBETWEEN(1,10) -> 8 | J28: =RANDBETWEEN(1,10) -> 2 | ... AG28: =RANDBETWEEN(1,10) -> 10 | AH28: =IF(SUM($C28:$AG28)>0,SUM($C28:$AG28),"") -> 192 | AI28: 67 | AJ28: 80 | AK28: =AJ28-AI28 -> 13 | AL28: =AJ28*AH28 -> 15360 | AM28: =AK28*AH28 -> 2496
... B57: Lamotrigine | C57: =RANDBETWEEN(1,10) -> 6 | D57: =RANDBETWEEN(1,10) -> 8 | E57: =RANDBETWEEN(1,10) -> 1 | F57: =RANDBETWEEN(1,10) -> 6 | G57: =RANDBETWEEN(1,10) -> 6 | H57: =RANDBETWEEN(1,10) -> 9 | I57: =RANDBETWEEN(1,10) -> 1 | J57: =RANDBETWEEN(1,10) -> 6 | ... AG57: =RANDBETWEEN(1,10) -> 4 | AH57: =IF(SUM($C57:$AG57)>0,SUM($C57:$AG57),"") -> 153 | AI57: 340 | AJ57: 380 | AK57: =AJ57-AI57 -> 40 | AL57: =AJ57*AH57 -> 58140 | AM57: =AK57*AH57 -> 6120

Sheet Aprail
C1: =TEXT(C2,"DDD") -> #VALUE! | D1: =TEXT(D2,"DDD") -> #VALUE! | E1: =TEXT(E2,"DDD") -> #VALUE! | F1: =TEXT(F2,"DDD") -> #VALUE! | G1: =TEXT(G2,"DDD") -> #VALUE! | H1: =TEXT(H2,"DDD") -> #VALUE! | I1: =TEXT(I2,"DDD") -> #VALUE! | J1: =TEXT(J2,"DDD") -> #VALUE! | ... AF1: =TEXT(AF2,"DDD") -> #VALUE! | AH1: Total Sales | AI1: Incoming price (Including GST) | AJ1: Sales price | AK1: Profit Margin | AL1: Total collection | AM1: Net collection | AO1: Month | AP1: Aprail
B2: Product Name | C2: =IF(COLUMNS($C$2:C2)>DAY($AP$4),"",$AP$3+COLUMNS($C$2:C2)-1) -> #VALUE! | D2: =IF(COLUMNS($C$2:D2)>DAY($AP$4),"",$AP$3+COLUMNS($C$2:D2)-1) -> #VALUE! | E2: =IF(COLUMNS($C$2:E2)>DAY($AP$4),"",$AP$3+COLUMNS($C$2:E2)-1) -> #VALUE! | F2: =IF(COLUMNS($C$2:F2)>DAY($AP$4),"",$AP$3+COLUMNS($C$2:F2)-1) -> #VALUE! | G2: =IF(COLUMNS($C$2:G2)>DAY($AP$4),"",$AP$3+COLUMNS($C$2:G2)-1) -> #VALUE! | H2: =IF(COLUMNS($C$2:H2)>DAY($AP$4),"",$AP$3+COLUMNS($C$2:H2)-1) -> #VALUE! | I2: =IF(COLUMNS($C$2:I2)>DAY($AP$4),"",$AP$3+COLUMNS($C$2:I2)-1) -> #VALUE! | J2: =IF(COLUMNS($C$2:J2)>DAY($AP$4),"",$AP$3+COLUMNS($C$2:J2)-1) -> #VALUE! | ... AF2: =IF(COLUMNS($C$2:AF2)>DAY($AP$4),"",$AP$3+COLUMNS($C$2:AF2)-1) -> #VALUE! | AO2: Year | AP2: 2024
B3: Iodex | C3: =RANDBETWEEN(1,10) -> 7 | D3: =RANDBETWEEN(1,10) -> 10 | E3: =RANDBETWEEN(1,10) -> 2 | F3: =RANDBETWEEN(1,10) -> 4 | G3: =RANDBETWEEN(1,10) -> 8 | H3: =RANDBETWEEN(1,10) -> 3 | I3: =RANDBETWEEN(1,10) -> 4 | J3: =RANDBETWEEN(1,10) -> 1 | ... AF3: =RANDBETWEEN(1,10) -> 5 | AH3: =IF(SUM($C3:$AG3)>0,SUM($C3:$AG3),"") -> 137 | AI3: 40 | AJ3: 80 | AK3: =AJ3-AI3 -> 40 | AL3: =AJ3*AH3 -> 10960 | AM3: =AK3*AH3 -> 5480 | AO3: Starting Date | AP3: =DATE(AP2,MONTH(AP1&1),1) -> #VALUE!
B4: Nimocet | C4: =RANDBETWEEN(1,10) -> 6 | D4: =RANDBETWEEN(1,10) -> 6 | E4: =RANDBETWEEN(1,10) -> 10 | F4: =RANDBETWEEN(1,10) -> 7 | G4: =RANDBETWEEN(1,10) -> 2 | H4: =RANDBETWEEN(1,10) -> 5 | I4: =RANDBETWEEN(1,10) -> 6 | J4: =RANDBETWEEN(1,10) -> 8 | ... AF4: =RANDBETWEEN(1,10) -> 3 | AH4: =IF(SUM($C4:$AG4)>0,SUM($C4:$AG4),"") -> 157 | AI4: 7 | AJ4: 15 | AK4: =AJ4-AI4 -> 8 | AL4: =AJ4*AH4 -> 2355 | AM4: =AK4*AH4 -> 1256 | AO4: Ending Date | AP4: =EOMONTH(AP3,0) -> #VALUE!
B5: Paracetamol | C5: =RANDBETWEEN(1,10) -> 1 | D5: =RANDBETWEEN(1,10) -> 6 | E5: =RANDBETWEEN(1,10) -> 5 | F5: =RANDBETWEEN(1,10) -> 4 | G5: =RANDBETWEEN(1,10) -> 10 | H5: =RANDBETWEEN(1,10) -> 2 | I5: =RANDBETWEEN(1,10) -> 5 | J5: =RANDBETWEEN(1,10) -> 2 | ... AF5: =RANDBETWEEN(1,10) -> 4 | AH5: =IF(SUM($C5:$AG5)>0,SUM($C5:$AG5),"") -> 172 | AI5: 5 | AJ5: 10 | AK5: =AJ5-AI5 -> 5 | AL5: =AJ5*AH5 -> 1720 | AM5: =AK5*AH5 -> 860
B6: Monocef | C6: =RANDBETWEEN(1,10) -> 9 | D6: =RANDBETWEEN(1,10) -> 1 | E6: =RANDBETWEEN(1,10) -> 7 | F6: =RANDBETWEEN(1,10) -> 1 | G6: =RANDBETWEEN(1,10) -> 6 | H6: =RANDBETWEEN(1,10) -> 10 | I6: =RANDBETWEEN(1,10) -> 5 | J6: =RANDBETWEEN(1,10) -> 10 | ... AF6: =RANDBETWEEN(1,10) -> 3 | AH6: =IF(SUM($C6:$AG6)>0,SUM($C6:$AG6),"") -> 167 | AI6: 45 | AJ6: 80 | AK6: =AJ6-AI6 -> 35 | AL6: =AJ6*AH6 -> 13360 | AM6: =AK6*AH6 -> 5845
B7: Cyclopalm | C7: =RANDBETWEEN(1,10) -> 8 | D7: =RANDBETWEEN(1,10) -> 6 | E7: =RANDBETWEEN(1,10) -> 6 | F7: =RANDBETWEEN(1,10) -> 7 | G7: =RANDBETWEEN(1,10) -> 3 | H7: =RANDBETWEEN(1,10) -> 3 | I7: =RANDBETWEEN(1,10) -> 9 | J7: =RANDBETWEEN(1,10) -> 3 | ... AF7: =RANDBETWEEN(1,10) -> 4 | AH7: =IF(SUM($C7:$AG7)>0,SUM($C7:$AG7),"") -> 171 | AI7: 392 | AJ7: 420 | AK7: =AJ7-AI7 -> 28 | AL7: =AJ7*AH7 -> 71820 | AM7: =AK7*AH7 -> 4788 | AO7: Expanses
B8: Cetaphil | C8: =RANDBETWEEN(1,10) -> 10 | D8: =RANDBETWEEN(1,10) -> 4 | E8: =RANDBETWEEN(1,10) -> 4 | F8: =RANDBETWEEN(1,10) -> 8 | G8: =RANDBETWEEN(1,10) -> 6 | H8: =RANDBETWEEN(1,10) -> 1 | I8: =RANDBETWEEN(1,10) -> 3 | J8: =RANDBETWEEN(1,10) -> 10 | ... AF8: =RANDBETWEEN(1,10) -> 3 | AH8: =IF(SUM($C8:$AG8)>0,SUM($C8:$AG8),"") -> 181 | AI8: 86 | AJ8: 100 | AK8: =AJ8-AI8 -> 14 | AL8: =AJ8*AH8 -> 18100 | AM8: =AK8*AH8 -> 2534 | AO8: Employee Salary
B9: Acetaminophen | C9: =RANDBETWEEN(1,10) -> 7 | D9: =RANDBETWEEN(1,10) -> 2 | E9: =RANDBETWEEN(1,10) -> 2 | F9: =RANDBETWEEN(1,10) -> 8 | G9: =RANDBETWEEN(1,10) -> 2 | H9: =RANDBETWEEN(1,10) -> 8 | I9: =RANDBETWEEN(1,10) -> 6 | J9: =RANDBETWEEN(1,10) -> 7 | ... AF9: =RANDBETWEEN(1,10) -> 9 | AH9: =IF(SUM($C9:$AG9)>0,SUM($C9:$AG9),"") -> 174 | AI9: 271 | AJ9: 300 | AK9: =AJ9-AI9 -> 29 | AL9: =AJ9*AH9 -> 52200 | AM9: =AK9*AH9 -> 5046 | AO9: Kaishav(Owner) | AP9: ='Attendence (Aprail)'!AL3 -> 48333.333
B10: Ibuprofen | C10: =RANDBETWEEN(1,10) -> 4 | D10: =RANDBETWEEN(1,10) -> 3 | E10: =RANDBETWEEN(1,10) -> 2 | F10: =RANDBETWEEN(1,10) -> 4 | G10: =RANDBETWEEN(1,10) -> 3 | H10: =RANDBETWEEN(1,10) -> 8 | I10: =RANDBETWEEN(1,10) -> 6 | J10: =RANDBETWEEN(1,10) -> 10 | ... AF10: =RANDBETWEEN(1,10) -> 2 | AH10: =IF(SUM($C10:$AG10)>0,SUM($C10:$AG10),"") -> 166 | AI10: 226 | AJ10: 250 | AK10: =AJ10-AI10 -> 24 | AL10: =AJ10*AH10 -> 41500 | AM10: =AK10*AH10 -> 3984 | AO10: Raman | AP10: ='Attendence (Aprail)'!AL4 -> 14000
B11: Aspirin | C11: =RANDBETWEEN(1,10) -> 7 | D11: =RANDBETWEEN(1,10) -> 8 | E11: =RANDBETWEEN(1,10) -> 3 | F11: =RANDBETWEEN(1,10) -> 5 | G11: =RANDBETWEEN(1,10) -> 5 | H11: =RANDBETWEEN(1,10) -> 1 | I11: =RANDBETWEEN(1,10) -> 10 | J11: =RANDBETWEEN(1,10) -> 3 | ... AF11: =RANDBETWEEN(1,10) -> 5 | AH11: =IF(SUM($C11:$AG11)>0,SUM($C11:$AG11),"") -> 159 | AI11: 390 | AJ11: 450 | AK11: =AJ11-AI11 -> 60 | AL11: =AJ11*AH11 -> 71550 | AM11: =AK11*AH11 -> 9540 | AO11: Sohan | AP11: ='Attendence (Aprail)'!AL5 -> 17400
B12: Amoxicillin | C12: =RANDBETWEEN(1,10) -> 8 | D12: =RANDBETWEEN(1,10) -> 4 | E12: =RANDBETWEEN(1,10) -> 10 | F12: =RANDBETWEEN(1,10) -> 1 | G12: =RANDBETWEEN(1,10) -> 5 | H12: =RANDBETWEEN(1,10) -> 3 | I12: =RANDBETWEEN(1,10) -> 3 | J12: =RANDBETWEEN(1,10) -> 1 | ... AF12: =RANDBETWEEN(1,10) -> 9 | AH12: =IF(SUM($C12:$AG12)>0,SUM($C12:$AG12),"") -> 155 | AI12: 379 | AJ12: 430 | AK12: =AJ12-AI12 -> 51 | AL12: =AJ12*AH12 -> 66650 | AM12: =AK12*AH12 -> 7905 | AO12: Tilak | AP12: ='Attendence (Aprail)'!AL6 -> 9666.6667
B13: Ciprofloxacin | C13: =RANDBETWEEN(1,10) -> 9 | D13: =RANDBETWEEN(1,10) -> 1 | E13: =RANDBETWEEN(1,10) -> 2 | F13: =RANDBETWEEN(1,10) -> 8 | G13: =RANDBETWEEN(1,10) -> 3 | H13: =RANDBETWEEN(1,10) -> 4 | I13: =RANDBETWEEN(1,10) -> 10 | J13: =RANDBETWEEN(1,10) -> 5 | ... AF13: =RANDBETWEEN(1,10) -> 6 | AH13: =IF(SUM($C13:$AG13)>0,SUM($C13:$AG13),"") -> 169 | AI13: 368 | AJ13: 435 | AK13: =AJ13-AI13 -> 67 | AL13: =AJ13*AH13 -> 73515 | AM13: =AK13*AH13 -> 11323 | AO13: Bill to pay | AP13: 10000
B14: Lisinopril | C14: =RANDBETWEEN(1,10) -> 3 | D14: =RANDBETWEEN(1,10) -> 3 | E14: =RANDBETWEEN(1,10) -> 9 | F14: =RANDBETWEEN(1,10) -> 10 | G14: =RANDBETWEEN(1,10) -> 10 | H14: =RANDBETWEEN(1,10) -> 2 | I14: =RANDBETWEEN(1,10) -> 3 | J14: =RANDBETWEEN(1,10) -> 7 | ... AF14: =RANDBETWEEN(1,10) -> 6 | AH14: =IF(SUM($C14:$AG14)>0,SUM($C14:$AG14),"") -> 153 | AI14: 88 | AJ14: 99 | AK14: =AJ14-AI14 -> 11 | AL14: =AJ14*AH14 -> 15147 | AM14: =AK14*AH14 -> 1683 | AO14: other | AP14: 2000
B15: Atorvastatin | C15: =RANDBETWEEN(1,10) -> 7 | D15: =RANDBETWEEN(1,10) -> 4 | E15: =RANDBETWEEN(1,10) -> 9 | F15: =RANDBETWEEN(1,10) -> 4 | G15: =RANDBETWEEN(1,10) -> 7 | H15: =RANDBETWEEN(1,10) -> 9 | I15: =RANDBETWEEN(1,10) -> 10 | J15: =RANDBETWEEN(1,10) -> 7 | ... AF15: =RANDBETWEEN(1,10) -> 3 | AH15: =IF(SUM($C15:$AG15)>0,SUM($C15:$AG15),"") -> 183 | AI15: 391 | AJ15: 500 | AK15: =AJ15-AI15 -> 109 | AL15: =AJ15*AH15 -> 91500 | AM15: =AK15*AH15 -> 19947 | AO15: Net collection | AP15: =SUM(AM3:AM57) -> 282392
B16: Metformin | C16: =RANDBETWEEN(1,10) -> 10 | D16: =RANDBETWEEN(1,10) -> 8 | E16: =RANDBETWEEN(1,10) -> 6 | F16: =RANDBETWEEN(1,10) -> 4 | G16: =RANDBETWEEN(1,10) -> 10 | H16: =RANDBETWEEN(1,10) -> 5 | I16: =RANDBETWEEN(1,10) -> 7 | J16: =RANDBETWEEN(1,10) -> 9 | ... AF16: =RANDBETWEEN(1,10) -> 2 | AH16: =IF(SUM($C16:$AG16)>0,SUM($C16:$AG16),"") -> 162 | AI16: 261 | AJ16: 300 | AK16: =AJ16-AI16 -> 39 | AL16: =AJ16*AH16 -> 48600 | AM16: =AK16*AH16 -> 6318 | AO16: Net Income | AP16: =AP15-(AP9+AP10+AP11+AP12+AP13+AP14) -> 180992
B17: Simvastatin | C17: =RANDBETWEEN(1,10) -> 6 | D17: =RANDBETWEEN(1,10) -> 9 | E17: =RANDBETWEEN(1,10) -> 1 | F17: =RANDBETWEEN(1,10) -> 4 | G17: =RANDBETWEEN(1,10) -> 5 | H17: =RANDBETWEEN(1,10) -> 2 | I17: =RANDBETWEEN(1,10) -> 10 | J17: =RANDBETWEEN(1,10) -> 7 | ... AF17: =RANDBETWEEN(1,10) -> 2 | AH17: =IF(SUM($C17:$AG17)>0,SUM($C17:$AG17),"") -> 140 | AI17: 67 | AJ17: 99 | AK17: =AJ17-AI17 -> 32 | AL17: =AJ17*AH17 -> 13860 | AM17: =AK17*AH17 -> 4480
B18: Omeprazole | C18: =RANDBETWEEN(1,10) -> 8 | D18: =RANDBETWEEN(1,10) -> 6 | E18: =RANDBETWEEN(1,10) -> 6 | F18: =RANDBETWEEN(1,10) -> 7 | G18: =RANDBETWEEN(1,10) -> 9 | H18: =RANDBETWEEN(1,10) -> 3 | I18: =RANDBETWEEN(1,10) -> 7 | J18: =RANDBETWEEN(1,10) -> 7 | ... AF18: =RANDBETWEEN(1,10) -> 4 | AH18: =IF(SUM($C18:$AG18)>0,SUM($C18:$AG18),"") -> 166 | AI18: 138 | AJ18: 150 | AK18: =AJ18-AI18 -> 12 | AL18: =AJ18*AH18 -> 24900 | AM18: =AK18*AH18 -> 1992
B19: Clopidogrel | C19: =RANDBETWEEN(1,10) -> 4 | D19: =RANDBETWEEN(1,10) -> 4 | E19: =RANDBETWEEN(1,10) -> 3 | F19: =RANDBETWEEN(1,10) -> 6 | G19: =RANDBETWEEN(1,10) -> 3 | H19: =RANDBETWEEN(1,10) -> 2 | I19: =RANDBETWEEN(1,10) -> 5 | J19: =RANDBETWEEN(1,10) -> 3 | ... AF19: =RANDBETWEEN(1,10) -> 1 | AH19: =IF(SUM($C19:$AG19)>0,SUM($C19:$AG19),"") -> 123 | AI19: 60 | AJ19: 80 | AK19: =AJ19-AI19 -> 20 | AL19: =AJ19*AH19 -> 9840 | AM19: =AK19*AH19 -> 2460
B20: Metoprolol | C20: =RANDBETWEEN(1,10) -> 8 | D20: =RANDBETWEEN(1,10) -> 8 | E20: =RANDBETWEEN(1,10) -> 4 | F20: =RANDBETWEEN(1,10) -> 6 | G20: =RANDBETWEEN(1,10) -> 3 | H20: =RANDBETWEEN(1,10) -> 3 | I20: =RANDBETWEEN(1,10) -> 4 | J20: =RANDBETWEEN(1,10) -> 9 | ... AF20: =RANDBETWEEN(1,10) -> 10 | AH20: =IF(SUM($C20:$AG20)>0,SUM($C20:$AG20),"") -> 194 | AI20: 44 | AJ20: 50 | AK20: =AJ20-AI20 -> 6 | AL20: =AJ20*AH20 -> 9700 | AM20: =AK20*AH20 -> 1164
B21: Amlodipine | C21: =RANDBETWEEN(1,10) -> 6 | D21: =RANDBETWEEN(1,10) -> 5 | E21: =RANDBETWEEN(1,10) -> 4 | F21: =RANDBETWEEN(1,10) -> 7 | G21: =RANDBETWEEN(1,10) -> 10 | H21: =RANDBETWEEN(1,10) -> 8 | I21: =RANDBETWEEN(1,10) -> 2 | J21: =RANDBETWEEN(1,10) -> 8 | ... AF21: =RANDBETWEEN(1,10) -> 6 | AH21: =IF(SUM($C21:$AG21)>0,SUM($C21:$AG21),"") -> 162 | AI21: 308 | AJ21: 320 | AK21: =AJ21-AI21 -> 12 | AL21: =AJ21*AH21 -> 51840 | AM21: =AK21*AH21 -> 1944
B22: Alprazolam | C22: =RANDBETWEEN(1,10) -> 2 | D22: =RANDBETWEEN(1,10) -> 1 | E22: =RANDBETWEEN(1,10) -> 5 | F22: =RANDBETWEEN(1,10) -> 10 | G22: =RANDBETWEEN(1,10) -> 6 | H22: =RANDBETWEEN(1,10) -> 1 | I22: =RANDBETWEEN(1,10) -> 10 | J22: =RANDBETWEEN(1,10) -> 4 | ... AF22: =RANDBETWEEN(1,10) -> 8 | AH22: =IF(SUM($C22:$AG22)>0,SUM($C22:$AG22),"") -> 167 | AI22: 234 | AJ22: 250 | AK22: =AJ22-AI22 -> 16 | AL22: =AJ22*AH22 -> 41750 | AM22: =AK22*AH22 -> 2672
B23: Hydrocodone | C23: =RANDBETWEEN(1,10) -> 3 | D23: =RANDBETWEEN(1,10) -> 10 | E23: =RANDBETWEEN(1,10) -> 1 | F23: =RANDBETWEEN(1,10) -> 2 | G23: =RANDBETWEEN(1,10) -> 8 | H23: =RANDBETWEEN(1,10) -> 9 | I23: =RANDBETWEEN(1,10) -> 4 | J23: =RANDBETWEEN(1,10) -> 7 | ... AF23: =RANDBETWEEN(1,10) -> 9 | AH23: =IF(SUM($C23:$AG23)>0,SUM($C23:$AG23),"") -> 173 | AI23: 121 | AJ23: 140 | AK23: =AJ23-AI23 -> 19 | AL23: =AJ23*AH23 -> 24220 | AM23: =AK23*AH23 -> 3287
B24: Gabapentin | C24: =RANDBETWEEN(1,10) -> 2 | D24: =RANDBETWEEN(1,10) -> 4 | E24: =RANDBETWEEN(1,10) -> 2 | F24: =RANDBETWEEN(1,10) -> 7 | G24: =RANDBETWEEN(1,10) -> 3 | H24: =RANDBETWEEN(1,10) -> 9 | I24: =RANDBETWEEN(1,10) -> 8 | J24: =RANDBETWEEN(1,10) -> 4 | ... AF24: =RANDBETWEEN(1,10) -> 5 | AH24: =IF(SUM($C24:$AG24)>0,SUM($C24:$AG24),"") -> 156 | AI24: 350 | AJ24: 390 | AK24: =AJ24-AI24 -> 40 | AL24: =AJ24*AH24 -> 60840 | AM24: =AK24*AH24 -> 6240
B25: Levothyroxine | C25: =RANDBETWEEN(1,10) -> 10 | D25: =RANDBETWEEN(1,10) -> 4 | E25: =RANDBETWEEN(1,10) -> 8 | F25: =RANDBETWEEN(1,10) -> 2 | G25: =RANDBETWEEN(1,10) -> 4 | H25: =RANDBETWEEN(1,10) -> 1 | I25: =RANDBETWEEN(1,10) -> 7 | J25: =RANDBETWEEN(1,10) -> 10 | ... AF25: =RANDBETWEEN(1,10) -> 2 | AH25: =IF(SUM($C25:$AG25)>0,SUM($C25:$AG25),"") -> 192 | AI25: 211 | AJ25: 240 | AK25: =AJ25-AI25 -> 29 | AL25: =AJ25*AH25 -> 46080 | AM25: =AK25*AH25 -> 5568
B26: Sertraline | C26: =RANDBETWEEN(1,10) -> 4 | D26: =RANDBETWEEN(1,10) -> 5 | E26: =RANDBETWEEN(1,10) -> 5 | F26: =RANDBETWEEN(1,10) -> 5 | G26: =RANDBETWEEN(1,10) -> 9 | H26: =RANDBETWEEN(1,10) -> 6 | I26: =RANDBETWEEN(1,10) -> 9 | J26: =RANDBETWEEN(1,10) -> 2 | ... AF26: =RANDBETWEEN(1,10) -> 8 | AH26: =IF(SUM($C26:$AG26)>0,SUM($C26:$AG26),"") -> 171 | AI26: 247 | AJ26: 280 | AK26: =AJ26-AI26 -> 33 | AL26: =AJ26*AH26 -> 47880 | AM26: =AK26*AH26 -> 5643
B27: Azithromycin | C27: =RANDBETWEEN(1,10) -> 7 | D27: =RANDBETWEEN(1,10) -> 4 | E27: =RANDBETWEEN(1,10) -> 3 | F27: =RANDBETWEEN(1,10) -> 1 | G27: =RANDBETWEEN(1,10) -> 4 | H27: =RANDBETWEEN(1,10) -> 7 | I27: =RANDBETWEEN(1,10) -> 3 | J27: =RANDBETWEEN(1,10) -> 4 | ... AF27: =RANDBETWEEN(1,10) -> 2 | AH27: =IF(SUM($C27:$AG27)>0,SUM($C27:$AG27),"") -> 154 | AI27: 286 | AJ27: 320 | AK27: =AJ27-AI27 -> 34 | AL27: =AJ27*AH27 -> 49280 | AM27: =AK27*AH27 -> 5236
B28: Losartan | C28: =RANDBETWEEN(1,10) -> 10 | D28: =RANDBETWEEN(1,10) -> 8 | E28: =RANDBETWEEN(1,10) -> 9 | F28: =RANDBETWEEN(1,10) -> 7 | G28: =RANDBETWEEN(1,10) -> 1 | H28: =RANDBETWEEN(1,10) -> 8 | I28: =RANDBETWEEN(1,10) -> 6 | J28: =RANDBETWEEN(1,10) -> 5 | ... AF28: =RANDBETWEEN(1,10) -> 2 | AH28: =IF(SUM($C28:$AG28)>0,SUM($C28:$AG28),"") -> 167 | AI28: 67 | AJ28: 80 | AK28: =AJ28-AI28 -> 13 | AL28: =AJ28*AH28 -> 13360 | AM28: =AK28*AH28 -> 2171
... B57: Lamotrigine | C57: =RANDBETWEEN(1,10) -> 10 | D57: =RANDBETWEEN(1,10) -> 2 | E57: =RANDBETWEEN(1,10) -> 10 | F57: =RANDBETWEEN(1,10) -> 9 | G57: =RANDBETWEEN(1,10) -> 8 | H57: =RANDBETWEEN(1,10) -> 7 | I57: =RANDBETWEEN(1,10) -> 9 | J57: =RANDBETWEEN(1,10) -> 8 | ... AF57: =RANDBETWEEN(1,10) -> 6 | AH57: =IF(SUM($C57:$AG57)>0,SUM($C57:$AG57),"") -> 187 | AI57: 340 | AJ57: 380 | AK57: =AJ57-AI57 -> 40 | AL57: =AJ57*AH57 -> 71060 | AM57: =AK57*AH57 -> 7480

Sheet May
C1: =TEXT(C2,"DDD") -> Wed | D1: =TEXT(D2,"DDD") -> Thu | E1: =TEXT(E2,"DDD") -> Fri | F1: =TEXT(F2,"DDD") -> Sat | G1: =TEXT(G2,"DDD") -> Sun | H1: =TEXT(H2,"DDD") -> Mon | I1: =TEXT(I2,"DDD") -> Tue | J1: =TEXT(J2,"DDD") -> Wed | ... AG1: =TEXT(AG2,"DDD") -> Fri | AH1: Total Sales | AI1: Incoming price (Including GST) | AJ1: Sales price | AK1: Profit Margin | AL1: Total collection | AM1: Net collection | AO1: Month | AP1: May
B2: Product Name | C2: =IF(COLUMNS($C$2:C2)>DAY($AP$4),"",$AP$3+COLUMNS($C$2:C2)-1) -> 45413 | D2: =IF(COLUMNS($C$2:D2)>DAY($AP$4),"",$AP$3+COLUMNS($C$2:D2)-1) -> 45414 | E2: =IF(COLUMNS($C$2:E2)>DAY($AP$4),"",$AP$3+COLUMNS($C$2:E2)-1) -> 45415 | F2: =IF(COLUMNS($C$2:F2)>DAY($AP$4),"",$AP$3+COLUMNS($C$2:F2)-1) -> 45416 | G2: =IF(COLUMNS($C$2:G2)>DAY($AP$4),"",$AP$3+COLUMNS($C$2:G2)-1) -> 45417 | H2: =IF(COLUMNS($C$2:H2)>DAY($AP$4),"",$AP$3+COLUMNS($C$2:H2)-1) -> 45418 | I2: =IF(COLUMNS($C$2:I2)>DAY($AP$4),"",$AP$3+COLUMNS($C$2:I2)-1) -> 45419 | J2: =IF(COLUMNS($C$2:J2)>DAY($AP$4),"",$AP$3+COLUMNS($C$2:J2)-1) -> 45420 | ... AG2: =IF(COLUMNS($C$2:AG2)>DAY($AP$4),"",$AP$3+COLUMNS($C$2:AG2)-1) -> 45443 | AO2: Year | AP2: 2024
B3: Iodex | C3: =RANDBETWEEN(1,10) -> 1 | D3: =RANDBETWEEN(1,10) -> 1 | E3: =RANDBETWEEN(1,10) -> 2 | F3: =RANDBETWEEN(1,10) -> 6 | G3: =RANDBETWEEN(1,10) -> 2 | H3: =RANDBETWEEN(1,10) -> 10 | I3: =RANDBETWEEN(1,10) -> 1 | J3: =RANDBETWEEN(1,10) -> 6 | ... AG3: =RANDBETWEEN(1,10) -> 5 | AH3: =IF(SUM($C3:$AG3)>0,SUM($C3:$AG3),"") -> 144 | AI3: 40 | AJ3: 80 | AK3: =AJ3-AI3 -> 40 | AL3: =AJ3*AH3 -> 11520 | AM3: =AK3*AH3 -> 5760 | AO3: Starting Date | AP3: =DATE(AP2,MONTH(AP1&1),1) -> 45413
B4: Nimocet | C4: =RANDBETWEEN(1,10) -> 5 | D4: =RANDBETWEEN(1,10) -> 4 | E4: =RANDBETWEEN(1,10) -> 4 | F4: =RANDBETWEEN(1,10) -> 10 | G4: =RANDBETWEEN(1,10) -> 10 | H4: =RANDBETWEEN(1,10) -> 3 | I4: =RANDBETWEEN(1,10) -> 3 | J4: =RANDBETWEEN(1,10) -> 5 | ... AG4: =RANDBETWEEN(1,10) -> 8 | AH4: =IF(SUM($C4:$AG4)>0,SUM($C4:$AG4),"") -> 171 | AI4: 7 | AJ4: 15 | AK4: =AJ4-AI4 -> 8 | AL4: =AJ4*AH4 -> 2565 | AM4: =AK4*AH4 -> 1368 | AO4: Ending Date | AP4: =EOMONTH(AP3,0) -> 45443
B5: Paracetamol | C5: =RANDBETWEEN(1,10) -> 6 | D5: =RANDBETWEEN(1,10) -> 6 | E5: =RANDBETWEEN(1,10) -> 9 | F5: =RANDBETWEEN(1,10) -> 10 | G5: =RANDBETWEEN(1,10) -> 3 | H5: =RANDBETWEEN(1,10) -> 1 | I5: =RANDBETWEEN(1,10) -> 5 | J5: =RANDBETWEEN(1,10) -> 5 | ... AG5: =RANDBETWEEN(1,10) -> 10 | AH5: =IF(SUM($C5:$AG5)>0,SUM($C5:$AG5),"") -> 193 | AI5: 5 | AJ5: 10 | AK5: =AJ5-AI5 -> 5 | AL5: =AJ5*AH5 -> 1930 | AM5: =AK5*AH5 -> 965
B6: Monocef | C6: =RANDBETWEEN(1,10) -> 2 | D6: =RANDBETWEEN(1,10) -> 5 | E6: =RANDBETWEEN(1,10) -> 9 | F6: =RANDBETWEEN(1,10) -> 4 | G6: =RANDBETWEEN(1,10) -> 9 | H6: =RANDBETWEEN(1,10) -> 10 | I6: =RANDBETWEEN(1,10) -> 6 | J6: =RANDBETWEEN(1,10) -> 1 | ... AG6: =RANDBETWEEN(1,10) -> 1 | AH6: =IF(SUM($C6:$AG6)>0,SUM($C6:$AG6),"") -> 163 | AI6: 45 | AJ6: 80 | AK6: =AJ6-AI6 -> 35 | AL6: =AJ6*AH6 -> 13040 | AM6: =AK6*AH6 -> 5705
B7: Cyclopalm | C7: =RANDBETWEEN(1,10) -> 1 | D7: =RANDBETWEEN(1,10) -> 6 | E7: =RANDBETWEEN(1,10) -> 9 | F7: =RANDBETWEEN(1,10) -> 5 | G7: =RANDBETWEEN(1,10) -> 9 | H7: =RANDBETWEEN(1,10) -> 1 | I7: =RANDBETWEEN(1,10) -> 10 | J7: =RANDBETWEEN(1,10) -> 3 | ... AG7: =RANDBETWEEN(1,10) -> 6 | AH7: =IF(SUM($C7:$AG7)>0,SUM($C7:$AG7),"") -> 161 | AI7: 392 | AJ7: 420 | AK7: =AJ7-AI7 -> 28 | AL7: =AJ7*AH7 -> 67620 | AM7: =AK7*AH7 -> 4508 | AO7: Expanses
B8: Cetaphil | C8: =RANDBETWEEN(1,10) -> 8 | D8: =RANDBETWEEN(1,10) -> 5 | E8: =RANDBETWEEN(1,10) -> 3 | F8: =RANDBETWEEN(1,10) -> 9 | G8: =RANDBETWEEN(1,10) -> 6 | H8: =RANDBETWEEN(1,10) -> 6 | I8: =RANDBETWEEN(1,10) -> 9 | J8: =RANDBETWEEN(1,10) -> 5 | ... AG8: =RANDBETWEEN(1,10) -> 9 | AH8: =IF(SUM($C8:$AG8)>0,SUM($C8:$AG8),"") -> 202 | AI8: 86 | AJ8: 100 | AK8: =AJ8-AI8 -> 14 | AL8: =AJ8*AH8 -> 20200 | AM8: =AK8*AH8 -> 2828 | AO8: Employee Salary
B9: Acetaminophen | C9: =RANDBETWEEN(1,10) -> 3 | D9: =RANDBETWEEN(1,10) -> 5 | E9: =RANDBETWEEN(1,10) -> 9 | F9: =RANDBETWEEN(1,10) -> 7 | G9: =RANDBETWEEN(1,10) -> 4 | H9: =RANDBETWEEN(1,10) -> 6 | I9: =RANDBETWEEN(1,10) -> 7 | J9: =RANDBETWEEN(1,10) -> 10 | ... AG9: =RANDBETWEEN(1,10) -> 1 | AH9: =IF(SUM($C9:$AG9)>0,SUM($C9:$AG9),"") -> 160 | AI9: 271 | AJ9: 300 | AK9: =AJ9-AI9 -> 29 | AL9: =AJ9*AH9 -> 48000 | AM9: =AK9*AH9 -> 4640 | AO9: Kaishav(Owner) | AP9: ='Attendence (May)'!AL3 -> 50000
B10: Ibuprofen | C10: =RANDBETWEEN(1,10) -> 4 | D10: =RANDBETWEEN(1,10) -> 3 | E10: =RANDBETWEEN(1,10) -> 8 | F10: =RANDBETWEEN(1,10) -> 10 | G10: =RANDBETWEEN(1,10) -> 7 | H10: =RANDBETWEEN(1,10) -> 7 | I10: =RANDBETWEEN(1,10) -> 5 | J10: =RANDBETWEEN(1,10) -> 7 | ... AG10: =RANDBETWEEN(1,10) -> 9 | AH10: =IF(SUM($C10:$AG10)>0,SUM($C10:$AG10),"") -> 164 | AI10: 226 | AJ10: 250 | AK10: =AJ10-AI10 -> 24 | AL10: =AJ10*AH10 -> 41000 | AM10: =AK10*AH10 -> 3936 | AO10: Raman | AP10: ='Attendence (May)'!AL4 -> 14000
B11: Aspirin | C11: =RANDBETWEEN(1,10) -> 6 | D11: =RANDBETWEEN(1,10) -> 7 | E11: =RANDBETWEEN(1,10) -> 6 | F11: =RANDBETWEEN(1,10) -> 7 | G11: =RANDBETWEEN(1,10) -> 5 | H11: =RANDBETWEEN(1,10) -> 8 | I11: =RANDBETWEEN(1,10) -> 7 | J11: =RANDBETWEEN(1,10) -> 2 | ... AG11: =RANDBETWEEN(1,10) -> 9 | AH11: =IF(SUM($C11:$AG11)>0,SUM($C11:$AG11),"") -> 182 | AI11: 390 | AJ11: 450 | AK11: =AJ11-AI11 -> 60 | AL11: =AJ11*AH11 -> 81900 | AM11: =AK11*AH11 -> 10920 | AO11: Sohan | AP11: ='Attendence (May)'!AL5 -> 18600
B12: Amoxicillin | C12: =RANDBETWEEN(1,10) -> 10 | D12: =RANDBETWEEN(1,10) -> 10 | E12: =RANDBETWEEN(1,10) -> 6 | F12: =RANDBETWEEN(1,10) -> 9 | G12: =RANDBETWEEN(1,10) -> 7 | H12: =RANDBETWEEN(1,10) -> 5 | I12: =RANDBETWEEN(1,10) -> 4 | J12: =RANDBETWEEN(1,10) -> 8 | ... AG12: =RANDBETWEEN(1,10) -> 3 | AH12: =IF(SUM($C12:$AG12)>0,SUM($C12:$AG12),"") -> 196 | AI12: 379 | AJ12: 430 | AK12: =AJ12-AI12 -> 51 | AL12: =AJ12*AH12 -> 84280 | AM12: =AK12*AH12 -> 9996 | AO12: Tilak | AP12: ='Attendence (May)'!AL6 -> 10000
B13: Ciprofloxacin | C13: =RANDBETWEEN(1,10) -> 8 | D13: =RANDBETWEEN(1,10) -> 6 | E13: =RANDBETWEEN(1,10) -> 8 | F13: =RANDBETWEEN(1,10) -> 2 | G13: =RANDBETWEEN(1,10) -> 2 | H13: =RANDBETWEEN(1,10) -> 5 | I13: =RANDBETWEEN(1,10) -> 10 | J13: =RANDBETWEEN(1,10) -> 8 | ... AG13: =RANDBETWEEN(1,10) -> 1 | AH13: =IF(SUM($C13:$AG13)>0,SUM($C13:$AG13),"") -> 163 | AI13: 368 | AJ13: 435 | AK13: =AJ13-AI13 -> 67 | AL13: =AJ13*AH13 -> 70905 | AM13: =AK13*AH13 -> 10921 | AO13: Bill to pay | AP13: 10000
B14: Lisinopril | C14: =RANDBETWEEN(1,10) -> 7 | D14: =RANDBETWEEN(1,10) -> 7 | E14: =RANDBETWEEN(1,10) -> 7 | F14: =RANDBETWEEN(1,10) -> 9 | G14: =RANDBETWEEN(1,10) -> 9 | H14: =RANDBETWEEN(1,10) -> 5 | I14: =RANDBETWEEN(1,10) -> 3 | J14: =RANDBETWEEN(1,10) -> 10 | ... AG14: =RANDBETWEEN(1,10) -> 10 | AH14: =IF(SUM($C14:$AG14)>0,SUM($C14:$AG14),"") -> 200 | AI14: 88 | AJ14: 99 | AK14: =AJ14-AI14 -> 11 | AL14: =AJ14*AH14 -> 19800 | AM14: =AK14*AH14 -> 2200 | AO14: other | AP14: 2000
B15: Atorvastatin | C15: =RANDBETWEEN(1,10) -> 4 | D15: =RANDBETWEEN(1,10) -> 1 | E15: =RANDBETWEEN(1,10) -> 4 | F15: =RANDBETWEEN(1,10) -> 5 | G15: =RANDBETWEEN(1,10) -> 7 | H15: =RANDBETWEEN(1,10) -> 9 | I15: =RANDBETWEEN(1,10) -> 6 | J15: =RANDBETWEEN(1,10) -> 8 | ... AG15: =RANDBETWEEN(1,10) -> 2 | AH15: =IF(SUM($C15:$AG15)>0,SUM($C15:$AG15),"") -> 148 | AI15: 391 | AJ15: 500 | AK15: =AJ15-AI15 -> 109 | AL15: =AJ15*AH15 -> 74000 | AM15: =AK15*AH15 -> 16132 | AO15: Net collection | AP15: =SUM(AM3:AM57) -> 292868
B16: Metformin | C16: =RANDBETWEEN(1,10) -> 5 | D16: =RANDBETWEEN(1,10) -> 2 | E16: =RANDBETWEEN(1,10) -> 4 | F16: =RANDBETWEEN(1,10) -> 3 | G16: =RANDBETWEEN(1,10) -> 6 | H16: =RANDBETWEEN(1,10) -> 7 | I16: =RANDBETWEEN(1,10) -> 2 | J16: =RANDBETWEEN(1,10) -> 6 | ... AG16: =RANDBETWEEN(1,10) -> 8 | AH16: =IF(SUM($C16:$AG16)>0,SUM($C16:$AG16),"") -> 166 | AI16: 261 | AJ16: 300 | AK16: =AJ16-AI16 -> 39 | AL16: =AJ16*AH16 -> 49800 | AM16: =AK16*AH16 -> 6474 | AO16: Net Income | AP16: =AP15-(AP9+AP10+AP11+AP12+AP13+AP14) -> 188268
B17: Simvastatin | C17: =RANDBETWEEN(1,10) -> 8 | D17: =RANDBETWEEN(1,10) -> 3 | E17: =RANDBETWEEN(1,10) -> 10 | F17: =RANDBETWEEN(1,10) -> 3 | G17: =RANDBETWEEN(1,10) -> 6 | H17: =RANDBETWEEN(1,10) -> 2 | I17: =RANDBETWEEN(1,10) -> 7 | J17: =RANDBETWEEN(1,10) -> 3 | ... AG17: =RANDBETWEEN(1,10) -> 8 | AH17: =IF(SUM($C17:$AG17)>0,SUM($C17:$AG17),"") -> 146 | AI17: 67 | AJ17: 99 | AK17: =AJ17-AI17 -> 32 | AL17: =AJ17*AH17 -> 14454 | AM17: =AK17*AH17 -> 4672
B18: Omeprazole | C18: =RANDBETWEEN(1,10) -> 10 | D18: =RANDBETWEEN(1,10) -> 7 | E18: =RANDBETWEEN(1,10) -> 8 | F18: =RANDBETWEEN(1,10) -> 5 | G18: =RANDBETWEEN(1,10) -> 10 | H18: =RANDBETWEEN(1,10) -> 2 | I18: =RANDBETWEEN(1,10) -> 5 | J18: =RANDBETWEEN(1,10) -> 2 | ... AG18: =RANDBETWEEN(1,10) -> 10 | AH18: =IF(SUM($C18:$AG18)>0,SUM($C18:$AG18),"") -> 157 | AI18: 138 | AJ18: 150 | AK18: =AJ18-AI18 -> 12 | AL18: =AJ18*AH18 -> 23550 | AM18: =AK18*AH18 -> 1884
B19: Clopidogrel | C19: =RANDBETWEEN(1,10) -> 2 | D19: =RANDBETWEEN(1,10) -> 6 | E19: =RANDBETWEEN(1,10) -> 7 | F19: =RANDBETWEEN(1,10) -> 7 | G19: =RANDBETWEEN(1,10) -> 5 | H19: =RANDBETWEEN(1,10) -> 1 | I19: =RANDBETWEEN(1,10) -> 2 | J19: =RANDBETWEEN(1,10) -> 3 | ... AG19: =RANDBETWEEN(1,10) -> 9 | AH19: =IF(SUM($C19:$AG19)>0,SUM($C19:$AG19),"") -> 152 | AI19: 60 | AJ19: 80 | AK19: =AJ19-AI19 -> 20 | AL19: =AJ19*AH19 -> 12160 | AM19: =AK19*AH19 -> 3040
B20: Metoprolol | C20: =RANDBETWEEN(1,10) -> 4 | D20: =RANDBETWEEN(1,10) -> 6 | E20: =RANDBETWEEN(1,10) -> 4 | F20: =RANDBETWEEN(1,10) -> 2 | G20: =RANDBETWEEN(1,10) -> 3 | H20: =RANDBETWEEN(1,10) -> 7 | I20: =RANDBETWEEN(1,10) -> 10 | J20: =RANDBETWEEN(1,10) -> 9 | ... AG20: =RANDBETWEEN(1,10) -> 1 | AH20: =IF(SUM($C20:$AG20)>0,SUM($C20:$AG20),"") -> 174 | AI20: 44 | AJ20: 50 | AK20: =AJ20-AI20 -> 6 | AL20: =AJ20*AH20 -> 8700 | AM20: =AK20*AH20 -> 1044
B21: Amlodipine | C21: =RANDBETWEEN(1,10) -> 8 | D21: =RANDBETWEEN(1,10) -> 7 | E21: =RANDBETWEEN(1,10) -> 4 | F21: =RANDBETWEEN(1,10) -> 7 | G21: =RANDBETWEEN(1,10) -> 1 | H21: =RANDBETWEEN(1,10) -> 7 | I21: =RANDBETWEEN(1,10) -> 10 | J21: =RANDBETWEEN(1,10) -> 1 | ... AG21: =RANDBETWEEN(1,10) -> 8 | AH21: =IF(SUM($C21:$AG21)>0,SUM($C21:$AG21),"") -> 185 | AI21: 308 | AJ21: 320 | AK21: =AJ21-AI21 -> 12 | AL21: =AJ21*AH21 -> 59200 | AM21: =AK21*AH21 -> 2220
B22: Alprazolam | C22: =RANDBETWEEN(1,10) -> 9 | D22: =RANDBETWEEN(1,10) -> 3 | E22: =RANDBETWEEN(1,10) -> 2 | F22: =RANDBETWEEN(1,10) -> 1 | G22: =RANDBETWEEN(1,10) -> 4 | H22: =RANDBETWEEN(1,10) -> 5 | I22: =RANDBETWEEN(1,10) -> 4 | J22: =RANDBETWEEN(1,10) -> 9 | ... AG22: =RANDBETWEEN(1,10) -> 9 | AH22: =IF(SUM($C22:$AG22)>0,SUM($C22:$AG22),"") -> 168 | AI22: 234 | AJ22: 250 | AK22: =AJ22-AI22 -> 16 | AL22: =AJ22*AH22 -> 42000 | AM22: =AK22*AH22 -> 2688
B23: Hydrocodone | C23: =RANDBETWEEN(1,10) -> 4 | D23: =RANDBETWEEN(1,10) -> 5 | E23: =RANDBETWEEN(1,10) -> 7 | F23: =RANDBETWEEN(1,10) -> 6 | G23: =RANDBETWEEN(1,10) -> 8 | H23: =RANDBETWEEN(1,10) -> 6 | I23: =RANDBETWEEN(1,10) -> 3 | J23: =RANDBETWEEN(1,10) -> 6 | ... AG23: =RANDBETWEEN(1,10) -> 8 | AH23: =IF(SUM($C23:$AG23)>0,SUM($C23:$AG23),"") -> 165 | AI23: 121 | AJ23: 140 | AK23: =AJ23-AI23 -> 19 | AL23: =AJ23*AH23 -> 23100 | AM23: =AK23*AH23 -> 3135
B24: Gabapentin | C24: =RANDBETWEEN(1,10) -> 2 | D24: =RANDBETWEEN(1,10) -> 7 | E24: =RANDBETWEEN(1,10) -> 1 | F24: =RANDBETWEEN(1,10) -> 9 | G24: =RANDBETWEEN(1,10) -> 3 | H24: =RANDBETWEEN(1,10) -> 7 | I24: =RANDBETWEEN(1,10) -> 5 | J24: =RANDBETWEEN(1,10) -> 2 | ... AG24: =RANDBETWEEN(1,10) -> 2 | AH24: =IF(SUM($C24:$AG24)>0,SUM($C24:$AG24),"") -> 190 | AI24: 350 | AJ24: 390 | AK24: =AJ24-AI24 -> 40 | AL24: =AJ24*AH24 -> 74100 | AM24: =AK24*AH24 -> 7600
B25: Levothyroxine | C25: =RANDBETWEEN(1,10) -> 1 | D25: =RANDBETWEEN(1,10) -> 7 | E25: =RANDBETWEEN(1,10) -> 2 | F25: =RANDBETWEEN(1,10) -> 8 | G25: =RANDBETWEEN(1,10) -> 3 | H25: =RANDBETWEEN(1,10) -> 5 | I25: =RANDBETWEEN(1,10) -> 2 | J25: =RANDBETWEEN(1,10) -> 3 | ... AG25: =RANDBETWEEN(1,10) -> 9 | AH25: =IF(SUM($C25:$AG25)>0,SUM($C25:$AG25),"") -> 169 | AI25: 211 | AJ25: 240 | AK25: =AJ25-AI25 -> 29 | AL25: =AJ25*AH25 -> 40560 | AM25: =AK25*AH25 -> 4901
B26: Sertraline | C26: =RANDBETWEEN(1,10) -> 5 | D26: =RANDBETWEEN(1,10) -> 7 | E26: =RANDBETWEEN(1,10) -> 10 | F26: =RANDBETWEEN(1,10) -> 3 | G26: =RANDBETWEEN(1,10) -> 1 | H26: =RANDBETWEEN(1,10) -> 8 | I26: =RANDBETWEEN(1,10) -> 4 | J26: =RANDBETWEEN(1,10) -> 7 | ... AG26: =RANDBETWEEN(1,10) -> 5 | AH26: =IF(SUM($C26:$AG26)>0,SUM($C26:$AG26),"") -> 180 | AI26: 247 | AJ26: 280 | AK26: =AJ26-AI26 -> 33 | AL26: =AJ26*AH26 -> 50400 | AM26: =AK26*AH26 -> 5940
B27: Azithromycin | C27: =RANDBETWEEN(1,10) -> 8 | D27: =RANDBETWEEN(1,10) -> 3 | E27: =RANDBETWEEN(1,10) -> 6 | F27: =RANDBETWEEN(1,10) -> 6 | G27: =RANDBETWEEN(1,10) -> 1 | H27: =RANDBETWEEN(1,10) -> 8 | I27: =RANDBETWEEN(1,10) -> 9 | J27: =RANDBETWEEN(1,10) -> 9 | ... AG27: =RANDBETWEEN(1,10) -> 1 | AH27: =IF(SUM($C27:$AG27)>0,SUM($C27:$AG27),"") -> 176 | AI27: 286 | AJ27: 320 | AK27: =AJ27-AI27 -> 34 | AL27: =AJ27*AH27 -> 56320 | AM27: =AK27*AH27 -> 5984
B28: Losartan | C28: =RANDBETWEEN(1,10) -> 7 | D28: =RANDBETWEEN(1,10) -> 8 | E28: =RANDBETWEEN(1,10) -> 2 | F28: =RANDBETWEEN(1,10) -> 8 | G28: =RANDBETWEEN(1,10) -> 2 | H28: =RANDBETWEEN(1,10) -> 6 | I28: =RANDBETWEEN(1,10) -> 8 | J28: =RANDBETWEEN(1,10) -> 3 | ... AG28: =RANDBETWEEN(1,10) -> 10 | AH28: =IF(SUM($C28:$AG28)>0,SUM($C28:$AG28),"") -> 164 | AI28: 67 | AJ28: 80 | AK28: =AJ28-AI28 -> 13 | AL28: =AJ28*AH28 -> 13120 | AM28: =AK28*AH28 -> 2132
... B57: Lamotrigine | C57: =RANDBETWEEN(1,10) -> 1 | D57: =RANDBETWEEN(1,10) -> 9 | E57: =RANDBETWEEN(1,10) -> 9 | F57: =RANDBETWEEN(1,10) -> 4 | G57: =RANDBETWEEN(1,10) -> 4 | H57: =RANDBETWEEN(1,10) -> 8 | I57: =RANDBETWEEN(1,10) -> 6 | J57: =RANDBETWEEN(1,10) -> 7 | ... AG57: =RANDBETWEEN(1,10) -> 4 | AH57: =IF(SUM($C57:$AG57)>0,SUM($C57:$AG57),"") -> 180 | AI57: 340 | AJ57: 380 | AK57: =AJ57-AI57 -> 40 | AL57: =AJ57*AH57 -> 68400 | AM57: =AK57*AH57 -> 7200

Sheet June
C1: =TEXT(C2,"DDD") -> Sat | D1: =TEXT(D2,"DDD") -> Sun | E1: =TEXT(E2,"DDD") -> Mon | F1: =TEXT(F2,"DDD") -> Tue | G1: =TEXT(G2,"DDD") -> Wed | H1: =TEXT(H2,"DDD") -> Thu | I1: =TEXT(I2,"DDD") -> Fri | J1: =TEXT(J2,"DDD") -> Sat | ... AG1: =TEXT(AG2,"DDD") | AH1: Total Sales | AI1: Incoming price (Including GST) | AJ1: Sales price | AK1: Profit Margin | AL1: Total collection | AM1: Net collection | AO1: Month | AP1: June
B2: Product Name | C2: =IF(COLUMNS($C$2:C2)>DAY($AP$4),"",$AP$3+COLUMNS($C$2:C2)-1) -> 45444 | D2: =IF(COLUMNS($C$2:D2)>DAY($AP$4),"",$AP$3+COLUMNS($C$2:D2)-1) -> 45445 | E2: =IF(COLUMNS($C$2:E2)>DAY($AP$4),"",$AP$3+COLUMNS($C$2:E2)-1) -> 45446 | F2: =IF(COLUMNS($C$2:F2)>DAY($AP$4),"",$AP$3+COLUMNS($C$2:F2)-1) -> 45447 | G2: =IF(COLUMNS($C$2:G2)>DAY($AP$4),"",$AP$3+COLUMNS($C$2:G2)-1) -> 45448 | H2: =IF(COLUMNS($C$2:H2)>DAY($AP$4),"",$AP$3+COLUMNS($C$2:H2)-1) -> 45449 | I2: =IF(COLUMNS($C$2:I2)>DAY($AP$4),"",$AP$3+COLUMNS($C$2:I2)-1) -> 45450 | J2: =IF(COLUMNS($C$2:J2)>DAY($AP$4),"",$AP$3+COLUMNS($C$2:J2)-1) -> 45451 | ... AG2: =IF(COLUMNS($C$2:AG2)>DAY($AP$4),"",$AP$3+COLUMNS($C$2:AG2)-1) | AO2: Year | AP2: 2024
B3: Iodex | C3: =RANDBETWEEN(1,10) -> 7 | D3: =RANDBETWEEN(1,10) -> 7 | E3: =RANDBETWEEN(1,10) -> 3 | F3: =RANDBETWEEN(1,10) -> 9 | G3: =RANDBETWEEN(1,10) -> 6 | H3: =RANDBETWEEN(1,10) -> 5 | I3: =RANDBETWEEN(1,10) -> 7 | J3: =RANDBETWEEN(1,10) -> 5 | ... AF3: =RANDBETWEEN(1,10) -> 7 | AH3: =IF(SUM($C3:$AG3)>0,SUM($C3:$AG3),"") -> 165 | AI3: 40 | AJ3: 80 | AK3: =AJ3-AI3 -> 40 | AL3: =AJ3*AH3 -> 13200 | AM3: =AK3*AH3 -> 6600 | AO3: Starting Date | AP3: =DATE(AP2,MONTH(AP1&1),1) -> 45444
B4: Nimocet | C4: =RANDBETWEEN(1,10) -> 10 | D4: =RANDBETWEEN(1,10) -> 3 | E4: =RANDBETWEEN(1,10) -> 2 | F4: =RANDBETWEEN(1,10) -> 5 | G4: =RANDBETWEEN(1,10) -> 6 | H4: =RANDBETWEEN(1,10) -> 9 | I4: =RANDBETWEEN(1,10) -> 9 | J4: =RANDBETWEEN(1,10) -> 9 | ... AF4: =RANDBETWEEN(1,10) -> 8 | AH4: =IF(SUM($C4:$AG4)>0,SUM($C4:$AG4),"") -> 162 | AI4: 7 | AJ4: 15 | AK4: =AJ4-AI4 -> 8 | AL4: =AJ4*AH4 -> 2430 | AM4: =AK4*AH4 -> 1296 | AO4: Ending Date | AP4: =EOMONTH(AP3,0) -> 45473
B5: Paracetamol | C5: =RANDBETWEEN(1,10) -> 1 | D5: =RANDBETWEEN(1,10) -> 1 | E5: =RANDBETWEEN(1,10) -> 6 | F5: =RANDBETWEEN(1,10) -> 3 | G5: =RANDBETWEEN(1,10) -> 6 | H5: =RANDBETWEEN(1,10) -> 5 | I5: =RANDBETWEEN(1,10) -> 4 | J5: =RANDBETWEEN(1,10) -> 4 | ... AF5: =RANDBETWEEN(1,10) -> 1 | AH5: =IF(SUM($C5:$AG5)>0,SUM($C5:$AG5),"") -> 165 | AI5: 5 | AJ5: 10 | AK5: =AJ5-AI5 -> 5 | AL5: =AJ5*AH5 -> 1650 | AM5: =AK5*AH5 -> 825
B6: Monocef | C6: =RANDBETWEEN(1,10) -> 2 | D6: =RANDBETWEEN(1,10) -> 7 | E6: =RANDBETWEEN(1,10) -> 2 | F6: =RANDBETWEEN(1,10) -> 7 | G6: =RANDBETWEEN(1,10) -> 1 | H6: =RANDBETWEEN(1,10) -> 8 | I6: =RANDBETWEEN(1,10) -> 1 | J6: =RANDBETWEEN(1,10) -> 6 | ... AF6: =RANDBETWEEN(1,10) -> 3 | AH6: =IF(SUM($C6:$AG6)>0,SUM($C6:$AG6),"") -> 152 | AI6: 45 | AJ6: 80 | AK6: =AJ6-AI6 -> 35 | AL6: =AJ6*AH6 -> 12160 | AM6: =AK6*AH6 -> 5320
B7: Cyclopalm | C7: =RANDBETWEEN(1,10) -> 7 | D7: =RANDBETWEEN(1,10) -> 10 | E7: =RANDBETWEEN(1,10) -> 5 | F7: =RANDBETWEEN(1,10) -> 10 | G7: =RANDBETWEEN(1,10) -> 6 | H7: =RANDBETWEEN(1,10) -> 6 | I7: =RANDBETWEEN(1,10) -> 10 | J7: =RANDBETWEEN(1,10) -> 4 | ... AF7: =RANDBETWEEN(1,10) -> 9 | AH7: =IF(SUM($C7:$AG7)>0,SUM($C7:$AG7),"") -> 174 | AI7: 392 | AJ7: 420 | AK7: =AJ7-AI7 -> 28 | AL7: =AJ7*AH7 -> 73080 | AM7: =AK7*AH7 -> 4872 | AO7: Expanses
B8: Cetaphil | C8: =RANDBETWEEN(1,10) -> 7 | D8: =RANDBETWEEN(1,10) -> 8 | E8: =RANDBETWEEN(1,10) -> 6 | F8: =RANDBETWEEN(1,10) -> 1 | G8: =RANDBETWEEN(1,10) -> 2 | H8: =RANDBETWEEN(1,10) -> 8 | I8: =RANDBETWEEN(1,10) -> 3 | J8: =RANDBETWEEN(1,10) -> 3 | ... AF8: =RANDBETWEEN(1,10) -> 10 | AH8: =IF(SUM($C8:$AG8)>0,SUM($C8:$AG8),"") -> 152 | AI8: 86 | AJ8: 100 | AK8: =AJ8-AI8 -> 14 | AL8: =AJ8*AH8 -> 15200 | AM8: =AK8*AH8 -> 2128 | AO8: Employee Salary
B9: Acetaminophen | C9: =RANDBETWEEN(1,10) -> 10 | D9: =RANDBETWEEN(1,10) -> 8 | E9: =RANDBETWEEN(1,10) -> 7 | F9: =RANDBETWEEN(1,10) -> 2 | G9: =RANDBETWEEN(1,10) -> 5 | H9: =RANDBETWEEN(1,10) -> 4 | I9: =RANDBETWEEN(1,10) -> 4 | J9: =RANDBETWEEN(1,10) -> 6 | ... AF9: =RANDBETWEEN(1,10) -> 6 | AH9: =IF(SUM($C9:$AG9)>0,SUM($C9:$AG9),"") -> 164 | AI9: 271 | AJ9: 300 | AK9: =AJ9-AI9 -> 29 | AL9: =AJ9*AH9 -> 49200 | AM9: =AK9*AH9 -> 4756 | AO9: Kaishav(Owner) | AP9: ='Attendence (June)'!AL3 -> 48333.333
B10: Ibuprofen | C10: =RANDBETWEEN(1,10) -> 1 | D10: =RANDBETWEEN(1,10) -> 3 | E10: =RANDBETWEEN(1,10) -> 5 | F10: =RANDBETWEEN(1,10) -> 6 | G10: =RANDBETWEEN(1,10) -> 8 | H10: =RANDBETWEEN(1,10) -> 8 | I10: =RANDBETWEEN(1,10) -> 4 | J10: =RANDBETWEEN(1,10) -> 1 | ... AF10: =RANDBETWEEN(1,10) -> 9 | AH10: =IF(SUM($C10:$AG10)>0,SUM($C10:$AG10),"") -> 167 | AI10: 226 | AJ10: 250 | AK10: =AJ10-AI10 -> 24 | AL10: =AJ10*AH10 -> 41750 | AM10: =AK10*AH10 -> 4008 | AO10: Raman | AP10: ='Attendence (June)'!AL4 -> 14000
B11: Aspirin | C11: =RANDBETWEEN(1,10) -> 3 | D11: =RANDBETWEEN(1,10) -> 6 | E11: =RANDBETWEEN(1,10) -> 5 | F11: =RANDBETWEEN(1,10) -> 2 | G11: =RANDBETWEEN(1,10) -> 10 | H11: =RANDBETWEEN(1,10) -> 8 | I11: =RANDBETWEEN(1,10) -> 10 | J11: =RANDBETWEEN(1,10) -> 10 | ... AF11: =RANDBETWEEN(1,10) -> 3 | AH11: =IF(SUM($C11:$AG11)>0,SUM($C11:$AG11),"") -> 152 | AI11: 390 | AJ11: 450 | AK11: =AJ11-AI11 -> 60 | AL11: =AJ11*AH11 -> 68400 | AM11: =AK11*AH11 -> 9120 | AO11: Sohan | AP11: ='Attendence (June)'!AL5 -> 17400
B12: Amoxicillin | C12: =RANDBETWEEN(1,10) -> 7 | D12: =RANDBETWEEN(1,10) -> 9 | E12: =RANDBETWEEN(1,10) -> 6 | F12: =RANDBETWEEN(1,10) -> 7 | G12: =RANDBETWEEN(1,10) -> 2 | H12: =RANDBETWEEN(1,10) -> 6 | I12: =RANDBETWEEN(1,10) -> 4 | J12: =RANDBETWEEN(1,10) -> 8 | ... AF12: =RANDBETWEEN(1,10) -> 4 | AH12: =IF(SUM($C12:$AG12)>0,SUM($C12:$AG12),"") -> 167 | AI12: 379 | AJ12: 430 | AK12: =AJ12-AI12 -> 51 | AL12: =AJ12*AH12 -> 71810 | AM12: =AK12*AH12 -> 8517 | AO12: Tilak | AP12: ='Attendence (June)'!AL6 -> 9333.3333
B13: Ciprofloxacin | C13: =RANDBETWEEN(1,10) -> 5 | D13: =RANDBETWEEN(1,10) -> 1 | E13: =RANDBETWEEN(1,10) -> 7 | F13: =RANDBETWEEN(1,10) -> 4 | G13: =RANDBETWEEN(1,10) -> 4 | H13: =RANDBETWEEN(1,10) -> 2 | I13: =RANDBETWEEN(1,10) -> 6 | J13: =RANDBETWEEN(1,10) -> 2 | ... AF13: =RANDBETWEEN(1,10) -> 7 | AH13: =IF(SUM($C13:$AG13)>0,SUM($C13:$AG13),"") -> 163 | AI13: 368 | AJ13: 435 | AK13: =AJ13-AI13 -> 67 | AL13: =AJ13*AH13 -> 70905 | AM13: =AK13*AH13 -> 10921 | AO13: Bill to pay | AP13: 10000
B14: Lisinopril | C14: =RANDBETWEEN(1,10) -> 5 | D14: =RANDBETWEEN(1,10) -> 8 | E14: =RANDBETWEEN(1,10) -> 5 | F14: =RANDBETWEEN(1,10) -> 8 | G14: =RANDBETWEEN(1,10) -> 2 | H14: =RANDBETWEEN(1,10) -> 8 | I14: =RANDBETWEEN(1,10) -> 10 | J14: =RANDBETWEEN(1,10) -> 2 | ... AF14: =RANDBETWEEN(1,10) -> 9 | AH14: =IF(SUM($C14:$AG14)>0,SUM($C14:$AG14),"") -> 163 | AI14: 88 | AJ14: 99 | AK14: =AJ14-AI14 -> 11 | AL14: =AJ14*AH14 -> 16137 | AM14: =AK14*AH14 -> 1793 | AO14: other | AP14: 2000
B15: Atorvastatin | C15: =RANDBETWEEN(1,10) -> 7 | D15: =RANDBETWEEN(1,10) -> 5 | E15: =RANDBETWEEN(1,10) -> 7 | F15: =RANDBETWEEN(1,10) -> 1 | G15: =RANDBETWEEN(1,10) -> 5 | H15: =RANDBETWEEN(1,10) -> 2 | I15: =RANDBETWEEN(1,10) -> 5 | J15: =RANDBETWEEN(1,10) -> 9 | ... AF15: =RANDBETWEEN(1,10) -> 10 | AH15: =IF(SUM($C15:$AG15)>0,SUM($C15:$AG15),"") -> 145 | AI15: 391 | AJ15: 500 | AK15: =AJ15-AI15 -> 109 | AL15: =AJ15*AH15 -> 72500 | AM15: =AK15*AH15 -> 15805 | AO15: Net collection | AP15: =SUM(AM3:AM57) -> 285537
B16: Metformin | C16: =RANDBETWEEN(1,10) -> 7 | D16: =RANDBETWEEN(1,10) -> 9 | E16: =RANDBETWEEN(1,10) -> 5 | F16: =RANDBETWEEN(1,10) -> 9 | G16: =RANDBETWEEN(1,10) -> 10 | H16: =RANDBETWEEN(1,10) -> 6 | I16: =RANDBETWEEN(1,10) -> 9 | J16: =RANDBETWEEN(1,10) -> 4 | ... AF16: =RANDBETWEEN(1,10) -> 2 | AH16: =IF(SUM($C16:$AG16)>0,SUM($C16:$AG16),"") -> 166 | AI16: 261 | AJ16: 300 | AK16: =AJ16-AI16 -> 39 | AL16: =AJ16*AH16 -> 49800 | AM16: =AK16*AH16 -> 6474 | AO16: Net Income | AP16: =AP15-(AP9+AP10+AP11+AP12+AP13+AP14) -> 184470.33
B17: Simvastatin | C17: =RANDBETWEEN(1,10) -> 7 | D17: =RANDBETWEEN(1,10) -> 9 | E17: =RANDBETWEEN(1,10) -> 9 | F17: =RANDBETWEEN(1,10) -> 3 | G17: =RANDBETWEEN(1,10) -> 6 | H17: =RANDBETWEEN(1,10) -> 7 | I17: =RANDBETWEEN(1,10) -> 5 | J17: =RANDBETWEEN(1,10) -> 1 | ... AF17: =RANDBETWEEN(1,10) -> 5 | AH17: =IF(SUM($C17:$AG17)>0,SUM($C17:$AG17),"") -> 182 | AI17: 67 | AJ17: 99 | AK17: =AJ17-AI17 -> 32 | AL17: =AJ17*AH17 -> 18018 | AM17: =AK17*AH17 -> 5824
B18: Omeprazole | C18: =RANDBETWEEN(1,10) -> 3 | D18: =RANDBETWEEN(1,10) -> 6 | E18: =RANDBETWEEN(1,10) -> 9 | F18: =RANDBETWEEN(1,10) -> 8 | G18: =RANDBETWEEN(1,10) -> 5 | H18: =RANDBETWEEN(1,10) -> 4 | I18: =RANDBETWEEN(1,10) -> 10 | J18: =RANDBETWEEN(1,10) -> 9 | ... AF18: =RANDBETWEEN(1,10) -> 2 | AH18: =IF(SUM($C18:$AG18)>0,SUM($C18:$AG18),"") -> 168 | AI18: 138 | AJ18: 150 | AK18: =AJ18-AI18 -> 12 | AL18: =AJ18*AH18 -> 25200 | AM18: =AK18*AH18 -> 2016
B19: Clopidogrel | C19: =RANDBETWEEN(1,10) -> 7 | D19: =RANDBETWEEN(1,10) -> 7 | E19: =RANDBETWEEN(1,10) -> 2 | F19: =RANDBETWEEN(1,10) -> 4 | G19: =RANDBETWEEN(1,10) -> 5 | H19: =RANDBETWEEN(1,10) -> 2 | I19: =RANDBETWEEN(1,10) -> 4 | J19: =RANDBETWEEN(1,10) -> 5 | ... AF19: =RANDBETWEEN(1,10) -> 3 | AH19: =IF(SUM($C19:$AG19)>0,SUM($C19:$AG19),"") -> 156 | AI19: 60 | AJ19: 80 | AK19: =AJ19-AI19 -> 20 | AL19: =AJ19*AH19 -> 12480 | AM19: =AK19*AH19 -> 3120
B20: Metoprolol | C20: =RANDBETWEEN(1,10) -> 10 | D20: =RANDBETWEEN(1,10) -> 5 | E20: =RANDBETWEEN(1,10) -> 5 | F20: =RANDBETWEEN(1,10) -> 6 | G20: =RANDBETWEEN(1,10) -> 9 | H20: =RANDBETWEEN(1,10) -> 6 | I20: =RANDBETWEEN(1,10) -> 10 | J20: =RANDBETWEEN(1,10) -> 5 | ... AF20: =RANDBETWEEN(1,10) -> 8 | AH20: =IF(SUM($C20:$AG20)>0,SUM($C20:$AG20),"") -> 176 | AI20: 44 | AJ20: 50 | AK20: =AJ20-AI20 -> 6 | AL20: =AJ20*AH20 -> 8800 | AM20: =AK20*AH20 -> 1056
B21: Amlodipine | C21: =RANDBETWEEN(1,10) -> 3 | D21: =RANDBETWEEN(1,10) -> 9 | E21: =RANDBETWEEN(1,10) -> 4 | F21: =RANDBETWEEN(1,10) -> 10 | G21: =RANDBETWEEN(1,10) -> 3 | H21: =RANDBETWEEN(1,10) -> 9 | I21: =RANDBETWEEN(1,10) -> 2 | J21: =RANDBETWEEN(1,10) -> 1 | ... AF21: =RANDBETWEEN(1,10) -> 3 | AH21: =IF(SUM($C21:$AG21)>0,SUM($C21:$AG21),"") -> 182 | AI21: 308 | AJ21: 320 | AK21: =AJ21-AI21 -> 12 | AL21: =AJ21*AH21 -> 58240 | AM21: =AK21*AH21 -> 2184
B22: Alprazolam | C22: =RANDBETWEEN(1,10) -> 7 | D22: =RANDBETWEEN(1,10) -> 3 | E22: =RANDBETWEEN(1,10) -> 1 | F22: =RANDBETWEEN(1,10) -> 10 | G22: =RANDBETWEEN(1,10) -> 8 | H22: =RANDBETWEEN(1,10) -> 8 | I22: =RANDBETWEEN(1,10) -> 7 | J22: =RANDBETWEEN(1,10) -> 4 | ... AF22: =RANDBETWEEN(1,10) -> 8 | AH22: =IF(SUM($C22:$AG22)>0,SUM($C22:$AG22),"") -> 168 | AI22: 234 | AJ22: 250 | AK22: =AJ22-AI22 -> 16 | AL22: =AJ22*AH22 -> 42000 | AM22: =AK22*AH22 -> 2688
B23: Hydrocodone | C23: =RANDBETWEEN(1,10) -> 9 | D23: =RANDBETWEEN(1,10) -> 1 | E23: =RANDBETWEEN(1,10) -> 3 | F23: =RANDBETWEEN(1,10) -> 3 | G23: =RANDBETWEEN(1,10) -> 9 | H23: =RANDBETWEEN(1,10) -> 9 | I23: =RANDBETWEEN(1,10) -> 6 | J23: =RANDBETWEEN(1,10) -> 8 | ... AF23: =RANDBETWEEN(1,10) -> 5 | AH23: =IF(SUM($C23:$AG23)>0,SUM($C23:$AG23),"") -> 173 | AI23: 121 | AJ23: 140 | AK23: =AJ23-AI23 -> 19 | AL23: =AJ23*AH23 -> 24220 | AM23: =AK23*AH23 -> 3287
B24: Gabapentin | C24: =RANDBETWEEN(1,10) -> 2 | D24: =RANDBETWEEN(1,10) -> 1 | E24: =RANDBETWEEN(1,10) -> 3 | F24: =RANDBETWEEN(1,10) -> 8 | G24: =RANDBETWEEN(1,10) -> 10 | H24: =RANDBETWEEN(1,10) -> 7 | I24: =RANDBETWEEN(1,10) -> 3 | J24: =RANDBETWEEN(1,10) -> 5 | ... AF24: =RANDBETWEEN(1,10) -> 10 | AH24: =IF(SUM($C24:$AG24)>0,SUM($C24:$AG24),"") -> 182 | AI24: 350 | AJ24: 390 | AK24: =AJ24-AI24 -> 40 | AL24: =AJ24*AH24 -> 70980 | AM24: =AK24*AH24 -> 7280
B25: Levothyroxine | C25: =RANDBETWEEN(1,10) -> 2 | D25: =RANDBETWEEN(1,10) -> 6 | E25: =RANDBETWEEN(1,10) -> 8 | F25: =RANDBETWEEN(1,10) -> 4 | G25: =RANDBETWEEN(1,10) -> 1 | H25: =RANDBETWEEN(1,10) -> 4 | I25: =RANDBETWEEN(1,10) -> 8 | J25: =RANDBETWEEN(1,10) -> 10 | ... AF25: =RANDBETWEEN(1,10) -> 10 | AH25: =IF(SUM($C25:$AG25)>0,SUM($C25:$AG25),"") -> 159 | AI25: 211 | AJ25: 240 | AK25: =AJ25-AI25 -> 29 | AL25: =AJ25*AH25 -> 38160 | AM25: =AK25*AH25 -> 4611
B26: Sertraline | C26: =RANDBETWEEN(1,10) -> 8 | D26: =RANDBETWEEN(1,10) -> 5 | E26: =RANDBETWEEN(1,10) -> 1 | F26: =RANDBETWEEN(1,10) -> 9 | G26: =RANDBETWEEN(1,10) -> 5 | H26: =RANDBETWEEN(1,10) -> 2 | I26: =RANDBETWEEN(1,10) -> 4 | J26: =RANDBETWEEN(1,10) -> 8 | ... AF26: =RANDBETWEEN(1,10) -> 6 | AH26: =IF(SUM($C26:$AG26)>0,SUM($C26:$AG26),"") -> 181 | AI26: 247 | AJ26: 280 | AK26: =AJ26-AI26 -> 33 | AL26: =AJ26*AH26 -> 50680 | AM26: =AK26*AH26 -> 5973
B27: Azithromycin | C27: =RANDBETWEEN(1,10) -> 2 | D27: =RANDBETWEEN(1,10) -> 8 | E27: =RANDBETWEEN(1,10) -> 3 | F27: =RANDBETWEEN(1,10) -> 8 | G27: =RANDBETWEEN(1,10) -> 2 | H27: =RANDBETWEEN(1,10) -> 6 | I27: =RANDBETWEEN(1,10) -> 2 | J27: =RANDBETWEEN(1,10) -> 8 | ... AF27: =RANDBETWEEN(1,10) -> 4 | AH27: =IF(SUM($C27:$AG27)>0,SUM($C27:$AG27),"") -> 144 | AI27: 286 | AJ27: 320 | AK27: =AJ27-AI27 -> 34 | AL27: =AJ27*AH27 -> 46080 | AM27: =AK27*AH27 -> 4896
B28: Losartan | C28: =RANDBETWEEN(1,10) -> 4 | D28: =RANDBETWEEN(1,10) -> 1 | E28: =RANDBETWEEN(1,10) -> 6 | F28: =RANDBETWEEN(1,10) -> 2 | G28: =RANDBETWEEN(1,10) -> 9 | H28: =RANDBETWEEN(1,10) -> 5 | I28: =RANDBETWEEN(1,10) -> 7 | J28: =RANDBETWEEN(1,10) -> 10 | ... AF28: =RANDBETWEEN(1,10) -> 3 | AH28: =IF(SUM($C28:$AG28)>0,SUM($C28:$AG28),"") -> 161 | AI28: 67 | AJ28: 80 | AK28: =AJ28-AI28 -> 13 | AL28: =AJ28*AH28 -> 12880 | AM28: =AK28*AH28 -> 2093
... B57: Lamotrigine | C57: =RANDBETWEEN(1,10) -> 5 | D57: =RANDBETWEEN(1,10) -> 6 | E57: =RANDBETWEEN(1,10) -> 2 | F57: =RANDBETWEEN(1,10) -> 8 | G57: =RANDBETWEEN(1,10) -> 6 | H57: =RANDBETWEEN(1,10) -> 1 | I57: =RANDBETWEEN(1,10) -> 3 | J57: =RANDBETWEEN(1,10) -> 4 | ... AF57: =RANDBETWEEN(1,10) -> 6 | AH57: =IF(SUM($C57:$AG57)>0,SUM($C57:$AG57),"") -> 137 | AI57: 340 | AJ57: 380 | AK57: =AJ57-AI57 -> 40 | AL57: =AJ57*AH57 -> 52060 | AM57: =AK57*AH57 -> 5480

Sheet July
C1: =TEXT(C2,"DDD") -> Mon | D1: =TEXT(D2,"DDD") -> Tue | E1: =TEXT(E2,"DDD") -> Wed | F1: =TEXT(F2,"DDD") -> Thu | G1: =TEXT(G2,"DDD") -> Fri | H1: =TEXT(H2,"DDD") -> Sat | I1: =TEXT(I2,"DDD") -> Sun | J1: =TEXT(J2,"DDD") -> Mon | ... AG1: =TEXT(AG2,"DDD") -> Wed | AH1: Total Sales | AI1: Incoming price (Including GST) | AJ1: Sales price | AK1: Profit Margin | AL1: Total collection | AM1: Net collection | AO1: Month | AP1: July
B2: Product Name | C2: =IF(COLUMNS($C$2:C2)>DAY($AP$4),"",$AP$3+COLUMNS($C$2:C2)-1) -> 45474 | D2: =IF(COLUMNS($C$2:D2)>DAY($AP$4),"",$AP$3+COLUMNS($C$2:D2)-1) -> 45475 | E2: =IF(COLUMNS($C$2:E2)>DAY($AP$4),"",$AP$3+COLUMNS($C$2:E2)-1) -> 45476 | F2: =IF(COLUMNS($C$2:F2)>DAY($AP$4),"",$AP$3+COLUMNS($C$2:F2)-1) -> 45477 | G2: =IF(COLUMNS($C$2:G2)>DAY($AP$4),"",$AP$3+COLUMNS($C$2:G2)-1) -> 45478 | H2: =IF(COLUMNS($C$2:H2)>DAY($AP$4),"",$AP$3+COLUMNS($C$2:H2)-1) -> 45479 | I2: =IF(COLUMNS($C$2:I2)>DAY($AP$4),"",$AP$3+COLUMNS($C$2:I2)-1) -> 45480 | J2: =IF(COLUMNS($C$2:J2)>DAY($AP$4),"",$AP$3+COLUMNS($C$2:J2)-1) -> 45481 | ... AG2: =IF(COLUMNS($C$2:AG2)>DAY($AP$4),"",$AP$3+COLUMNS($C$2:AG2)-1) -> 45504 | AO2: Year | AP2: 2024
B3: Iodex | C3: =RANDBETWEEN(1,10) -> 5 | D3: =RANDBETWEEN(1,10) -> 9 | E3: =RANDBETWEEN(1,10) -> 6 | F3: =RANDBETWEEN(1,10) -> 6 | G3: =RANDBETWEEN(1,10) -> 1 | H3: =RANDBETWEEN(1,10) -> 9 | I3: =RANDBETWEEN(1,10) -> 5 | J3: =RANDBETWEEN(1,10) -> 10 | ... AG3: =RANDBETWEEN(1,10) -> 10 | AH3: =IF(SUM($C3:$AG3)>0,SUM($C3:$AG3),"") -> 169 | AI3: 40 | AJ3: 80 | AK3: =AJ3-AI3 -> 40 | AL3: =AJ3*AH3 -> 13520 | AM3: =AK3*AH3 -> 6760 | AO3: Starting Date | AP3: =DATE(AP2,MONTH(AP1&1),1) -> 45474
B4: Nimocet | C4: =RANDBETWEEN(1,10) -> 10 | D4: =RANDBETWEEN(1,10) -> 6 | E4: =RANDBETWEEN(1,10) -> 4 | F4: =RANDBETWEEN(1,10) -> 3 | G4: =RANDBETWEEN(1,10) -> 1 | H4: =RANDBETWEEN(1,10) -> 10 | I4: =RANDBETWEEN(1,10) -> 5 | J4: =RANDBETWEEN(1,10) -> 4 | ... AG4: =RANDBETWEEN(1,10) -> 6 | AH4: =IF(SUM($C4:$AG4)>0,SUM($C4:$AG4),"") -> 181 | AI4: 7 | AJ4: 15 | AK4: =AJ4-AI4 -> 8 | AL4: =AJ4*AH4 -> 2715 | AM4: =AK4*AH4 -> 1448 | AO4: Ending Date | AP4: =EOMONTH(AP3,0) -> 45504
B5: Paracetamol | C5: =RANDBETWEEN(1,10) -> 1 | D5: =RANDBETWEEN(1,10) -> 5 | E5: =RANDBETWEEN(1,10) -> 4 | F5: =RANDBETWEEN(1,10) -> 8 | G5: =RANDBETWEEN(1,10) -> 7 | H5: =RANDBETWEEN(1,10) -> 7 | I5: =RANDBETWEEN(1,10) -> 2 | J5: =RANDBETWEEN(1,10) -> 8 | ... AG5: =RANDBETWEEN(1,10) -> 5 | AH5: =IF(SUM($C5:$AG5)>0,SUM($C5:$AG5),"") -> 216 | AI5: 5 | AJ5: 10 | AK5: =AJ5-AI5 -> 5 | AL5: =AJ5*AH5 -> 2160 | AM5: =AK5*AH5 -> 1080
B6: Monocef | C6: =RANDBETWEEN(1,10) -> 5 | D6: =RANDBETWEEN(1,10) -> 9 | E6: =RANDBETWEEN(1,10) -> 7 | F6: =RANDBETWEEN(1,10) -> 9 | G6: =RANDBETWEEN(1,10) -> 7 | H6: =RANDBETWEEN(1,10) -> 8 | I6: =RANDBETWEEN(1,10) -> 8 | J6: =RANDBETWEEN(1,10) -> 7 | ... AG6: =RANDBETWEEN(1,10) -> 9 | AH6: =IF(SUM($C6:$AG6)>0,SUM($C6:$AG6),"") -> 177 | AI6: 45 | AJ6: 80 | AK6: =AJ6-AI6 -> 35 | AL6: =AJ6*AH6 -> 14160 | AM6: =AK6*AH6 -> 6195
B7: Cyclopalm | C7: =RANDBETWEEN(1,10) -> 10 | D7: =RANDBETWEEN(1,10) -> 5 | E7: =RANDBETWEEN(1,10) -> 1 | F7: =RANDBETWEEN(1,10) -> 5 | G7: =RANDBETWEEN(1,10) -> 8 | H7: =RANDBETWEEN(1,10) -> 8 | I7: =RANDBETWEEN(1,10) -> 9 | J7: =RANDBETWEEN(1,10) -> 6 | ... AG7: =RANDBETWEEN(1,10) -> 7 | AH7: =IF(SUM($C7:$AG7)>0,SUM($C7:$AG7),"") -> 163 | AI7: 392 | AJ7: 420 | AK7: =AJ7-AI7 -> 28 | AL7: =AJ7*AH7 -> 68460 | AM7: =AK7*AH7 -> 4564 | AO7: Expanses
B8: Cetaphil | C8: =RANDBETWEEN(1,10) -> 3 | D8: =RANDBETWEEN(1,10) -> 5 | E8: =RANDBETWEEN(1,10) -> 9 | F8: =RANDBETWEEN(1,10) -> 2 | G8: =RANDBETWEEN(1,10) -> 3 | H8: =RANDBETWEEN(1,10) -> 10 | I8: =RANDBETWEEN(1,10) -> 9 | J8: =RANDBETWEEN(1,10) -> 3 | ... AG8: =RANDBETWEEN(1,10) -> 6 | AH8: =IF(SUM($C8:$AG8)>0,SUM($C8:$AG8),"") -> 170 | AI8: 86 | AJ8: 100 | AK8: =AJ8-AI8 -> 14 | AL8: =AJ8*AH8 -> 17000 | AM8: =AK8*AH8 -> 2380 | AO8: Employee Salary
B9: Acetaminophen | C9: =RANDBETWEEN(1,10) -> 7 | D9: =RANDBETWEEN(1,10) -> 6 | E9: =RANDBETWEEN(1,10) -> 9 | F9: =RANDBETWEEN(1,10) -> 10 | G9: =RANDBETWEEN(1,10) -> 8 | H9: =RANDBETWEEN(1,10) -> 2 | I9: =RANDBETWEEN(1,10) -> 8 | J9: =RANDBETWEEN(1,10) -> 5 | ... AG9: =RANDBETWEEN(1,10) -> 6 | AH9: =IF(SUM($C9:$AG9)>0,SUM($C9:$AG9),"") -> 194 | AI9: 271 | AJ9: 300 | AK9: =AJ9-AI9 -> 29 | AL9: =AJ9*AH9 -> 58200 | AM9: =AK9*AH9 -> 5626 | AO9: Kaishav(Owner) | AP9: ='Attendence (July)'!AL3 -> 48333.333
B10: Ibuprofen | C10: =RANDBETWEEN(1,10) -> 8 | D10: =RANDBETWEEN(1,10) -> 1 | E10: =RANDBETWEEN(1,10) -> 2 | F10: =RANDBETWEEN(1,10) -> 10 | G10: =RANDBETWEEN(1,10) -> 5 | H10: =RANDBETWEEN(1,10) -> 2 | I10: =RANDBETWEEN(1,10) -> 6 | J10: =RANDBETWEEN(1,10) -> 3 | ... AG10: =RANDBETWEEN(1,10) -> 5 | AH10: =IF(SUM($C10:$AG10)>0,SUM($C10:$AG10),"") -> 158 | AI10: 226 | AJ10: 250 | AK10: =AJ10-AI10 -> 24 | AL10: =AJ10*AH10 -> 39500 | AM10: =AK10*AH10 -> 3792 | AO10: Raman | AP10: ='Attendence (July)'!AL4 -> 15000
B11: Aspirin | C11: =RANDBETWEEN(1,10) -> 4 | D11: =RANDBETWEEN(1,10) -> 3 | E11: =RANDBETWEEN(1,10) -> 9 | F11: =RANDBETWEEN(1,10) -> 4 | G11: =RANDBETWEEN(1,10) -> 4 | H11: =RANDBETWEEN(1,10) -> 8 | I11: =RANDBETWEEN(1,10) -> 6 | J11: =RANDBETWEEN(1,10) -> 6 | ... AG11: =RANDBETWEEN(1,10) -> 5 | AH11: =IF(SUM($C11:$AG11)>0,SUM($C11:$AG11),"") -> 147 | AI11: 390 | AJ11: 450 | AK11: =AJ11-AI11 -> 60 | AL11: =AJ11*AH11 -> 66150 | AM11: =AK11*AH11 -> 8820 | AO11: Sohan | AP11: ='Attendence (July)'!AL5 -> 18000
B12: Amoxicillin | C12: =RANDBETWEEN(1,10) -> 7 | D12: =RANDBETWEEN(1,10) -> 5 | E12: =RANDBETWEEN(1,10) -> 3 | F12: =RANDBETWEEN(1,10) -> 7 | G12: =RANDBETWEEN(1,10) -> 1 | H12: =RANDBETWEEN(1,10) -> 3 | I12: =RANDBETWEEN(1,10) -> 2 | J12: =RANDBETWEEN(1,10) -> 8 | ... AG12: =RANDBETWEEN(1,10) -> 4 | AH12: =IF(SUM($C12:$AG12)>0,SUM($C12:$AG12),"") -> 167 | AI12: 379 | AJ12: 430 | AK12: =AJ12-AI12 -> 51 | AL12: =AJ12*AH12 -> 71810 | AM12: =AK12*AH12 -> 8517 | AO12: Tilak | AP12: ='Attendence (July)'!AL6 -> 9333.3333
B13: Ciprofloxacin | C13: =RANDBETWEEN(1,10) -> 8 | D13: =RANDBETWEEN(1,10) -> 4 | E13: =RANDBETWEEN(1,10) -> 5 | F13: =RANDBETWEEN(1,10) -> 8 | G13: =RANDBETWEEN(1,10) -> 7 | H13: =RANDBETWEEN(1,10) -> 1 | I13: =RANDBETWEEN(1,10) -> 9 | J13: =RANDBETWEEN(1,10) -> 7 | ... AG13: =RANDBETWEEN(1,10) -> 8 | AH13: =IF(SUM($C13:$AG13)>0,SUM($C13:$AG13),"") -> 161 | AI13: 368 | AJ13: 435 | AK13: =AJ13-AI13 -> 67 | AL13: =AJ13*AH13 -> 70035 | AM13: =AK13*AH13 -> 10787 | AO13: Bill to pay | AP13: 10000
B14: Lisinopril | C14: =RANDBETWEEN(1,10) -> 10 | D14: =RANDBETWEEN(1,10) -> 2 | E14: =RANDBETWEEN(1,10) -> 8 | F14: =RANDBETWEEN(1,10) -> 8 | G14: =RANDBETWEEN(1,10) -> 10 | H14: =RANDBETWEEN(1,10) -> 3 | I14: =RANDBETWEEN(1,10) -> 5 | J14: =RANDBETWEEN(1,10) -> 10 | ... AG14: =RANDBETWEEN(1,10) -> 2 | AH14: =IF(SUM($C14:$AG14)>0,SUM($C14:$AG14),"") -> 215 | AI14: 88 | AJ14: 99 | AK14: =AJ14-AI14 -> 11 | AL14: =AJ14*AH14 -> 21285 | AM14: =AK14*AH14 -> 2365 | AO14: other | AP14: 2000
B15: Atorvastatin | C15: =RANDBETWEEN(1,10) -> 3 | D15: =RANDBETWEEN(1,10) -> 6 | E15: =RANDBETWEEN(1,10) -> 8 | F15: =RANDBETWEEN(1,10) -> 8 | G15: =RANDBETWEEN(1,10) -> 3 | H15: =RANDBETWEEN(1,10) -> 10 | I15: =RANDBETWEEN(1,10) -> 3 | J15: =RANDBETWEEN(1,10) -> 3 | ... AG15: =RANDBETWEEN(1,10) -> 5 | AH15: =IF(SUM($C15:$AG15)>0,SUM($C15:$AG15),"") -> 173 | AI15: 391 | AJ15: 500 | AK15: =AJ15-AI15 -> 109 | AL15: =AJ15*AH15 -> 86500 | AM15: =AK15*AH15 -> 18857 | AO15: Net collection | AP15: =SUM(AM3:AM57) -> 298042
B16: Metformin | C16: =RANDBETWEEN(1,10) -> 7 | D16: =RANDBETWEEN(1,10) -> 9 | E16: =RANDBETWEEN(1,10) -> 2 | F16: =RANDBETWEEN(1,10) -> 5 | G16: =RANDBETWEEN(1,10) -> 4 | H16: =RANDBETWEEN(1,10) -> 7 | I16: =RANDBETWEEN(1,10) -> 3 | J16: =RANDBETWEEN(1,10) -> 3 | ... AG16: =RANDBETWEEN(1,10) -> 4 | AH16: =IF(SUM($C16:$AG16)>0,SUM($C16:$AG16),"") -> 182 | AI16: 261 | AJ16: 300 | AK16: =AJ16-AI16 -> 39 | AL16: =AJ16*AH16 -> 54600 | AM16: =AK16*AH16 -> 7098 | AO16: Net Income | AP16: =AP15-(AP9+AP10+AP11+AP12+AP13+AP14) -> 195375.33
B17: Simvastatin | C17: =RANDBETWEEN(1,10) -> 1 | D17: =RANDBETWEEN(1,10) -> 4 | E17: =RANDBETWEEN(1,10) -> 4 | F17: =RANDBETWEEN(1,10) -> 1 | G17: =RANDBETWEEN(1,10) -> 6 | H17: =RANDBETWEEN(1,10) -> 4 | I17: =RANDBETWEEN(1,10) -> 9 | J17: =RANDBETWEEN(1,10) -> 8 | ... AG17: =RANDBETWEEN(1,10) -> 10 | AH17: =IF(SUM($C17:$AG17)>0,SUM($C17:$AG17),"") -> 165 | AI17: 67 | AJ17: 99 | AK17: =AJ17-AI17 -> 32 | AL17: =AJ17*AH17 -> 16335 | AM17: =AK17*AH17 -> 5280
B18: Omeprazole | C18: =RANDBETWEEN(1,10) -> 2 | D18: =RANDBETWEEN(1,10) -> 3 | E18: =RANDBETWEEN(1,10) -> 10 | F18: =RANDBETWEEN(1,10) -> 3 | G18: =RANDBETWEEN(1,10) -> 1 | H18: =RANDBETWEEN(1,10) -> 7 | I18: =RANDBETWEEN(1,10) -> 6 | J18: =RANDBETWEEN(1,10) -> 10 | ... AG18: =RANDBETWEEN(1,10) -> 2 | AH18: =IF(SUM($C18:$AG18)>0,SUM($C18:$AG18),"") -> 177 | AI18: 138 | AJ18: 150 | AK18: =AJ18-AI18 -> 12 | AL18: =AJ18*AH18 -> 26550 | AM18: =AK18*AH18 -> 2124
B19: Clopidogrel | C19: =RANDBETWEEN(1,10) -> 2 | D19: =RANDBETWEEN(1,10) -> 7 | E19: =RANDBETWEEN(1,10) -> 6 | F19: =RANDBETWEEN(1,10) -> 2 | G19: =RANDBETWEEN(1,10) -> 9 | H19: =RANDBETWEEN(1,10) -> 3 | I19: =RANDBETWEEN(1,10) -> 8 | J19: =RANDBETWEEN(1,10) -> 2 | ... AG19: =RANDBETWEEN(1,10) -> 9 | AH19: =IF(SUM($C19:$AG19)>0,SUM($C19:$AG19),"") -> 184 | AI19: 60 | AJ19: 80 | AK19: =AJ19-AI19 -> 20 | AL19: =AJ19*AH19 -> 14720 | AM19: =AK19*AH19 -> 3680
B20: Metoprolol | C20: =RANDBETWEEN(1,10) -> 4 | D20: =RANDBETWEEN(1,10) -> 1 | E20: =RANDBETWEEN(1,10) -> 10 | F20: =RANDBETWEEN(1,10) -> 7 | G20: =RANDBETWEEN(1,10) -> 7 | H20: =RANDBETWEEN(1,10) -> 5 | I20: =RANDBETWEEN(1,10) -> 4 | J20: =RANDBETWEEN(1,10) -> 3 | ... AG20: =RANDBETWEEN(1,10) -> 1 | AH20: =IF(SUM($C20:$AG20)>0,SUM($C20:$AG20),"") -> 177 | AI20: 44 | AJ20: 50 | AK20: =AJ20-AI20 -> 6 | AL20: =AJ20*AH20 -> 8850 | AM20: =AK20*AH20 -> 1062
B21: Amlodipine | C21: =RANDBETWEEN(1,10) -> 1 | D21: =RANDBETWEEN(1,10) -> 7 | E21: =RANDBETWEEN(1,10) -> 5 | F21: =RANDBETWEEN(1,10) -> 6 | G21: =RANDBETWEEN(1,10) -> 4 | H21: =RANDBETWEEN(1,10) -> 10 | I21: =RANDBETWEEN(1,10) -> 4 | J21: =RANDBETWEEN(1,10) -> 3 | ... AG21: =RANDBETWEEN(1,10) -> 7 | AH21: =IF(SUM($C21:$AG21)>0,SUM($C21:$AG21),"") -> 162 | AI21: 308 | AJ21: 320 | AK21: =AJ21-AI21 -> 12 | AL21: =AJ21*AH21 -> 51840 | AM21: =AK21*AH21 -> 1944
B22: Alprazolam | C22: =RANDBETWEEN(1,10) -> 8 | D22: =RANDBETWEEN(1,10) -> 8 | E22: =RANDBETWEEN(1,10) -> 1 | F22: =RANDBETWEEN(1,10) -> 10 | G22: =RANDBETWEEN(1,10) -> 10 | H22: =RANDBETWEEN(1,10) -> 3 | I22: =RANDBETWEEN(1,10) -> 10 | J22: =RANDBETWEEN(1,10) -> 5 | ... AG22: =RANDBETWEEN(1,10) -> 4 | AH22: =IF(SUM($C22:$AG22)>0,SUM($C22:$AG22),"") -> 184 | AI22: 234 | AJ22: 250 | AK22: =AJ22-AI22 -> 16 | AL22: =AJ22*AH22 -> 46000 | AM22: =AK22*AH22 -> 2944
B23: Hydrocodone | C23: =RANDBETWEEN(1,10) -> 10 | D23: =RANDBETWEEN(1,10) -> 8 | E23: =RANDBETWEEN(1,10) -> 1 | F23: =RANDBETWEEN(1,10) -> 8 | G23: =RANDBETWEEN(1,10) -> 1 | H23: =RANDBETWEEN(1,10) -> 6 | I23: =RANDBETWEEN(1,10) -> 10 | J23: =RANDBETWEEN(1,10) -> 9 | ... AG23: =RANDBETWEEN(1,10) -> 1 | AH23: =IF(SUM($C23:$AG23)>0,SUM($C23:$AG23),"") -> 198 | AI23: 121 | AJ23: 140 | AK23: =AJ23-AI23 -> 19 | AL23: =AJ23*AH23 -> 27720 | AM23: =AK23*AH23 -> 3762
B24: Gabapentin | C24: =RANDBETWEEN(1,10) -> 4 | D24: =RANDBETWEEN(1,10) -> 3 | E24: =RANDBETWEEN(1,10) -> 7 | F24: =RANDBETWEEN(1,10) -> 9 | G24: =RANDBETWEEN(1,10) -> 5 | H24: =RANDBETWEEN(1,10) -> 9 | I24: =RANDBETWEEN(1,10) -> 4 | J24: =RANDBETWEEN(1,10) -> 7 | ... AG24: =RANDBETWEEN(1,10) -> 10 | AH24: =IF(SUM($C24:$AG24)>0,SUM($C24:$AG24),"") -> 181 | AI24: 350 | AJ24: 390 | AK24: =AJ24-AI24 -> 40 | AL24: =AJ24*AH24 -> 70590 | AM24: =AK24*AH24 -> 7240
B25: Levothyroxine | C25: =RANDBETWEEN(1,10) -> 7 | D25: =RANDBETWEEN(1,10) -> 4 | E25: =RANDBETWEEN(1,10) -> 1 | F25: =RANDBETWEEN(1,10) -> 7 | G25: =RANDBETWEEN(1,10) -> 3 | H25: =RANDBETWEEN(1,10) -> 7 | I25: =RANDBETWEEN(1,10) -> 3 | J25: =RANDBETWEEN(1,10) -> 8 | ... AG25: =RANDBETWEEN(1,10) -> 8 | AH25: =IF(SUM($C25:$AG25)>0,SUM($C25:$AG25),"") -> 186 | AI25: 211 | AJ25: 240 | AK25: =AJ25-AI25 -> 29 | AL25: =AJ25*AH25 -> 44640 | AM25: =AK25*AH25 -> 5394
B26: Sertraline | C26: =RANDBETWEEN(1,10) -> 4 | D26: =RANDBETWEEN(1,10) -> 3 | E26: =RANDBETWEEN(1,10) -> 8 | F26: =RANDBETWEEN(1,10) -> 4 | G26: =RANDBETWEEN(1,10) -> 5 | H26: =RANDBETWEEN(1,10) -> 2 | I26: =RANDBETWEEN(1,10) -> 5 | J26: =RANDBETWEEN(1,10) -> 10 | ... AG26: =RANDBETWEEN(1,10) -> 7 | AH26: =IF(SUM($C26:$AG26)>0,SUM($C26:$AG26),"") -> 193 | AI26: 247 | AJ26: 280 | AK26: =AJ26-AI26 -> 33 | AL26: =AJ26*AH26 -> 54040 | AM26: =AK26*AH26 -> 6369
B27: Azithromycin | C27: =RANDBETWEEN(1,10) -> 8 | D27: =RANDBETWEEN(1,10) -> 4 | E27: =RANDBETWEEN(1,10) -> 7 | F27: =RANDBETWEEN(1,10) -> 7 | G27: =RANDBETWEEN(1,10) -> 1 | H27: =RANDBETWEEN(1,10) -> 1 | I27: =RANDBETWEEN(1,10) -> 1 | J27: =RANDBETWEEN(1,10) -> 9 | ... AG27: =RANDBETWEEN(1,10) -> 5 | AH27: =IF(SUM($C27:$AG27)>0,SUM($C27:$AG27),"") -> 169 | AI27: 286 | AJ27: 320 | AK27: =AJ27-AI27 -> 34 | AL27: =AJ27*AH27 -> 54080 | AM27: =AK27*AH27 -> 5746
B28: Losartan | C28: =RANDBETWEEN(1,10) -> 4 | D28: =RANDBETWEEN(1,10) -> 10 | E28: =RANDBETWEEN(1,10) -> 8 | F28: =RANDBETWEEN(1,10) -> 7 | G28: =RANDBETWEEN(1,10) -> 2 | H28: =RANDBETWEEN(1,10) -> 2 | I28: =RANDBETWEEN(1,10) -> 7 | J28: =RANDBETWEEN(1,10) -> 7 | ... AG28: =RANDBETWEEN(1,10) -> 2 | AH28: =IF(SUM($C28:$AG28)>0,SUM($C28:$AG28),"") -> 150 | AI28: 67 | AJ28: 80 | AK28: =AJ28-AI28 -> 13 | AL28: =AJ28*AH28 -> 12000 | AM28: =AK28*AH28 -> 1950
... B57: Lamotrigine | C57: =RANDBETWEEN(1,10) -> 5 | D57: =RANDBETWEEN(1,10) -> 3 | E57: =RANDBETWEEN(1,10) -> 3 | F57: =RANDBETWEEN(1,10) -> 1 | G57: =RANDBETWEEN(1,10) -> 2 | H57: =RANDBETWEEN(1,10) -> 9 | I57: =RANDBETWEEN(1,10) -> 1 | J57: =RANDBETWEEN(1,10) -> 10 | ... AG57: =RANDBETWEEN(1,10) -> 1 | AH57: =IF(SUM($C57:$AG57)>0,SUM($C57:$AG57),"") -> 174 | AI57: 340 | AJ57: 380 | AK57: =AJ57-AI57 -> 40 | AL57: =AJ57*AH57 -> 66120 | AM57: =AK57*AH57 -> 6960

Sheet August
C1: =TEXT(C2,"DDD") -> Thu | D1: =TEXT(D2,"DDD") -> Fri | E1: =TEXT(E2,"DDD") -> Sat | F1: =TEXT(F2,"DDD") -> Sun | G1: =TEXT(G2,"DDD") -> Mon | H1: =TEXT(H2,"DDD") -> Tue | I1: =TEXT(I2,"DDD") -> Wed | J1: =TEXT(J2,"DDD") -> Thu | ... AG1: =TEXT(AG2,"DDD") -> Sat | AH1: Total Sales | AI1: Incoming price (Including GST) | AJ1: Sales price | AK1: Profit Margin | AL1: Total collection | AM1: Net collection | AO1: Month | AP1: August
B2: Product Name | C2: =IF(COLUMNS($C$2:C2)>DAY($AP$4),"",$AP$3+COLUMNS($C$2:C2)-1) -> 45505 | D2: =IF(COLUMNS($C$2:D2)>DAY($AP$4),"",$AP$3+COLUMNS($C$2:D2)-1) -> 45506 | E2: =IF(COLUMNS($C$2:E2)>DAY($AP$4),"",$AP$3+COLUMNS($C$2:E2)-1) -> 45507 | F2: =IF(COLUMNS($C$2:F2)>DAY($AP$4),"",$AP$3+COLUMNS($C$2:F2)-1) -> 45508 | G2: =IF(COLUMNS($C$2:G2)>DAY($AP$4),"",$AP$3+COLUMNS($C$2:G2)-1) -> 45509 | H2: =IF(COLUMNS($C$2:H2)>DAY($AP$4),"",$AP$3+COLUMNS($C$2:H2)-1) -> 45510 | I2: =IF(COLUMNS($C$2:I2)>DAY($AP$4),"",$AP$3+COLUMNS($C$2:I2)-1) -> 45511 | J2: =IF(COLUMNS($C$2:J2)>DAY($AP$4),"",$AP$3+COLUMNS($C$2:J2)-1) -> 45512 | ... AG2: =IF(COLUMNS($C$2:AG2)>DAY($AP$4),"",$AP$3+COLUMNS($C$2:AG2)-1) -> 45535 | AO2: Year | AP2: 2024
B3: Iodex | C3: 8 | D3: 8 | E3: 4 | F3: 6 | G3: 10 | H3: 4 | I3: 8 | J3: 3 | K3: 8 | L3: 5 | M3: 8 | N3: 2 | O3: 9 | P3: 4 | Q3: 6 | R3: 2 | S3: 7 | T3: 5 | U3: 6 | V3: 1 | W3: 3 | X3: 10 | Y3: 6 | Z3: 2 | AA3: 4 | AB3: 4 | AC3: 3 | AD3: 2 | AE3: 1 | AF3: 6 | AG3: 5 | AH3: =IF(SUM($C3:$AG3)>0,SUM($C3:$AG3),"") -> 160 | AI3: 40 | AJ3: 80 | AK3: =AJ3-AI3 -> 40 | AL3: =AJ3*AH3 -> 12800 | AM3: =AK3*AH3 -> 6400 | AO3: Starting Date | AP3: =DATE(AP2,MONTH(AP1&1),1) -> 45505
B4: Nimocet | C4: 2 | D4: 9 | E4: 2 | F4: 7 | G4: 4 | H4: 8 | I4: 10 | J4: 6 | K4: 6 | L4: 5 | M4: 3 | N4: 1 | O4: 2 | P4: 6 | Q4: 5 | R4: 3 | S4: 1 | T4: 6 | U4: 4 | V4: 1 | W4: 9 | X4: 1 | Y4: 3 | Z4: 7 | AA4: 2 | AB4: 1 | AC4: 9 | AD4: 10 | AE4: 8 | AF4: 9 | AG4: 7 | AH4: =IF(SUM($C4:$AG4)>0,SUM($C4:$AG4),"") -> 157 | AI4: 7 | AJ4: 15 | AK4: =AJ4-AI4 -> 8 | AL4: =AJ4*AH4 -> 2355 | AM4: =AK4*AH4 -> 1256 | AO4: Ending Date | AP4: =EOMONTH(AP3,0) -> 45535
B5: Paracetamol | C5: 1 | D5: 3 | E5: 8 | F5: 1 | G5: 6 | H5: 5 | I5: 10 | J5: 5 | K5: 7 | L5: 1 | M5: 3 | N5: 2 | O5: 7 | P5: 5 | Q5: 8 | R5: 9 | S5: 9 | T5: 8 | U5: 9 | V5: 4 | W5: 6 | X5: 7 | Y5: 9 | Z5: 4 | AA5: 3 | AB5: 10 | AC5: 8 | AD5: 6 | AE5: 1 | AF5: 6 | AG5: 7 | AH5: =IF(SUM($C5:$AG5)>0,SUM($C5:$AG5),"") -> 178 | AI5: 5 | AJ5: 10 | AK5: =AJ5-AI5 -> 5 | AL5: =AJ5*AH5 -> 1780 | AM5: =AK5*AH5 -> 890
B6: Monocef | C6: 7 | D6: 7 | E6: 8 | F6: 8 | G6: 9 | H6: 4 | I6: 4 | J6: 4 | K6: 5 | L6: 3 | M6: 9 | N6: 9 | O6: 5 | P6: 10 | Q6: 7 | R6: 5 | S6: 5 | T6: 1 | U6: 8 | V6: 6 | W6: 1 | X6: 5 | Y6: 4 | Z6: 6 | AA6: 10 | AB6: 7 | AC6: 6 | AD6: 1 | AE6: 7 | AF6: 6 | AG6: 9 | AH6: =IF(SUM($C6:$AG6)>0,SUM($C6:$AG6),"") -> 186 | AI6: 45 | AJ6: 80 | AK6: =AJ6-AI6 -> 35 | AL6: =AJ6*AH6 -> 14880 | AM6: =AK6*AH6 -> 6510
B7: Cyclopalm | C7: 2 | D7: 2 | E7: 8 | F7: 8 | G7: 8 | H7: 6 | I7: 7 | J7: 6 | K7: 2 | L7: 1 | M7: 2 | N7: 1 | O7: 7 | P7: 2 | Q7: 2 | R7: 2 | S7: 4 | T7: 7 | U7: 3 | V7: 3 | W7: 4 | X7: 1 | Y7: 7 | Z7: 6 | AA7: 9 | AB7: 10 | AC7: 3 | AD7: 3 | AE7: 7 | AF7: 9 | AG7: 3 | AH7: =IF(SUM($C7:$AG7)>0,SUM($C7:$AG7),"") -> 145 | AI7: 392 | AJ7: 420 | AK7: =AJ7-AI7 -> 28 | AL7: =AJ7*AH7 -> 60900 | AM7: =AK7*AH7 -> 4060 | AO7: Expanses
B8: Cetaphil | C8: 4 | D8: 7 | E8: 5 | F8: 8 | G8: 2 | H8: 2 | I8: 1 | J8: 9 | K8: 6 | L8: 1 | M8: 3 | N8: 7 | O8: 4 | P8: 3 | Q8: 10 | R8: 6 | S8: 5 | T8: 2 | U8: 9 | V8: 1 | W8: 8 | X8: 5 | Y8: 5 | Z8: 1 | AA8: 9 | AB8: 8 | AC8: 7 | AD8: 7 | AE8: 10 | AF8: 5 | AG8: 4 | AH8: =IF(SUM($C8:$AG8)>0,SUM($C8:$AG8),"") -> 164 | AI8: 86 | AJ8: 100 | AK8: =AJ8-AI8 -> 14 | AL8: =AJ8*AH8 -> 16400 | AM8: =AK8*AH8 -> 2296 | AO8: Employee Salary
B9: Acetaminophen | C9: 10 | D9: 2 | E9: 2 | F9: 7 | G9: 9 | H9: 8 | I9: 5 | J9: 1 | K9: 7 | L9: 10 | M9: 8 | N9: 2 | O9: 3 | P9: 8 | Q9: 5 | R9: 4 | S9: 8 | T9: 3 | U9: 4 | V9: 1 | W9: 9 | X9: 8 | Y9: 4 | Z9: 10 | AA9: 10 | AB9: 5 | AC9: 9 | AD9: 4 | AE9: 4 | AF9: 3 | AG9: 7 | AH9: =IF(SUM($C9:$AG9)>0,SUM($C9:$AG9),"") -> 180 | AI9: 271 | AJ9: 300 | AK9: =AJ9-AI9 -> 29 | AL9: =AJ9*AH9 -> 54000 | AM9: =AK9*AH9 -> 5220 | AO9: Kaishav(Owner) | AP9: ='Attendence (Aug)'!AL3 -> 50000
B10: Ibuprofen | C10: 10 | D10: 7 | E10: 8 | F10: 2 | G10: 2 | H10: 6 | I10: 4 | J10: 1 | K10: 5 | L10: 6 | M10: 1 | N10: 2 | O10: 8 | P10: 8 | Q10: 2 | R10: 6 | S10: 2 | T10: 9 | U10: 9 | V10: 5 | W10: 2 | X10: 3 | Y10: 10 | Z10: 6 | AA10: 2 | AB10: 2 | AC10: 10 | AD10: 3 | AE10: 4 | AF10: 4 | AG10: 4 | AH10: =IF(SUM($C10:$AG10)>0,SUM($C10:$AG10),"") -> 153 | AI10: 226 | AJ10: 250 | AK10: =AJ10-AI10 -> 24 | AL10: =AJ10*AH10 -> 38250 | AM10: =AK10*AH10 -> 3672 | AO10: Raman | AP10: ='Attendence (Aug)'!AL4 -> 15000
B11: Aspirin | C11: 5 | D11: 6 | E11: 5 | F11: 5 | G11: 7 | H11: 8 | I11: 3 | J11: 10 | K11: 3 | L11: 10 | M11: 4 | N11: 8 | O11: 7 | P11: 1 | Q11: 6 | R11: 2 | S11: 1 | T11: 9 | U11: 2 | V11: 7 | W11: 5 | X11: 8 | Y11: 2 | Z11: 6 | AA11: 3 | AB11: 1 | AC11: 8 | AD11: 1 | AE11: 10 | AF11: 9 | AG11: 4 | AH11: =IF(SUM($C11:$AG11)>0,SUM($C11:$AG11),"") -> 166 | AI11: 390 | AJ11: 450 | AK11: =AJ11-AI11 -> 60 | AL11: =AJ11*AH11 -> 74700 | AM11: =AK11*AH11 -> 9960 | AO11: Sohan | AP11: ='Attendence (Aug)'!AL5 -> 18000
B12: Amoxicillin | C12: 5 | D12: 9 | E12: 1 | F12: 6 | G12: 10 | H12: 4 | I12: 6 | J12: 3 | K12: 6 | L12: 2 | M12: 5 | N12: 5 | O12: 3 | P12: 8 | Q12: 1 | R12: 2 | S12: 4 | T12: 8 | U12: 2 | V12: 5 | W12: 8 | X12: 4 | Y12: 8 | Z12: 8 | AA12: 5 | AB12: 2 | AC12: 8 | AD12: 1 | AE12: 7 | AF12: 3 | AG12: 2 | AH12: =IF(SUM($C12:$AG12)>0,SUM($C12:$AG12),"") -> 151 | AI12: 379 | AJ12: 430 | AK12: =AJ12-AI12 -> 51 | AL12: =AJ12*AH12 -> 64930 | AM12: =AK12*AH12 -> 7701 | AO12: Tilak | AP12: =-'Attendence (Aug)'!AL6 -> -9666.6667
B13: Ciprofloxacin | C13: 3 | D13: 9 | E13: 2 | F13: 8 | G13: 3 | H13: 3 | I13: 3 | J13: 5 | K13: 1 | L13: 5 | M13: 3 | N13: 6 | O13: 4 | P13: 5 | Q13: 1 | R13: 1 | S13: 4 | T13: 7 | U13: 2 | V13: 10 | W13: 5 | X13: 8 | Y13: 2 | Z13: 8 | AA13: 8 | AB13: 3 | AC13: 2 | AD13: 8 | AE13: 4 | AF13: 3 | AG13: 4 | AH13: =IF(SUM($C13:$AG13)>0,SUM($C13:$AG13),"") -> 140 | AI13: 368 | AJ13: 435 | AK13: =AJ13-AI13 -> 67 | AL13: =AJ13*AH13 -> 60900 | AM13: =AK13*AH13 -> 9380 | AO13: Bill to pay | AP13: 10000
B14: Lisinopril | C14: 7 | D14: 7 | E14: 4 | F14: 7 | G14: 10 | H14: 5 | I14: 5 | J14: 1 | K14: 8 | L14: 6 | M14: 1 | N14: 4 | O14: 5 | P14: 9 | Q14: 7 | R14: 4 | S14: 7 | T14: 3 | U14: 4 | V14: 10 | W14: 9 | X14: 2 | Y14: 8 | Z14: 6 | AA14: 6 | AB14: 5 | AC14: 1 | AD14: 4 | AE14: 4 | AF14: 1 | AG14: 5 | AH14: =IF(SUM($C14:$AG14)>0,SUM($C14:$AG14),"") -> 165 | AI14: 88 | AJ14: 99 | AK14: =AJ14-AI14 -> 11 | AL14: =AJ14*AH14 -> 16335 | AM14: =AK14*AH14 -> 1815 | AO14: other | AP14: 2000
B15: Atorvastatin | C15: 10 | D15: 9 | E15: 9 | F15: 3 | G15: 9 | H15: 2 | I15: 10 | J15: 2 | K15: 9 | L15: 3 | M15: 8 | N15: 9 | O15: 10 | P15: 7 | Q15: 6 | R15: 3 | S15: 10 | T15: 1 | U15: 10 | V15: 2 | W15: 4 | X15: 4 | Y15: 1 | Z15: 2 | AA15: 8 | AB15: 6 | AC15: 2 | AD15: 7 | AE15: 10 | AF15: 9 | AG15: 4 | AH15: =IF(SUM($C15:$AG15)>0,SUM($C15:$AG15),"") -> 189 | AI15: 391 | AJ15: 500 | AK15: =AJ15-AI15 -> 109 | AL15: =AJ15*AH15 -> 94500 | AM15: =AK15*AH15 -> 20601 | AO15: Net collection | AP15: =SUM(AM3:AM57) -> 296980
B16: Metformin | C16: 7 | D16: 8 | E16: 9 | F16: 3 | G16: 9 | H16: 8 | I16: 8 | J16: 6 | K16: 7 | L16: 8 | M16: 6 | N16: 3 | O16: 9 | P16: 6 | Q16: 7 | R16: 7 | S16: 4 | T16: 3 | U16: 1 | V16: 1 | W16: 8 | X16: 10 | Y16: 7 | Z16: 4 | AA16: 9 | AB16: 4 | AC16: 7 | AD16: 5 | AE16: 5 | AF16: 10 | AG16: 10 | AH16: =IF(SUM($C16:$AG16)>0,SUM($C16:$AG16),"") -> 199 | AI16: 261 | AJ16: 300 | AK16: =AJ16-AI16 -> 39 | AL16: =AJ16*AH16 -> 59700 | AM16: =AK16*AH16 -> 7761 | AO16: Net Income | AP16: =AP15-(AP9+AP10+AP11+(-AP12)+AP13+AP14) -> 192313.33
B17: Simvastatin | C17: 2 | D17: 7 | E17: 10 | F17: 1 | G17: 5 | H17: 7 | I17: 8 | J17: 3 | K17: 2 | L17: 2 | M17: 1 | N17: 10 | O17: 2 | P17: 2 | Q17: 10 | R17: 4 | S17: 1 | T17: 8 | U17: 3 | V17: 5 | W17: 2 | X17: 2 | Y17: 4 | Z17: 8 | AA17: 6 | AB17: 5 | AC17: 1 | AD17: 7 | AE17: 10 | AF17: 3 | AG17: 10 | AH17: =IF(SUM($C17:$AG17)>0,SUM($C17:$AG17),"") -> 151 | AI17: 67 | AJ17: 99 | AK17: =AJ17-AI17 -> 32 | AL17: =AJ17*AH17 -> 14949 | AM17: =AK17*AH17 -> 4832
B18: Omeprazole | C18: 3 | D18: 3 | E18: 1 | F18: 2 | G18: 1 | H18: 8 | I18: 1 | J18: 6 | K18: 9 | L18: 3 | M18: 3 | N18: 5 | O18: 9 | P18: 1 | Q18: 3 | R18: 8 | S18: 3 | T18: 9 | U18: 6 | V18: 10 | W18: 8 | X18: 6 | Y18: 4 | Z18: 8 | AA18: 5 | AB18: 10 | AC18: 1 | AD18: 7 | AE18: 1 | AF18: 6 | AG18: 7 | AH18: =IF(SUM($C18:$AG18)>0,SUM($C18:$AG18),"") -> 157 | AI18: 138 | AJ18: 150 | AK18: =AJ18-AI18 -> 12 | AL18: =AJ18*AH18 -> 23550 | AM18: =AK18*AH18 -> 1884
B19: Clopidogrel | C19: 9 | D19: 3 | E19: 1 | F19: 4 | G19: 4 | H19: 5 | I19: 4 | J19: 9 | K19: 4 | L19: 5 | M19: 7 | N19: 9 | O19: 3 | P19: 10 | Q19: 5 | R19: 6 | S19: 5 | T19: 3 | U19: 4 | V19: 8 | W19: 1 | X19: 1 | Y19: 7 | Z19: 8 | AA19: 6 | AB19: 2 | AC19: 1 | AD19: 3 | AE19: 5 | AF19: 8 | AG19: 8 | AH19: =IF(SUM($C19:$AG19)>0,SUM($C19:$AG19),"") -> 158 | AI19: 60 | AJ19: 80 | AK19: =AJ19-AI19 -> 20 | AL19: =AJ19*AH19 -> 12640 | AM19: =AK19*AH19 -> 3160
B20: Metoprolol | C20: 9 | D20: 6 | E20: 9 | F20: 2 | G20: 4 | H20: 2 | I20: 5 | J20: 6 | K20: 4 | L20: 6 | M20: 4 | N20: 5 | O20: 4 | P20: 4 | Q20: 8 | R20: 2 | S20: 7 | T20: 8 | U20: 1 | V20: 4 | W20: 1 | X20: 2 | Y20: 7 | Z20: 9 | AA20: 4 | AB20: 3 | AC20: 3 | AD20: 6 | AE20: 5 | AF20: 10 | AG20: 8 | AH20: =IF(SUM($C20:$AG20)>0,SUM($C20:$AG20),"") -> 158 | AI20: 44 | AJ20: 50 | AK20: =AJ20-AI20 -> 6 | AL20: =AJ20*AH20 -> 7900 | AM20: =AK20*AH20 -> 948
B21: Amlodipine | C21: 8 | D21: 10 | E21: 4 | F21: 1 | G21: 6 | H21: 9 | I21: 10 | J21: 7 | K21: 7 | L21: 2 | M21: 10 | N21: 9 | O21: 7 | P21: 7 | Q21: 10 | R21: 10 | S21: 2 | T21: 8 | U21: 1 | V21: 8 | W21: 4 | X21: 9 | Y21: 3 | Z21: 7 | AA21: 7 | AB21: 1 | AC21: 6 | AD21: 9 | AE21: 5 | AF21: 4 | AG21: 4 | AH21: =IF(SUM($C21:$AG21)>0,SUM($C21:$AG21),"") -> 195 | AI21: 308 | AJ21: 320 | AK21: =AJ21-AI21 -> 12 | AL21: =AJ21*AH21 -> 62400 | AM21: =AK21*AH21 -> 2340
B22: Alprazolam | C22: 10 | D22: 5 | E22: 2 | F22: 6 | G22: 10 | H22: 2 | I22: 1 | J22: 9 | K22: 1 | L22: 4 | M22: 2 | N22: 10 | O22: 2 | P22: 8 | Q22: 8 | R22: 9 | S22: 5 | T22: 3 | U22: 4 | V22: 3 | W22: 8 | X22: 9 | Y22: 10 | Z22: 1 | AA22: 1 | AB22: 4 | AC22: 4 | AD22: 4 | AE22: 4 | AF22: 5 | AG22: 8 | AH22: =IF(SUM($C22:$AG22)>0,SUM($C22:$AG22),"") -> 162 | AI22: 234 | AJ22: 250 | AK22: =AJ22-AI22 -> 16 | AL22: =AJ22*AH22 -> 40500 | AM22: =AK22*AH22 -> 2592
B23: Hydrocodone | C23: 7 | D23: 3 | E23: 7 | F23: 6 | G23: 7 | H23: 9 | I23: 2 | J23: 3 | K23: 6 | L23: 6 | M23: 4 | N23: 9 | O23: 8 | P23: 3 | Q23: 3 | R23: 3 | S23: 2 | T23: 7 | U23: 10 | V23: 6 | W23: 9 | X23: 5 | Y23: 4 | Z23: 8 | AA23: 10 | AB23: 8 | AC23: 3 | AD23: 6 | AE23: 4 | AF23: 1 | AG23: 1 | AH23: =IF(SUM($C23:$AG23)>0,SUM($C23:$AG23),"") -> 170 | AI23: 121 | AJ23: 140 | AK23: =AJ23-AI23 -> 19 | AL23: =AJ23*AH23 -> 23800 | AM23: =AK23*AH23 -> 3230
B24: Gabapentin | C24: 2 | D24: 5 | E24: 4 | F24: 5 | G24: 8 | H24: 4 | I24: 8 | J24: 1 | K24: 7 | L24: 6 | M24: 7 | N24: 2 | O24: 7 | P24: 4 | Q24: 3 | R24: 1 | S24: 7 | T24: 6 | U24: 5 | V24: 7 | W24: 4 | X24: 5 | Y24: 10 | Z24: 6 | AA24: 2 | AB24: 8 | AC24: 8 | AD24: 3 | AE24: 7 | AF24: 3 | AG24: 6 | AH24: =IF(SUM($C24:$AG24)>0,SUM($C24:$AG24),"") -> 161 | AI24: 350 | AJ24: 390 | AK24: =AJ24-AI24 -> 40 | AL24: =AJ24*AH24 -> 62790 | AM24: =AK24*AH24 -> 6440
B25: Levothyroxine | C25: 3 | D25: 2 | E25: 6 | F25: 8 | G25: 7 | H25: 7 | I25: 6 | J25: 8 | K25: 4 | L25: 3 | M25: 8 | N25: 10 | O25: 2 | P25: 3 | Q25: 10 | R25: 10 | S25: 2 | T25: 7 | U25: 8 | V25: 10 | W25: 1 | X25: 7 | Y25: 10 | Z25: 2 | AA25: 2 | AB25: 9 | AC25: 9 | AD25: 5 | AE25: 6 | AF25: 9 | AG25: 7 | AH25: =IF(SUM($C25:$AG25)>0,SUM($C25:$AG25),"") -> 191 | AI25: 211 | AJ25: 240 | AK25: =AJ25-AI25 -> 29 | AL25: =AJ25*AH25 -> 45840 | AM25: =AK25*AH25 -> 5539
B26: Sertraline | C26: 4 | D26: 1 | E26: 8 | F26: 6 | G26: 10 | H26: 2 | I26: 9 | J26: 6 | K26: 1 | L26: 5 | M26: 10 | N26: 3 | O26: 1 | P26: 10 | Q26: 8 | R26: 1 | S26: 6 | T26: 5 | U26: 5 | V26: 8 | W26: 6 | X26: 6 | Y26: 8 | Z26: 6 | AA26: 9 | AB26: 9 | AC26: 3 | AD26: 7 | AE26: 6 | AF26: 4 | AG26: 6 | AH26: =IF(SUM($C26:$AG26)>0,SUM($C26:$AG26),"") -> 179 | AI26: 247 | AJ26: 280 | AK26: =AJ26-AI26 -> 33 | AL26: =AJ26*AH26 -> 50120 | AM26: =AK26*AH26 -> 5907
B27: Azithromycin | C27: 6 | D27: 3 | E27: 2 | F27: 7 | G27: 5 | H27: 9 | I27: 5 | J27: 6 | K27: 4 | L27: 5 | M27: 9 | N27: 8 | O27: 4 | P27: 1 | Q27: 6 | R27: 1 | S27: 10 | T27: 1 | U27: 9 | V27: 2 | W27: 5 | X27: 6 | Y27: 5 | Z27: 10 | AA27: 6 | AB27: 5 | AC27: 7 | AD27: 3 | AE27: 8 | AF27: 2 | AG27: 6 | AH27: =IF(SUM($C27:$AG27)>0,SUM($C27:$AG27),"") -> 166 | AI27: 286 | AJ27: 320 | AK27: =AJ27-AI27 -> 34 | AL27: =AJ27*AH27 -> 53120 | AM27: =AK27*AH27 -> 5644
B28: Losartan | C28: 7 | D28: 4 | E28: 10 | F28: 5 | G28: 7 | H28: 5 | I28: 4 | J28: 1 | K28: 1 | L28: 10 | M28: 5 | N28: 1 | O28: 6 | P28: 9 | Q28: 8 | R28: 10 | S28: 5 | T28: 4 | U28: 7 | V28: 1 | W28: 4 | X28: 6 | Y28: 7 | Z28: 4 | AA28: 3 | AB28: 10 | AC28: 7 | AD28: 7 | AE28: 6 | AF28: 9 | AG28: 2 | AH28: =IF(SUM($C28:$AG28)>0,SUM($C28:$AG28),"") -> 175 | AI28: 67 | AJ28: 80 | AK28: =AJ28-AI28 -> 13 | AL28: =AJ28*AH28 -> 14000 | AM28: =AK28*AH28 -> 2275
... B57: Lamotrigine | C57: 6 | D57: 2 | E57: 8 | F57: 9 | G57: 10 | H57: 1 | I57: 5 | J57: 9 | K57: 9 | L57: 7 | M57: 2 | N57: 10 | O57: 4 | P57: 3 | Q57: 5 | R57: 2 | S57: 3 | T57: 2 | U57: 9 | V57: 4 | W57: 3 | X57: 8 | Y57: 2 | Z57: 3 | AA57: 3 | AB57: 5 | AC57: 9 | AD57: 9 | AE57: 8 | AF57: 1 | AG57: 1 | AH57: =IF(SUM($C57:$AG57)>0,SUM($C57:$AG57),"") -> 162 | AI57: 340 | AJ57: 380 | AK57: =AJ57-AI57 -> 40 | AL57: =AJ57*AH57 -> 61560 | AM57: =AK57*AH57 -> 6480

Sheet September
C1: =TEXT(C2,"DDD") -> Sun | D1: =TEXT(D2,"DDD") -> Mon | E1: =TEXT(E2,"DDD") -> Tue | F1: =TEXT(F2,"DDD") -> Wed | G1: =TEXT(G2,"DDD") -> Thu | H1: =TEXT(H2,"DDD") -> Fri | I1: =TEXT(I2,"DDD") -> Sat | J1: =TEXT(J2,"DDD") -> Sun | ... AG1: =TEXT(AG2,"DDD") | AH1: Total Sales | AI1: Incoming price (Including GST) | AJ1: Sales price | AK1: Profit Margin | AL1: Total collection | AM1: Net collection | AO1: Month | AP1: September
B2: Product Name | C2: =IF(COLUMNS($C$2:C2)>DAY($AP$4),"",$AP$3+COLUMNS($C$2:C2)-1) -> 45536 | D2: =IF(COLUMNS($C$2:D2)>DAY($AP$4),"",$AP$3+COLUMNS($C$2:D2)-1) -> 45537 | E2: =IF(COLUMNS($C$2:E2)>DAY($AP$4),"",$AP$3+COLUMNS($C$2:E2)-1) -> 45538 | F2: =IF(COLUMNS($C$2:F2)>DAY($AP$4),"",$AP$3+COLUMNS($C$2:F2)-1) -> 45539 | G2: =IF(COLUMNS($C$2:G2)>DAY($AP$4),"",$AP$3+COLUMNS($C$2:G2)-1) -> 45540 | H2: =IF(COLUMNS($C$2:H2)>DAY($AP$4),"",$AP$3+COLUMNS($C$2:H2)-1) -> 45541 | I2: =IF(COLUMNS($C$2:I2)>DAY($AP$4),"",$AP$3+COLUMNS($C$2:I2)-1) -> 45542 | J2: =IF(COLUMNS($C$2:J2)>DAY($AP$4),"",$AP$3+COLUMNS($C$2:J2)-1) -> 45543 | ... AG2: =IF(COLUMNS($C$2:AG2)>DAY($AP$4),"",$AP$3+COLUMNS($C$2:AG2)-1) | AO2: Year | AP2: 2024
B3: Iodex | C3: =RANDBETWEEN(1,10) -> 1 | D3: =RANDBETWEEN(1,10) -> 3 | E3: =RANDBETWEEN(1,10) -> 3 | F3: =RANDBETWEEN(1,10) -> 2 | G3: =RANDBETWEEN(1,10) -> 8 | H3: =RANDBETWEEN(1,10) -> 8 | I3: =RANDBETWEEN(1,10) -> 9 | J3: =RANDBETWEEN(1,10) -> 3 | ... AF3: =RANDBETWEEN(1,10) -> 1 | AH3: =IF(SUM($C3:$AG3)>0,SUM($C3:$AG3),"") -> 147 | AI3: 40 | AJ3: 80 | AK3: =AJ3-AI3 -> 40 | AL3: =AJ3*AH3 -> 11760 | AM3: =AK3*AH3 -> 5880 | AO3: Starting Date | AP3: =DATE(AP2,MONTH(AP1&1),1) -> 45536
B4: Nimocet | C4: =RANDBETWEEN(1,10) -> 9 | D4: =RANDBETWEEN(1,10) -> 10 | E4: =RANDBETWEEN(1,10) -> 9 | F4: =RANDBETWEEN(1,10) -> 8 | G4: =RANDBETWEEN(1,10) -> 3 | H4: =RANDBETWEEN(1,10) -> 7 | I4: =RANDBETWEEN(1,10) -> 3 | J4: =RANDBETWEEN(1,10) -> 5 | ... AF4: =RANDBETWEEN(1,10) -> 5 | AH4: =IF(SUM($C4:$AG4)>0,SUM($C4:$AG4),"") -> 165 | AI4: 7 | AJ4: 15 | AK4: =AJ4-AI4 -> 8 | AL4: =AJ4*AH4 -> 2475 | AM4: =AK4*AH4 -> 1320 | AO4: Ending Date | AP4: =EOMONTH(AP3,0) -> 45565
B5: Paracetamol | C5: =RANDBETWEEN(1,10) -> 7 | D5: =RANDBETWEEN(1,10) -> 2 | E5: =RANDBETWEEN(1,10) -> 9 | F5: =RANDBETWEEN(1,10) -> 7 | G5: =RANDBETWEEN(1,10) -> 4 | H5: =RANDBETWEEN(1,10) -> 10 | I5: =RANDBETWEEN(1,10) -> 5 | J5: =RANDBETWEEN(1,10) -> 2 | ... AF5: =RANDBETWEEN(1,10) -> 3 | AH5: =IF(SUM($C5:$AG5)>0,SUM($C5:$AG5),"") -> 176 | AI5: 5 | AJ5: 10 | AK5: =AJ5-AI5 -> 5 | AL5: =AJ5*AH5 -> 1760 | AM5: =AK5*AH5 -> 880
B6: Monocef | C6: =RANDBETWEEN(1,10) -> 4 | D6: =RANDBETWEEN(1,10) -> 7 | E6: =RANDBETWEEN(1,10) -> 6 | F6: =RANDBETWEEN(1,10) -> 8 | G6: =RANDBETWEEN(1,10) -> 4 | H6: =RANDBETWEEN(1,10) -> 1 | I6: =RANDBETWEEN(1,10) -> 3 | J6: =RANDBETWEEN(1,10) -> 8 | ... AF6: =RANDBETWEEN(1,10) -> 1 | AH6: =IF(SUM($C6:$AG6)>0,SUM($C6:$AG6),"") -> 159 | AI6: 45 | AJ6: 80 | AK6: =AJ6-AI6 -> 35 | AL6: =AJ6*AH6 -> 12720 | AM6: =AK6*AH6 -> 5565
B7: Cyclopalm | C7: =RANDBETWEEN(1,10) -> 4 | D7: =RANDBETWEEN(1,10) -> 8 | E7: =RANDBETWEEN(1,10) -> 4 | F7: =RANDBETWEEN(1,10) -> 5 | G7: =RANDBETWEEN(1,10) -> 1 | H7: =RANDBETWEEN(1,10) -> 4 | I7: =RANDBETWEEN(1,10) -> 4 | J7: =RANDBETWEEN(1,10) -> 3 | ... AF7: =RANDBETWEEN(1,10) -> 3 | AH7: =IF(SUM($C7:$AG7)>0,SUM($C7:$AG7),"") -> 151 | AI7: 392 | AJ7: 420 | AK7: =AJ7-AI7 -> 28 | AL7: =AJ7*AH7 -> 63420 | AM7: =AK7*AH7 -> 4228 | AO7: Expanses
B8: Cetaphil | C8: =RANDBETWEEN(1,10) -> 6 | D8: =RANDBETWEEN(1,10) -> 8 | E8: =RANDBETWEEN(1,10) -> 6 | F8: =RANDBETWEEN(1,10) -> 10 | G8: =RANDBETWEEN(1,10) -> 7 | H8: =RANDBETWEEN(1,10) -> 9 | I8: =RANDBETWEEN(1,10) -> 5 | J8: =RANDBETWEEN(1,10) -> 7 | ... AF8: =RANDBETWEEN(1,10) -> 1 | AH8: =IF(SUM($C8:$AG8)>0,SUM($C8:$AG8),"") -> 192 | AI8: 86 | AJ8: 100 | AK8: =AJ8-AI8 -> 14 | AL8: =AJ8*AH8 -> 19200 | AM8: =AK8*AH8 -> 2688 | AO8: Employee Salary
B9: Acetaminophen | C9: =RANDBETWEEN(1,10) -> 3 | D9: =RANDBETWEEN(1,10) -> 2 | E9: =RANDBETWEEN(1,10) -> 10 | F9: =RANDBETWEEN(1,10) -> 5 | G9: =RANDBETWEEN(1,10) -> 2 | H9: =RANDBETWEEN(1,10) -> 9 | I9: =RANDBETWEEN(1,10) -> 5 | J9: =RANDBETWEEN(1,10) -> 3 | ... AF9: =RANDBETWEEN(1,10) -> 3 | AH9: =IF(SUM($C9:$AG9)>0,SUM($C9:$AG9),"") -> 170 | AI9: 271 | AJ9: 300 | AK9: =AJ9-AI9 -> 29 | AL9: =AJ9*AH9 -> 51000 | AM9: =AK9*AH9 -> 4930 | AO9: Kaishav(Owner) | AP9: ='Attendence (Sep)'!AL3 -> 50000
B10: Ibuprofen | C10: =RANDBETWEEN(1,10) -> 10 | D10: =RANDBETWEEN(1,10) -> 6 | E10: =RANDBETWEEN(1,10) -> 9 | F10: =RANDBETWEEN(1,10) -> 9 | G10: =RANDBETWEEN(1,10) -> 10 | H10: =RANDBETWEEN(1,10) -> 10 | I10: =RANDBETWEEN(1,10) -> 2 | J10: =RANDBETWEEN(1,10) -> 4 | ... AF10: =RANDBETWEEN(1,10) -> 9 | AH10: =IF(SUM($C10:$AG10)>0,SUM($C10:$AG10),"") -> 187 | AI10: 226 | AJ10: 250 | AK10: =AJ10-AI10 -> 24 | AL10: =AJ10*AH10 -> 46750 | AM10: =AK10*AH10 -> 4488 | AO10: Raman | AP10: ='Attendence (Sep)'!AL4 -> 15000
B11: Aspirin | C11: =RANDBETWEEN(1,10) -> 6 | D11: =RANDBETWEEN(1,10) -> 2 | E11: =RANDBETWEEN(1,10) -> 7 | F11: =RANDBETWEEN(1,10) -> 2 | G11: =RANDBETWEEN(1,10) -> 4 | H11: =RANDBETWEEN(1,10) -> 5 | I11: =RANDBETWEEN(1,10) -> 3 | J11: =RANDBETWEEN(1,10) -> 5 | ... AF11: =RANDBETWEEN(1,10) -> 4 | AH11: =IF(SUM($C11:$AG11)>0,SUM($C11:$AG11),"") -> 152 | AI11: 390 | AJ11: 450 | AK11: =AJ11-AI11 -> 60 | AL11: =AJ11*AH11 -> 68400 | AM11: =AK11*AH11 -> 9120 | AO11: Sohan | AP11: ='Attendence (Sep)'!AL5 -> 18000
B12: Amoxicillin | C12: =RANDBETWEEN(1,10) -> 2 | D12: =RANDBETWEEN(1,10) -> 4 | E12: =RANDBETWEEN(1,10) -> 4 | F12: =RANDBETWEEN(1,10) -> 3 | G12: =RANDBETWEEN(1,10) -> 7 | H12: =RANDBETWEEN(1,10) -> 1 | I12: =RANDBETWEEN(1,10) -> 6 | J12: =RANDBETWEEN(1,10) -> 5 | ... AF12: =RANDBETWEEN(1,10) -> 3 | AH12: =IF(SUM($C12:$AG12)>0,SUM($C12:$AG12),"") -> 146 | AI12: 379 | AJ12: 430 | AK12: =AJ12-AI12 -> 51 | AL12: =AJ12*AH12 -> 62780 | AM12: =AK12*AH12 -> 7446 | AO12: Tilak | AP12: ='Attendence (Sep)'!AL6 -> 10000
B13: Ciprofloxacin | C13: =RANDBETWEEN(1,10) -> 5 | D13: =RANDBETWEEN(1,10) -> 5 | E13: =RANDBETWEEN(1,10) -> 1 | F13: =RANDBETWEEN(1,10) -> 5 | G13: =RANDBETWEEN(1,10) -> 2 | H13: =RANDBETWEEN(1,10) -> 10 | I13: =RANDBETWEEN(1,10) -> 9 | J13: =RANDBETWEEN(1,10) -> 1 | ... AF13: =RANDBETWEEN(1,10) -> 2 | AH13: =IF(SUM($C13:$AG13)>0,SUM($C13:$AG13),"") -> 157 | AI13: 368 | AJ13: 435 | AK13: =AJ13-AI13 -> 67 | AL13: =AJ13*AH13 -> 68295 | AM13: =AK13*AH13 -> 10519 | AO13: Bill to pay | AP13: 10000
B14: Lisinopril | C14: =RANDBETWEEN(1,10) -> 5 | D14: =RANDBETWEEN(1,10) -> 8 | E14: =RANDBETWEEN(1,10) -> 8 | F14: =RANDBETWEEN(1,10) -> 1 | G14: =RANDBETWEEN(1,10) -> 7 | H14: =RANDBETWEEN(1,10) -> 5 | I14: =RANDBETWEEN(1,10) -> 8 | J14: =RANDBETWEEN(1,10) -> 8 | ... AF14: =RANDBETWEEN(1,10) -> 1 | AH14: =IF(SUM($C14:$AG14)>0,SUM($C14:$AG14),"") -> 219 | AI14: 88 | AJ14: 99 | AK14: =AJ14-AI14 -> 11 | AL14: =AJ14*AH14 -> 21681 | AM14: =AK14*AH14 -> 2409 | AO14: other | AP14: 2000
B15: Atorvastatin | C15: =RANDBETWEEN(1,10) -> 8 | D15: =RANDBETWEEN(1,10) -> 8 | E15: =RANDBETWEEN(1,10) -> 4 | F15: =RANDBETWEEN(1,10) -> 7 | G15: =RANDBETWEEN(1,10) -> 5 | H15: =RANDBETWEEN(1,10) -> 2 | I15: =RANDBETWEEN(1,10) -> 1 | J15: =RANDBETWEEN(1,10) -> 1 | ... AF15: =RANDBETWEEN(1,10) -> 3 | AH15: =IF(SUM($C15:$AG15)>0,SUM($C15:$AG15),"") -> 148 | AI15: 391 | AJ15: 500 | AK15: =AJ15-AI15 -> 109 | AL15: =AJ15*AH15 -> 74000 | AM15: =AK15*AH15 -> 16132 | AO15: Net collection | AP15: =SUM(AM3:AM57) -> 282662
B16: Metformin | C16: =RANDBETWEEN(1,10) -> 10 | D16: =RANDBETWEEN(1,10) -> 6 | E16: =RANDBETWEEN(1,10) -> 3 | F16: =RANDBETWEEN(1,10) -> 10 | G16: =RANDBETWEEN(1,10) -> 3 | H16: =RANDBETWEEN(1,10) -> 5 | I16: =RANDBETWEEN(1,10) -> 7 | J16: =RANDBETWEEN(1,10) -> 3 | ... AF16: =RANDBETWEEN(1,10) -> 6 | AH16: =IF(SUM($C16:$AG16)>0,SUM($C16:$AG16),"") -> 168 | AI16: 261 | AJ16: 300 | AK16: =AJ16-AI16 -> 39 | AL16: =AJ16*AH16 -> 50400 | AM16: =AK16*AH16 -> 6552 | AO16: Net Income | AP16: =AP15-(AP9+AP10+AP11+AP12+AP13+AP14) -> 177662
B17: Simvastatin | C17: =RANDBETWEEN(1,10) -> 9 | D17: =RANDBETWEEN(1,10) -> 2 | E17: =RANDBETWEEN(1,10) -> 3 | F17: =RANDBETWEEN(1,10) -> 1 | G17: =RANDBETWEEN(1,10) -> 3 | H17: =RANDBETWEEN(1,10) -> 8 | I17: =RANDBETWEEN(1,10) -> 3 | J17: =RANDBETWEEN(1,10) -> 10 | ... AF17: =RANDBETWEEN(1,10) -> 4 | AH17: =IF(SUM($C17:$AG17)>0,SUM($C17:$AG17),"") -> 159 | AI17: 67 | AJ17: 99 | AK17: =AJ17-AI17 -> 32 | AL17: =AJ17*AH17 -> 15741 | AM17: =AK17*AH17 -> 5088
B18: Omeprazole | C18: =RANDBETWEEN(1,10) -> 10 | D18: =RANDBETWEEN(1,10) -> 6 | E18: =RANDBETWEEN(1,10) -> 7 | F18: =RANDBETWEEN(1,10) -> 5 | G18: =RANDBETWEEN(1,10) -> 3 | H18: =RANDBETWEEN(1,10) -> 2 | I18: =RANDBETWEEN(1,10) -> 4 | J18: =RANDBETWEEN(1,10) -> 8 | ... AF18: =RANDBETWEEN(1,10) -> 4 | AH18: =IF(SUM($C18:$AG18)>0,SUM($C18:$AG18),"") -> 142 | AI18: 138 | AJ18: 150 | AK18: =AJ18-AI18 -> 12 | AL18: =AJ18*AH18 -> 21300 | AM18: =AK18*AH18 -> 1704
B19: Clopidogrel | C19: =RANDBETWEEN(1,10) -> 8 | D19: =RANDBETWEEN(1,10) -> 6 | E19: =RANDBETWEEN(1,10) -> 4 | F19: =RANDBETWEEN(1,10) -> 10 | G19: =RANDBETWEEN(1,10) -> 2 | H19: =RANDBETWEEN(1,10) -> 3 | I19: =RANDBETWEEN(1,10) -> 9 | J19: =RANDBETWEEN(1,10) -> 6 | ... AF19: =RANDBETWEEN(1,10) -> 2 | AH19: =IF(SUM($C19:$AG19)>0,SUM($C19:$AG19),"") -> 142 | AI19: 60 | AJ19: 80 | AK19: =AJ19-AI19 -> 20 | AL19: =AJ19*AH19 -> 11360 | AM19: =AK19*AH19 -> 2840
B20: Metoprolol | C20: =RANDBETWEEN(1,10) -> 5 | D20: =RANDBETWEEN(1,10) -> 5 | E20: =RANDBETWEEN(1,10) -> 4 | F20: =RANDBETWEEN(1,10) -> 2 | G20: =RANDBETWEEN(1,10) -> 10 | H20: =RANDBETWEEN(1,10) -> 5 | I20: =RANDBETWEEN(1,10) -> 3 | J20: =RANDBETWEEN(1,10) -> 1 | ... AF20: =RANDBETWEEN(1,10) -> 7 | AH20: =IF(SUM($C20:$AG20)>0,SUM($C20:$AG20),"") -> 138 | AI20: 44 | AJ20: 50 | AK20: =AJ20-AI20 -> 6 | AL20: =AJ20*AH20 -> 6900 | AM20: =AK20*AH20 -> 828
B21: Amlodipine | C21: =RANDBETWEEN(1,10) -> 4 | D21: =RANDBETWEEN(1,10) -> 8 | E21: =RANDBETWEEN(1,10) -> 7 | F21: =RANDBETWEEN(1,10) -> 1 | G21: =RANDBETWEEN(1,10) -> 9 | H21: =RANDBETWEEN(1,10) -> 10 | I21: =RANDBETWEEN(1,10) -> 7 | J21: =RANDBETWEEN(1,10) -> 6 | ... AF21: =RANDBETWEEN(1,10) -> 9 | AH21: =IF(SUM($C21:$AG21)>0,SUM($C21:$AG21),"") -> 177 | AI21: 308 | AJ21: 320 | AK21: =AJ21-AI21 -> 12 | AL21: =AJ21*AH21 -> 56640 | AM21: =AK21*AH21 -> 2124
B22: Alprazolam | C22: =RANDBETWEEN(1,10) -> 4 | D22: =RANDBETWEEN(1,10) -> 9 | E22: =RANDBETWEEN(1,10) -> 2 | F22: =RANDBETWEEN(1,10) -> 5 | G22: =RANDBETWEEN(1,10) -> 5 | H22: =RANDBETWEEN(1,10) -> 6 | I22: =RANDBETWEEN(1,10) -> 1 | J22: =RANDBETWEEN(1,10) -> 8 | ... AF22: =RANDBETWEEN(1,10) -> 3 | AH22: =IF(SUM($C22:$AG22)>0,SUM($C22:$AG22),"") -> 150 | AI22: 234 | AJ22: 250 | AK22: =AJ22-AI22 -> 16 | AL22: =AJ22*AH22 -> 37500 | AM22: =AK22*AH22 -> 2400
B23: Hydrocodone | C23: =RANDBETWEEN(1,10) -> 8 | D23: =RANDBETWEEN(1,10) -> 4 | E23: =RANDBETWEEN(1,10) -> 4 | F23: =RANDBETWEEN(1,10) -> 8 | G23: =RANDBETWEEN(1,10) -> 8 | H23: =RANDBETWEEN(1,10) -> 9 | I23: =RANDBETWEEN(1,10) -> 3 | J23: =RANDBETWEEN(1,10) -> 10 | ... AF23: =RANDBETWEEN(1,10) -> 3 | AH23: =IF(SUM($C23:$AG23)>0,SUM($C23:$AG23),"") -> 164 | AI23: 121 | AJ23: 140 | AK23: =AJ23-AI23 -> 19 | AL23: =AJ23*AH23 -> 22960 | AM23: =AK23*AH23 -> 3116
B24: Gabapentin | C24: =RANDBETWEEN(1,10) -> 8 | D24: =RANDBETWEEN(1,10) -> 4 | E24: =RANDBETWEEN(1,10) -> 7 | F24: =RANDBETWEEN(1,10) -> 8 | G24: =RANDBETWEEN(1,10) -> 3 | H24: =RANDBETWEEN(1,10) -> 10 | I24: =RANDBETWEEN(1,10) -> 3 | J24: =RANDBETWEEN(1,10) -> 8 | ... AF24: =RANDBETWEEN(1,10) -> 6 | AH24: =IF(SUM($C24:$AG24)>0,SUM($C24:$AG24),"") -> 184 | AI24: 350 | AJ24: 390 | AK24: =AJ24-AI24 -> 40 | AL24: =AJ24*AH24 -> 71760 | AM24: =AK24*AH24 -> 7360
B25: Levothyroxine | C25: =RANDBETWEEN(1,10) -> 1 | D25: =RANDBETWEEN(1,10) -> 4 | E25: =RANDBETWEEN(1,10) -> 2 | F25: =RANDBETWEEN(1,10) -> 5 | G25: =RANDBETWEEN(1,10) -> 6 | H25: =RANDBETWEEN(1,10) -> 9 | I25: =RANDBETWEEN(1,10) -> 3 | J25: =RANDBETWEEN(1,10) -> 7 | ... AF25: =RANDBETWEEN(1,10) -> 7 | AH25: =IF(SUM($C25:$AG25)>0,SUM($C25:$AG25),"") -> 157 | AI25: 211 | AJ25: 240 | AK25: =AJ25-AI25 -> 29 | AL25: =AJ25*AH25 -> 37680 | AM25: =AK25*AH25 -> 4553
B26: Sertraline | C26: =RANDBETWEEN(1,10) -> 8 | D26: =RANDBETWEEN(1,10) -> 5 | E26: =RANDBETWEEN(1,10) -> 6 | F26: =RANDBETWEEN(1,10) -> 5 | G26: =RANDBETWEEN(1,10) -> 6 | H26: =RANDBETWEEN(1,10) -> 9 | I26: =RANDBETWEEN(1,10) -> 2 | J26: =RANDBETWEEN(1,10) -> 10 | ... AF26: =RANDBETWEEN(1,10) -> 8 | AH26: =IF(SUM($C26:$AG26)>0,SUM($C26:$AG26),"") -> 169 | AI26: 247 | AJ26: 280 | AK26: =AJ26-AI26 -> 33 | AL26: =AJ26*AH26 -> 47320 | AM26: =AK26*AH26 -> 5577
B27: Azithromycin | C27: =RANDBETWEEN(1,10) -> 1 | D27: =RANDBETWEEN(1,10) -> 4 | E27: =RANDBETWEEN(1,10) -> 8 | F27: =RANDBETWEEN(1,10) -> 10 | G27: =RANDBETWEEN(1,10) -> 9 | H27: =RANDBETWEEN(1,10) -> 5 | I27: =RANDBETWEEN(1,10) -> 6 | J27: =RANDBETWEEN(1,10) -> 5 | ... AF27: =RANDBETWEEN(1,10) -> 1 | AH27: =IF(SUM($C27:$AG27)>0,SUM($C27:$AG27),"") -> 160 | AI27: 286 | AJ27: 320 | AK27: =AJ27-AI27 -> 34 | AL27: =AJ27*AH27 -> 51200 | AM27: =AK27*AH27 -> 5440
B28: Losartan | C28: =RANDBETWEEN(1,10) -> 7 | D28: =RANDBETWEEN(1,10) -> 1 | E28: =RANDBETWEEN(1,10) -> 8 | F28: =RANDBETWEEN(1,10) -> 5 | G28: =RANDBETWEEN(1,10) -> 3 | H28: =RANDBETWEEN(1,10) -> 6 | I28: =RANDBETWEEN(1,10) -> 9 | J28: =RANDBETWEEN(1,10) -> 8 | ... AF28: =RANDBETWEEN(1,10) -> 2 | AH28: =IF(SUM($C28:$AG28)>0,SUM($C28:$AG28),"") -> 172 | AI28: 67 | AJ28: 80 | AK28: =AJ28-AI28 -> 13 | AL28: =AJ28*AH28 -> 13760 | AM28: =AK28*AH28 -> 2236
... B57: Lamotrigine | C57: =RANDBETWEEN(1,10) -> 5 | D57: =RANDBETWEEN(1,10) -> 8 | E57: =RANDBETWEEN(1,10) -> 5 | F57: =RANDBETWEEN(1,10) -> 3 | G57: =RANDBETWEEN(1,10) -> 3 | H57: =RANDBETWEEN(1,10) -> 9 | I57: =RANDBETWEEN(1,10) -> 8 | J57: =RANDBETWEEN(1,10) -> 8 | ... AF57: =RANDBETWEEN(1,10) -> 2 | AH57: =IF(SUM($C57:$AG57)>0,SUM($C57:$AG57),"") -> 153 | AI57: 340 | AJ57: 380 | AK57: =AJ57-AI57 -> 40 | AL57: =AJ57*AH57 -> 58140 | AM57: =AK57*AH57 -> 6120

Sheet October
C1: =TEXT(C2,"DDD") -> Tue | D1: =TEXT(D2,"DDD") -> Wed | E1: =TEXT(E2,"DDD") -> Thu | F1: =TEXT(F2,"DDD") -> Fri | G1: =TEXT(G2,"DDD") -> Sat | H1: =TEXT(H2,"DDD") -> Sun | I1: =TEXT(I2,"DDD") -> Mon | J1: =TEXT(J2,"DDD") -> Tue | ... AG1: =TEXT(AG2,"DDD") -> Thu | AH1: Total Sales | AI1: Incoming price (Including GST) | AJ1: Sales price | AK1: Profit Margin | AL1: Total collection | AM1: Net collection | AO1: Month | AP1: October
B2: Product Name | C2: =IF(COLUMNS($C$2:C2)>DAY($AP$4),"",$AP$3+COLUMNS($C$2:C2)-1) -> 45566 | D2: =IF(COLUMNS($C$2:D2)>DAY($AP$4),"",$AP$3+COLUMNS($C$2:D2)-1) -> 45567 | E2: =IF(COLUMNS($C$2:E2)>DAY($AP$4),"",$AP$3+COLUMNS($C$2:E2)-1) -> 45568 | F2: =IF(COLUMNS($C$2:F2)>DAY($AP$4),"",$AP$3+COLUMNS($C$2:F2)-1) -> 45569 | G2: =IF(COLUMNS($C$2:G2)>DAY($AP$4),"",$AP$3+COLUMNS($C$2:G2)-1) -> 45570 | H2: =IF(COLUMNS($C$2:H2)>DAY($AP$4),"",$AP$3+COLUMNS($C$2:H2)-1) -> 45571 | I2: =IF(COLUMNS($C$2:I2)>DAY($AP$4),"",$AP$3+COLUMNS($C$2:I2)-1) -> 45572 | J2: =IF(COLUMNS($C$2:J2)>DAY($AP$4),"",$AP$3+COLUMNS($C$2:J2)-1) -> 45573 | ... AG2: =IF(COLUMNS($C$2:AG2)>DAY($AP$4),"",$AP$3+COLUMNS($C$2:AG2)-1) -> 45596 | AO2: Year | AP2: 2024
B3: Iodex | C3: 2 | D3: 5 | E3: 7 | F3: 8 | G3: 6 | H3: 4 | I3: 9 | J3: 7 | K3: 5 | L3: 7 | M3: 9 | N3: 4 | O3: 3 | P3: 7 | AH3: =IF(SUM($C3:$AG3)>0,SUM($C3:$AG3),"") -> 83 | AI3: 40 | AJ3: 80 | AK3: =AJ3-AI3 -> 40 | AL3: =AJ3*AH3 -> 6640 | AM3: =IFERROR(AK3*AH3,"") -> 3320 | AO3: Starting Date | AP3: =DATE(AP2,MONTH(AP1&1),1) -> 45566
B4: Nimocet | AH4: =IF(SUM($C4:$AG4)>0,SUM($C4:$AG4),"") | AI4: 7 | AJ4: 15 | AK4: =AJ4-AI4 -> 8 | AL4: =AJ4*AH4 -> #VALUE! | AM4: =IFERROR(AK4*AH4,"") | AO4: Ending Date | AP4: =EOMONTH(AP3,0) -> 45596
B5: Paracetamol | AH5: =IF(SUM($C5:$AG5)>0,SUM($C5:$AG5),"") | AI5: 5 | AJ5: 10 | AK5: =AJ5-AI5 -> 5 | AL5: =AJ5*AH5 -> #VALUE! | AM5: =IFERROR(AK5*AH5,"")
B6: Monocef | AH6: =IF(SUM($C6:$AG6)>0,SUM($C6:$AG6),"") | AI6: 45 | AJ6: 80 | AK6: =AJ6-AI6 -> 35 | AL6: =AJ6*AH6 -> #VALUE! | AM6: =IFERROR(AK6*AH6,"")
B7: Cyclopalm | AH7: =IF(SUM($C7:$AG7)>0,SUM($C7:$AG7),"") | AI7: 392 | AJ7: 420 | AK7: =AJ7-AI7 -> 28 | AL7: =AJ7*AH7 -> #VALUE! | AM7: =IFERROR(AK7*AH7,"") | AO7: Expanses
B8: Cetaphil | AH8: =IF(SUM($C8:$AG8)>0,SUM($C8:$AG8),"") | AI8: 86 | AJ8: 100 | AK8: =AJ8-AI8 -> 14 | AL8: =AJ8*AH8 -> #VALUE! | AM8: =IFERROR(AK8*AH8,"") | AO8: Employee Salary
B9: Acetaminophen | AH9: =IF(SUM($C9:$AG9)>0,SUM($C9:$AG9),"") | AI9: 271 | AJ9: 300 | AK9: =AJ9-AI9 -> 29 | AL9: =AJ9*AH9 -> #VALUE! | AM9: =IFERROR(AK9*AH9,"") | AO9: Kaishav(Owner) | AP9: ='Attendence (Oct)'!AL3 -> 35000
B10: Ibuprofen | AH10: =IF(SUM($C10:$AG10)>0,SUM($C10:$AG10),"") | AI10: 226 | AJ10: 250 | AK10: =AJ10-AI10 -> 24 | AL10: =AJ10*AH10 -> #VALUE! | AM10: =IFERROR(AK10*AH10,"") | AO10: Raman | AP10: ='Attendence (Oct)'!AL4 -> 10500
B11: Aspirin | AH11: =IF(SUM($C11:$AG11)>0,SUM($C11:$AG11),"") | AI11: 390 | AJ11: 450 | AK11: =AJ11-AI11 -> 60 | AL11: =AJ11*AH11 -> #VALUE! | AM11: =IFERROR(AK11*AH11,"") | AO11: Sohan | AP11: ='Attendence (Oct)'!AL5 -> 12600
B12: Amoxicillin | AH12: =IF(SUM($C12:$AG12)>0,SUM($C12:$AG12),"") | AI12: 379 | AJ12: 430 | AK12: =AJ12-AI12 -> 51 | AL12: =AJ12*AH12 -> #VALUE! | AM12: =IFERROR(AK12*AH12,"") | AO12: Tilak | AP12: ='Attendence (Oct)'!AL6 -> 7000
B13: Ciprofloxacin | AH13: =IF(SUM($C13:$AG13)>0,SUM($C13:$AG13),"") | AI13: 368 | AJ13: 435 | AK13: =AJ13-AI13 -> 67 | AL13: =AJ13*AH13 -> #VALUE! | AM13: =IFERROR(AK13*AH13,"") | AO13: Bill to pay | AP13: 10000
B14: Lisinopril | AH14: =IF(SUM($C14:$AG14)>0,SUM($C14:$AG14),"") | AI14: 88 | AJ14: 99 | AK14: =AJ14-AI14 -> 11 | AL14: =AJ14*AH14 -> #VALUE! | AM14: =IFERROR(AK14*AH14,"") | AO14: other | AP14: 2000
B15: Atorvastatin | AH15: =IF(SUM($C15:$AG15)>0,SUM($C15:$AG15),"") | AI15: 391 | AJ15: 500 | AK15: =AJ15-AI15 -> 109 | AL15: =AJ15*AH15 -> #VALUE! | AM15: =IFERROR(AK15*AH15,"") | AO15: Net collection | AP15: =SUM(AM3:AM57) -> 3320
B16: Metformin | AH16: =IF(SUM($C16:$AG16)>0,SUM($C16:$AG16),"") | AI16: 261 | AJ16: 300 | AK16: =AJ16-AI16 -> 39 | AL16: =AJ16*AH16 -> #VALUE! | AM16: =IFERROR(AK16*AH16,"") | AO16: Net Income | AP16: =AP15-(AP9+AP10+AP11+AP12+AP13+AP14) -> -73780
B17: Simvastatin | AH17: =IF(SUM($C17:$AG17)>0,SUM($C17:$AG17),"") | AI17: 67 | AJ17: 99 | AK17: =AJ17-AI17 -> 32 | AL17: =AJ17*AH17 -> #VALUE! | AM17: =IFERROR(AK17*AH17,"")
B18: Omeprazole | AH18: =IF(SUM($C18:$AG18)>0,SUM($C18:$AG18),"") | AI18: 138 | AJ18: 150 | AK18: =AJ18-AI18 -> 12 | AL18: =AJ18*AH18 -> #VALUE! | AM18: =IFERROR(AK18*AH18,"")
B19: Clopidogrel | AH19: =IF(SUM($C19:$AG19)>0,SUM($C19:$AG19),"") | AI19: 60 | AJ19: 80 | AK19: =AJ19-AI19 -> 20 | AL19: =AJ19*AH19 -> #VALUE! | AM19: =IFERROR(AK19*AH19,"")
B20: Metoprolol | AH20: =IF(SUM($C20:$AG20)>0,SUM($C20:$AG20),"") | AI20: 44 | AJ20: 50 | AK20: =AJ20-AI20 -> 6 | AL20: =AJ20*AH20 -> #VALUE! | AM20: =IFERROR(AK20*AH20,"")
B21: Amlodipine | AH21: =IF(SUM($C21:$AG21)>0,SUM($C21:$AG21),"") | AI21: 308 | AJ21: 320 | AK21: =AJ21-AI21 -> 12 | AL21: =AJ21*AH21 -> #VALUE! | AM21: =IFERROR(AK21*AH21,"")
B22: Alprazolam | AH22: =IF(SUM($C22:$AG22)>0,SUM($C22:$AG22),"") | AI22: 234 | AJ22: 250 | AK22: =AJ22-AI22 -> 16 | AL22: =AJ22*AH22 -> #VALUE! | AM22: =IFERROR(AK22*AH22,"")
B23: Hydrocodone | AH23: =IF(SUM($C23:$AG23)>0,SUM($C23:$AG23),"") | AI23: 121 | AJ23: 140 | AK23: =AJ23-AI23 -> 19 | AL23: =AJ23*AH23 -> #VALUE! | AM23: =IFERROR(AK23*AH23,"")
B24: Gabapentin | AH24: =IF(SUM($C24:$AG24)>0,SUM($C24:$AG24),"") | AI24: 350 | AJ24: 390 | AK24: =AJ24-AI24 -> 40 | AL24: =AJ24*AH24 -> #VALUE! | AM24: =IFERROR(AK24*AH24,"")
B25: Levothyroxine | AH25: =IF(SUM($C25:$AG25)>0,SUM($C25:$AG25),"") | AI25: 211 | AJ25: 240 | AK25: =AJ25-AI25 -> 29 | AL25: =AJ25*AH25 -> #VALUE! | AM25: =IFERROR(AK25*AH25,"")
B26: Sertraline | AH26: =IF(SUM($C26:$AG26)>0,SUM($C26:$AG26),"") | AI26: 247 | AJ26: 280 | AK26: =AJ26-AI26 -> 33 | AL26: =AJ26*AH26 -> #VALUE! | AM26: =IFERROR(AK26*AH26,"")
B27: Azithromycin | AH27: =IF(SUM($C27:$AG27)>0,SUM($C27:$AG27),"") | AI27: 286 | AJ27: 320 | AK27: =AJ27-AI27 -> 34 | AL27: =AJ27*AH27 -> #VALUE! | AM27: =IFERROR(AK27*AH27,"")
B28: Losartan | AH28: =IF(SUM($C28:$AG28)>0,SUM($C28:$AG28),"") | AI28: 67 | AJ28: 80 | AK28: =AJ28-AI28 -> 13 | AL28: =AJ28*AH28 -> #VALUE! | AM28: =IFERROR(AK28*AH28,"")
... B57: Lamotrigine | AH57: =IF(SUM($C57:$AG57)>0,SUM($C57:$AG57),"") | AI57: 340 | AJ57: 380 | AK57: =AJ57-AI57 -> 40 | AL57: =AJ57*AH57 -> #VALUE! | AM57: =IFERROR(AK57*AH57,"")

Sheet November
C1: =TEXT(C2,"DDD") -> Fri | D1: =TEXT(D2,"DDD") -> Sat | E1: =TEXT(E2,"DDD") -> Sun | F1: =TEXT(F2,"DDD") -> Mon | G1: =TEXT(G2,"DDD") -> Tue | H1: =TEXT(H2,"DDD") -> Wed | I1: =TEXT(I2,"DDD") -> Thu | J1: =TEXT(J2,"DDD") -> Fri | ... AG1: =TEXT(AG2,"DDD") | AH1: Total Sales | AI1: Incoming price (Including GST) | AJ1: Sales price | AK1: Profit Margin | AL1: Total collection | AM1: Net collection | AO1: Month | AP1: November
B2: Product Name | C2: =IF(COLUMNS($C$2:C2)>DAY($AP$4),"",$AP$3+COLUMNS($C$2:C2)-1) -> 45597 | D2: =IF(COLUMNS($C$2:D2)>DAY($AP$4),"",$AP$3+COLUMNS($C$2:D2)-1) -> 45598 | E2: =IF(COLUMNS($C$2:E2)>DAY($AP$4),"",$AP$3+COLUMNS($C$2:E2)-1) -> 45599 | F2: =IF(COLUMNS($C$2:F2)>DAY($AP$4),"",$AP$3+COLUMNS($C$2:F2)-1) -> 45600 | G2: =IF(COLUMNS($C$2:G2)>DAY($AP$4),"",$AP$3+COLUMNS($C$2:G2)-1) -> 45601 | H2: =IF(COLUMNS($C$2:H2)>DAY($AP$4),"",$AP$3+COLUMNS($C$2:H2)-1) -> 45602 | I2: =IF(COLUMNS($C$2:I2)>DAY($AP$4),"",$AP$3+COLUMNS($C$2:I2)-1) -> 45603 | J2: =IF(COLUMNS($C$2:J2)>DAY($AP$4),"",$AP$3+COLUMNS($C$2:J2)-1) -> 45604 | ... AG2: =IF(COLUMNS($C$2:AG2)>DAY($AP$4),"",$AP$3+COLUMNS($C$2:AG2)-1) | AO2: Year | AP2: 2024
B3: Iodex | C3: 2 | D3: 5 | E3: 7 | F3: 8 | G3: 6 | H3: 4 | I3: 9 | J3: 7 | K3: 5 | L3: 7 | M3: 9 | N3: 4 | O3: 3 | P3: 7 | AH3: =IF(SUM($C3:$AG3)>0,SUM($C3:$AG3),"") -> 83 | AI3: 40 | AJ3: 80 | AK3: =AJ3-AI3 -> 40 | AL3: =AJ3*AH3 -> 6640 | AM3: =IFERROR(AK3*AH3,"") -> 3320 | AO3: Starting Date | AP3: =DATE(AP2,MONTH(AP1&1),1) -> 45597
B4: Nimocet | AH4: =IF(SUM($C4:$AG4)>0,SUM($C4:$AG4),"") | AI4: 7 | AJ4: 15 | AK4: =AJ4-AI4 -> 8 | AL4: =AJ4*AH4 -> #VALUE! | AM4: =IFERROR(AK4*AH4,"") | AO4: Ending Date | AP4: =EOMONTH(AP3,0) -> 45626
B5: Paracetamol | AH5: =IF(SUM($C5:$AG5)>0,SUM($C5:$AG5),"") | AI5: 5 | AJ5: 10 | AK5: =AJ5-AI5 -> 5 | AL5: =AJ5*AH5 -> #VALUE! | AM5: =IFERROR(AK5*AH5,"")
B6: Monocef | AH6: =IF(SUM($C6:$AG6)>0,SUM($C6:$AG6),"") | AI6: 45 | AJ6: 80 | AK6: =AJ6-AI6 -> 35 | AL6: =AJ6*AH6 -> #VALUE! | AM6: =IFERROR(AK6*AH6,"")
B7: Cyclopalm | AH7: =IF(SUM($C7:$AG7)>0,SUM($C7:$AG7),"") | AI7: 392 | AJ7: 420 | AK7: =AJ7-AI7 -> 28 | AL7: =AJ7*AH7 -> #VALUE! | AM7: =IFERROR(AK7*AH7,"") | AO7: Expanses
B8: Cetaphil | AH8: =IF(SUM($C8:$AG8)>0,SUM($C8:$AG8),"") | AI8: 86 | AJ8: 100 | AK8: =AJ8-AI8 -> 14 | AL8: =AJ8*AH8 -> #VALUE! | AM8: =IFERROR(AK8*AH8,"") | AO8: Employee Salary
B9: Acetaminophen | AH9: =IF(SUM($C9:$AG9)>0,SUM($C9:$AG9),"") | AI9: 271 | AJ9: 300 | AK9: =AJ9-AI9 -> 29 | AL9: =AJ9*AH9 -> #VALUE! | AM9: =IFERROR(AK9*AH9,"") | AO9: Kaishav(Owner) | AP9: ='Attendence (Nov)'!AL3 -> 0
B10: Ibuprofen | AH10: =IF(SUM($C10:$AG10)>0,SUM($C10:$AG10),"") | AI10: 226 | AJ10: 250 | AK10: =AJ10-AI10 -> 24 | AL10: =AJ10*AH10 -> #VALUE! | AM10: =IFERROR(AK10*AH10,"") | AO10: Raman | AP10: ='Attendence (Nov)'!AL4 -> 0
B11: Aspirin | AH11: =IF(SUM($C11:$AG11)>0,SUM($C11:$AG11),"") | AI11: 390 | AJ11: 450 | AK11: =AJ11-AI11 -> 60 | AL11: =AJ11*AH11 -> #VALUE! | AM11: =IFERROR(AK11*AH11,"") | AO11: Sohan | AP11: ='Attendence (Nov)'!AL5 -> 0
B12: Amoxicillin | AH12: =IF(SUM($C12:$AG12)>0,SUM($C12:$AG12),"") | AI12: 379 | AJ12: 430 | AK12: =AJ12-AI12 -> 51 | AL12: =AJ12*AH12 -> #VALUE! | AM12: =IFERROR(AK12*AH12,"") | AO12: Tilak | AP12: ='Attendence (Nov)'!AL6 -> 0
B13: Ciprofloxacin | AH13: =IF(SUM($C13:$AG13)>0,SUM($C13:$AG13),"") | AI13: 368 | AJ13: 435 | AK13: =AJ13-AI13 -> 67 | AL13: =AJ13*AH13 -> #VALUE! | AM13: =IFERROR(AK13*AH13,"") | AO13: Bill to pay | AP13: 10000
B14: Lisinopril | AH14: =IF(SUM($C14:$AG14)>0,SUM($C14:$AG14),"") | AI14: 88 | AJ14: 99 | AK14: =AJ14-AI14 -> 11 | AL14: =AJ14*AH14 -> #VALUE! | AM14: =IFERROR(AK14*AH14,"") | AO14: other | AP14: 2000
B15: Atorvastatin | AH15: =IF(SUM($C15:$AG15)>0,SUM($C15:$AG15),"") | AI15: 391 | AJ15: 500 | AK15: =AJ15-AI15 -> 109 | AL15: =AJ15*AH15 -> #VALUE! | AM15: =IFERROR(AK15*AH15,"") | AO15: Net collection | AP15: =SUM(AM3:AM57) -> 3320
B16: Metformin | AH16: =IF(SUM($C16:$AG16)>0,SUM($C16:$AG16),"") | AI16: 261 | AJ16: 300 | AK16: =AJ16-AI16 -> 39 | AL16: =AJ16*AH16 -> #VALUE! | AM16: =IFERROR(AK16*AH16,"") | AO16: Net Income | AP16: =AP15-(AP9+AP10+AP11+AP12+AP13+AP14) -> -8680
B17: Simvastatin | AH17: =IF(SUM($C17:$AG17)>0,SUM($C17:$AG17),"") | AI17: 67 | AJ17: 99 | AK17: =AJ17-AI17 -> 32 | AL17: =AJ17*AH17 -> #VALUE! | AM17: =IFERROR(AK17*AH17,"")
B18: Omeprazole | AH18: =IF(SUM($C18:$AG18)>0,SUM($C18:$AG18),"") | AI18: 138 | AJ18: 150 | AK18: =AJ18-AI18 -> 12 | AL18: =AJ18*AH18 -> #VALUE! | AM18: =IFERROR(AK18*AH18,"")
B19: Clopidogrel | AH19: =IF(SUM($C19:$AG19)>0,SUM($C19:$AG19),"") | AI19: 60 | AJ19: 80 | AK19: =AJ19-AI19 -> 20 | AL19: =AJ19*AH19 -> #VALUE! | AM19: =IFERROR(AK19*AH19,"")
B20: Metoprolol | AH20: =IF(SUM($C20:$AG20)>0,SUM($C20:$AG20),"") | AI20: 44 | AJ20: 50 | AK20: =AJ20-AI20 -> 6 | AL20: =AJ20*AH20 -> #VALUE! | AM20: =IFERROR(AK20*AH20,"")
B21: Amlodipine | AH21: =IF(SUM($C21:$AG21)>0,SUM($C21:$AG21),"") | AI21: 308 | AJ21: 320 | AK21: =AJ21-AI21 -> 12 | AL21: =AJ21*AH21 -> #VALUE! | AM21: =IFERROR(AK21*AH21,"")
B22: Alprazolam | AH22: =IF(SUM($C22:$AG22)>0,SUM($C22:$AG22),"") | AI22: 234 | AJ22: 250 | AK22: =AJ22-AI22 -> 16 | AL22: =AJ22*AH22 -> #VALUE! | AM22: =IFERROR(AK22*AH22,"")
B23: Hydrocodone | AH23: =IF(SUM($C23:$AG23)>0,SUM($C23:$AG23),"") | AI23: 121 | AJ23: 140 | AK23: =AJ23-AI23 -> 19 | AL23: =AJ23*AH23 -> #VALUE! | AM23: =IFERROR(AK23*AH23,"")
B24: Gabapentin | AH24: =IF(SUM($C24:$AG24)>0,SUM($C24:$AG24),"") | AI24: 350 | AJ24: 390 | AK24: =AJ24-AI24 -> 40 | AL24: =AJ24*AH24 -> #VALUE! | AM24: =IFERROR(AK24*AH24,"")
B25: Levothyroxine | AH25: =IF(SUM($C25:$AG25)>0,SUM($C25:$AG25),"") | AI25: 211 | AJ25: 240 | AK25: =AJ25-AI25 -> 29 | AL25: =AJ25*AH25 -> #VALUE! | AM25: =IFERROR(AK25*AH25,"")
B26: Sertraline | AH26: =IF(SUM($C26:$AG26)>0,SUM($C26:$AG26),"") | AI26: 247 | AJ26: 280 | AK26: =AJ26-AI26 -> 33 | AL26: =AJ26*AH26 -> #VALUE! | AM26: =IFERROR(AK26*AH26,"")
B27: Azithromycin | AH27: =IF(SUM($C27:$AG27)>0,SUM($C27:$AG27),"") | AI27: 286 | AJ27: 320 | AK27: =AJ27-AI27 -> 34 | AL27: =AJ27*AH27 -> #VALUE! | AM27: =IFERROR(AK27*AH27,"")
B28: Losartan | AH28: =IF(SUM($C28:$AG28)>0,SUM($C28:$AG28),"") | AI28: 67 | AJ28: 80 | AK28: =AJ28-AI28 -> 13 | AL28: =AJ28*AH28 -> #VALUE! | AM28: =IFERROR(AK28*AH28,"")
... B57: Lamotrigine | AH57: =IF(SUM($C57:$AG57)>0,SUM($C57:$AG57),"") | AI57: 340 | AJ57: 380 | AK57: =AJ57-AI57 -> 40 | AL57: =AJ57*AH57 -> #VALUE! | AM57: =IFERROR(AK57*AH57,"")

Sheet December
C1: =TEXT(C2,"DDD") -> Sun | D1: =TEXT(D2,"DDD") -> Mon | E1: =TEXT(E2,"DDD") -> Tue | F1: =TEXT(F2,"DDD") -> Wed | G1: =TEXT(G2,"DDD") -> Thu | H1: =TEXT(H2,"DDD") -> Fri | I1: =TEXT(I2,"DDD") -> Sat | J1: =TEXT(J2,"DDD") -> Sun | ... AG1: =TEXT(AG2,"DDD") -> Tue | AH1: Total Sales | AI1: Incoming price (Including GST) | AJ1: Sales price | AK1: Profit Margin | AL1: Total collection | AM1: Net collection | AO1: Month | AP1: December
B2: Product Name | C2: =IF(COLUMNS($C$2:C2)>DAY($AP$4),"",$AP$3+COLUMNS($C$2:C2)-1) -> 45627 | D2: =IF(COLUMNS($C$2:D2)>DAY($AP$4),"",$AP$3+COLUMNS($C$2:D2)-1) -> 45628 | E2: =IF(COLUMNS($C$2:E2)>DAY($AP$4),"",$AP$3+COLUMNS($C$2:E2)-1) -> 45629 | F2: =IF(COLUMNS($C$2:F2)>DAY($AP$4),"",$AP$3+COLUMNS($C$2:F2)-1) -> 45630 | G2: =IF(COLUMNS($C$2:G2)>DAY($AP$4),"",$AP$3+COLUMNS($C$2:G2)-1) -> 45631 | H2: =IF(COLUMNS($C$2:H2)>DAY($AP$4),"",$AP$3+COLUMNS($C$2:H2)-1) -> 45632 | I2: =IF(COLUMNS($C$2:I2)>DAY($AP$4),"",$AP$3+COLUMNS($C$2:I2)-1) -> 45633 | J2: =IF(COLUMNS($C$2:J2)>DAY($AP$4),"",$AP$3+COLUMNS($C$2:J2)-1) -> 45634 | ... AG2: =IF(COLUMNS($C$2:AG2)>DAY($AP$4),"",$AP$3+COLUMNS($C$2:AG2)-1) -> 45657 | AO2: Year | AP2: 2024
B3: Iodex | C3: 2 | D3: 5 | E3: 7 | F3: 8 | G3: 6 | H3: 4 | I3: 9 | J3: 7 | K3: 5 | L3: 7 | M3: 9 | N3: 4 | O3: 3 | P3: 7 | AH3: =IF(SUM($C3:$AG3)>0,SUM($C3:$AG3),"") -> 83 | AI3: 40 | AJ3: 80 | AK3: =AJ3-AI3 -> 40 | AL3: =AJ3*AH3 -> 6640 | AM3: =IFERROR(AK3*AH3,"") -> 3320 | AO3: Starting Date | AP3: =DATE(AP2,MONTH(AP1&1),1) -> 45627
B4: Nimocet | AH4: =IF(SUM($C4:$AG4)>0,SUM($C4:$AG4),"") | AI4: 7 | AJ4: 15 | AK4: =AJ4-AI4 -> 8 | AL4: =AJ4*AH4 -> #VALUE! | AM4: =IFERROR(AK4*AH4,"") | AO4: Ending Date | AP4: =EOMONTH(AP3,0) -> 45657
B5: Paracetamol | AH5: =IF(SUM($C5:$AG5)>0,SUM($C5:$AG5),"") | AI5: 5 | AJ5: 10 | AK5: =AJ5-AI5 -> 5 | AL5: =AJ5*AH5 -> #VALUE! | AM5: =IFERROR(AK5*AH5,"")
B6: Monocef | AH6: =IF(SUM($C6:$AG6)>0,SUM($C6:$AG6),"") | AI6: 45 | AJ6: 80 | AK6: =AJ6-AI6 -> 35 | AL6: =AJ6*AH6 -> #VALUE! | AM6: =IFERROR(AK6*AH6,"")
B7: Cyclopalm | AH7: =IF(SUM($C7:$AG7)>0,SUM($C7:$AG7),"") | AI7: 392 | AJ7: 420 | AK7: =AJ7-AI7 -> 28 | AL7: =AJ7*AH7 -> #VALUE! | AM7: =IFERROR(AK7*AH7,"") | AO7: Expanses
B8: Cetaphil | AH8: =IF(SUM($C8:$AG8)>0,SUM($C8:$AG8),"") | AI8: 86 | AJ8: 100 | AK8: =AJ8-AI8 -> 14 | AL8: =AJ8*AH8 -> #VALUE! | AM8: =IFERROR(AK8*AH8,"") | AO8: Employee Salary
B9: Acetaminophen | AH9: =IF(SUM($C9:$AG9)>0,SUM($C9:$AG9),"") | AI9: 271 | AJ9: 300 | AK9: =AJ9-AI9 -> 29 | AL9: =AJ9*AH9 -> #VALUE! | AM9: =IFERROR(AK9*AH9,"") | AO9: Kaishav(Owner) | AP9: ='Attendence (Dec)'!AL3 -> 0
B10: Ibuprofen | AH10: =IF(SUM($C10:$AG10)>0,SUM($C10:$AG10),"") | AI10: 226 | AJ10: 250 | AK10: =AJ10-AI10 -> 24 | AL10: =AJ10*AH10 -> #VALUE! | AM10: =IFERROR(AK10*AH10,"") | AO10: Raman | AP10: ='Attendence (Dec)'!AL4 -> 0
B11: Aspirin | AH11: =IF(SUM($C11:$AG11)>0,SUM($C11:$AG11),"") | AI11: 390 | AJ11: 450 | AK11: =AJ11-AI11 -> 60 | AL11: =AJ11*AH11 -> #VALUE! | AM11: =IFERROR(AK11*AH11,"") | AO11: Sohan | AP11: ='Attendence (Dec)'!AL5 -> 0
B12: Amoxicillin | AH12: =IF(SUM($C12:$AG12)>0,SUM($C12:$AG12),"") | AI12: 379 | AJ12: 430 | AK12: =AJ12-AI12 -> 51 | AL12: =AJ12*AH12 -> #VALUE! | AM12: =IFERROR(AK12*AH12,"") | AO12: Tilak | AP12: ='Attendence (Dec)'!AL6 -> 0
B13: Ciprofloxacin | AH13: =IF(SUM($C13:$AG13)>0,SUM($C13:$AG13),"") | AI13: 368 | AJ13: 435 | AK13: =AJ13-AI13 -> 67 | AL13: =AJ13*AH13 -> #VALUE! | AM13: =IFERROR(AK13*AH13,"") | AO13: Bill to pay | AP13: 10000
B14: Lisinopril | AH14: =IF(SUM($C14:$AG14)>0,SUM($C14:$AG14),"") | AI14: 88 | AJ14: 99 | AK14: =AJ14-AI14 -> 11 | AL14: =AJ14*AH14 -> #VALUE! | AM14: =IFERROR(AK14*AH14,"") | AO14: other | AP14: 2000
B15: Atorvastatin | AH15: =IF(SUM($C15:$AG15)>0,SUM($C15:$AG15),"") | AI15: 391 | AJ15: 500 | AK15: =AJ15-AI15 -> 109 | AL15: =AJ15*AH15 -> #VALUE! | AM15: =IFERROR(AK15*AH15,"") | AO15: Net collection | AP15: =SUM(AM3:AM57) -> 3320
B16: Metformin | AH16: =IF(SUM($C16:$AG16)>0,SUM($C16:$AG16),"") | AI16: 261 | AJ16: 300 | AK16: =AJ16-AI16 -> 39 | AL16: =AJ16*AH16 -> #VALUE! | AM16: =IFERROR(AK16*AH16,"") | AO16: Net Income | AP16: =AP15-(AP9+AP10+AP11+AP12+AP13+AP14) -> -8680
B17: Simvastatin | AH17: =IF(SUM($C17:$AG17)>0,SUM($C17:$AG17),"") | AI17: 67 | AJ17: 99 | AK17: =AJ17-AI17 -> 32 | AL17: =AJ17*AH17 -> #VALUE! | AM17: =IFERROR(AK17*AH17,"")
B18: Omeprazole | AH18: =IF(SUM($C18:$AG18)>0,SUM($C18:$AG18),"") | AI18: 138 | AJ18: 150 | AK18: =AJ18-AI18 -> 12 | AL18: =AJ18*AH18 -> #VALUE! | AM18: =IFERROR(AK18*AH18,"")
B19: Clopidogrel | AH19: =IF(SUM($C19:$AG19)>0,SUM($C19:$AG19),"") | AI19: 60 | AJ19: 80 | AK19: =AJ19-AI19 -> 20 | AL19: =AJ19*AH19 -> #VALUE! | AM19: =IFERROR(AK19*AH19,"")
B20: Metoprolol | AH20: =IF(SUM($C20:$AG20)>0,SUM($C20:$AG20),"") | AI20: 44 | AJ20: 50 | AK20: =AJ20-AI20 -> 6 | AL20: =AJ20*AH20 -> #VALUE! | AM20: =IFERROR(AK20*AH20,"")
B21: Amlodipine | AH21: =IF(SUM($C21:$AG21)>0,SUM($C21:$AG21),"") | AI21: 308 | AJ21: 320 | AK21: =AJ21-AI21 -> 12 | AL21: =AJ21*AH21 -> #VALUE! | AM21: =IFERROR(AK21*AH21,"")
B22: Alprazolam | AH22: =IF(SUM($C22:$AG22)>0,SUM($C22:$AG22),"") | AI22: 234 | AJ22: 250 | AK22: =AJ22-AI22 -> 16 | AL22: =AJ22*AH22 -> #VALUE! | AM22: =IFERROR(AK22*AH22,"")
B23: Hydrocodone | AH23: =IF(SUM($C23:$AG23)>0,SUM($C23:$AG23),"") | AI23: 121 | AJ23: 140 | AK23: =AJ23-AI23 -> 19 | AL23: =AJ23*AH23 -> #VALUE! | AM23: =IFERROR(AK23*AH23,"")
B24: Gabapentin | AH24: =IF(SUM($C24:$AG24)>0,SUM($C24:$AG24),"") | AI24: 350 | AJ24: 390 | AK24: =AJ24-AI24 -> 40 | AL24: =AJ24*AH24 -> #VALUE! | AM24: =IFERROR(AK24*AH24,"")
B25: Levothyroxine | AH25: =IF(SUM($C25:$AG25)>0,SUM($C25:$AG25),"") | AI25: 211 | AJ25: 240 | AK25: =AJ25-AI25 -> 29 | AL25: =AJ25*AH25 -> #VALUE! | AM25: =IFERROR(AK25*AH25,"")
B26: Sertraline | AH26: =IF(SUM($C26:$AG26)>0,SUM($C26:$AG26),"") | AI26: 247 | AJ26: 280 | AK26: =AJ26-AI26 -> 33 | AL26: =AJ26*AH26 -> #VALUE! | AM26: =IFERROR(AK26*AH26,"")
B27: Azithromycin | AH27: =IF(SUM($C27:$AG27)>0,SUM($C27:$AG27),"") | AI27: 286 | AJ27: 320 | AK27: =AJ27-AI27 -> 34 | AL27: =AJ27*AH27 -> #VALUE! | AM27: =IFERROR(AK27*AH27,"")
B28: Losartan | AH28: =IF(SUM($C28:$AG28)>0,SUM($C28:$AG28),"") | AI28: 67 | AJ28: 80 | AK28: =AJ28-AI28 -> 13 | AL28: =AJ28*AH28 -> #VALUE! | AM28: =IFERROR(AK28*AH28,"")
... B57: Lamotrigine | AH57: =IF(SUM($C57:$AG57)>0,SUM($C57:$AG57),"") | AI57: 340 | AJ57: 380 | AK57: =AJ57-AI57 -> 40 | AL57: =AJ57*AH57 -> #VALUE! | AM57: =IFERROR(AK57*AH57,"")

Sheet Attendence (Jan)
C1: =TEXT(C2,"DDD") -> Mon | D1: =TEXT(D2,"DDD") -> Tue | E1: =TEXT(E2,"DDD") -> Wed | F1: =TEXT(F2,"DDD") -> Thu | G1: =TEXT(G2,"DDD") -> Fri | H1: =TEXT(H2,"DDD") -> Sat | I1: =TEXT(I2,"DDD") -> Sun | J1: =TEXT(J2,"DDD") -> Mon | ... AG1: =TEXT(AG2,"DDD") -> Wed | AH1: Monthly Salary(avg) | AI1: Present | AJ1: Absent | AK1: Leave | AL1: Net Salary | AM1: Month | AN1: January
B2: Employee Name | C2: =IF(COLUMNS($C$2:C2)>DAY($AN$4),"",$AN$3+COLUMNS($C$2:C2)-1) -> 45292 | D2: =IF(COLUMNS($C$2:D2)>DAY($AN$4),"",$AN$3+COLUMNS($C$2:D2)-1) -> 45293 | E2: =IF(COLUMNS($C$2:E2)>DAY($AN$4),"",$AN$3+COLUMNS($C$2:E2)-1) -> 45294 | F2: =IF(COLUMNS($C$2:F2)>DAY($AN$4),"",$AN$3+COLUMNS($C$2:F2)-1) -> 45295 | G2: =IF(COLUMNS($C$2:G2)>DAY($AN$4),"",$AN$3+COLUMNS($C$2:G2)-1) -> 45296 | H2: =IF(COLUMNS($C$2:H2)>DAY($AN$4),"",$AN$3+COLUMNS($C$2:H2)-1) -> 45297 | I2: =IF(COLUMNS($C$2:I2)>DAY($AN$4),"",$AN$3+COLUMNS($C$2:I2)-1) -> 45298 | J2: =IF(COLUMNS($C$2:J2)>DAY($AN$4),"",$AN$3+COLUMNS($C$2:J2)-1) -> 45299 | ... AG2: =IF(COLUMNS($C$2:AG2)>DAY($AN$4),"",$AN$3+COLUMNS($C$2:AG2)-1) -> 45322 | AM2: Year | AN2: 2024
B3: Kaishav(Owner) | C3: p | D3: p | E3: p | F3: p | G3: p | H3: p | I3: p | J3: p | K3: p | L3: ab | M3: p | N3: p | O3: p | P3: p | Q3: p | R3: p | S3: p | T3: p | U3: p | V3: p | W3: p | X3: p | Y3: p | Z3: p | AA3: l | AB3: p | AC3: p | AD3: p | AE3: p | AF3: p | AG3: p | AH3: 50000 | AI3: =COUNTIF($C3:$AG3,"P") -> 29 | AJ3: =COUNTIF($C3:$AG3,"Ab") -> 1 | AK3: =COUNTIF($C3:$AG3,"L") -> 1 | AL3: =AH3/30*(AI3+AK3) -> 50000 | AM3: Starting Date | AN3: =DATE(AN2,MONTH(AN1&1),1) -> 45292
B4: Raman | C4: p | D4: p | E4: p | F4: p | G4: p | H4: p | I4: p | J4: p | K4: p | L4: p | M4: p | N4: p | O4: p | P4: p | Q4: p | R4: ab | S4: p | T4: p | U4: p | V4: ab | W4: p | X4: p | Y4: p | Z4: p | AA4: p | AB4: p | AC4: p | AD4: p | AE4: p | AF4: p | AG4: p | AH4: 15000 | AI4: =COUNTIF($C4:$AG4,"P") -> 29 | AJ4: =COUNTIF($C4:$AG4,"Ab") -> 2 | AK4: =COUNTIF($C4:$AG4,"L") -> 0 | AL4: =AH4/30*(AI4+AK4) -> 14500 | AM4: Ending Date | AN4: =EOMONTH(AN3,0) -> 45322
B5: Sohan | C5: p | D5: p | E5: p | F5: ab | G5: p | H5: p | I5: p | J5: p | K5: p | L5: p | M5: p | N5: p | O5: p | P5: p | Q5: p | R5: p | S5: p | T5: p | U5: p | V5: p | W5: p | X5: ab | Y5: p | Z5: p | AA5: p | AB5: p | AC5: p | AD5: p | AE5: p | AF5: p | AG5: p | AH5: 18000 | AI5: =COUNTIF($C5:$AG5,"P") -> 29 | AJ5: =COUNTIF($C5:$AG5,"Ab") -> 2 | AK5: =COUNTIF($C5:$AG5,"L") -> 0 | AL5: =AH5/30*(AI5+AK5) -> 17400
B6: Tilak | C6: p | D6: p | E6: p | F6: p | G6: p | H6: p | I6: p | J6: p | K6: p | L6: p | M6: p | N6: p | O6: ab | P6: p | Q6: p | R6: p | S6: p | T6: p | U6: p | V6: p | W6: p | X6: p | Y6: p | Z6: p | AA6: p | AB6: p | AC6: ab | AD6: p | AE6: p | AF6: p | AG6: p | AH6: 10000 | AI6: =COUNTIF($C6:$AG6,"P") -> 29 | AJ6: =COUNTIF($C6:$AG6,"Ab") -> 2 | AK6: =COUNTIF($C6:$AG6,"L") -> 0 | AL6: =AH6/30*(AI6+AK6) -> 9666.6667

Sheet Attendence (Feb)
C1: =TEXT(C2,"DDD") -> Thu | D1: =TEXT(D2,"DDD") -> Fri | E1: =TEXT(E2,"DDD") -> Sat | F1: =TEXT(F2,"DDD") -> Sun | G1: =TEXT(G2,"DDD") -> Mon | H1: =TEXT(H2,"DDD") -> Tue | I1: =TEXT(I2,"DDD") -> Wed | J1: =TEXT(J2,"DDD") -> Thu | ... AG1: =TEXT(AG2,"DDD") | AH1: Monthly Salary(avg) | AI1: Present | AJ1: Absent | AK1: Leave | AL1: Net Salary | AM1: Month | AN1: February
B2: Employee Name | C2: =IF(COLUMNS($C$2:C2)>DAY($AN$4),"",$AN$3+COLUMNS($C$2:C2)-1) -> 45323 | D2: =IF(COLUMNS($C$2:D2)>DAY($AN$4),"",$AN$3+COLUMNS($C$2:D2)-1) -> 45324 | E2: =IF(COLUMNS($C$2:E2)>DAY($AN$4),"",$AN$3+COLUMNS($C$2:E2)-1) -> 45325 | F2: =IF(COLUMNS($C$2:F2)>DAY($AN$4),"",$AN$3+COLUMNS($C$2:F2)-1) -> 45326 | G2: =IF(COLUMNS($C$2:G2)>DAY($AN$4),"",$AN$3+COLUMNS($C$2:G2)-1) -> 45327 | H2: =IF(COLUMNS($C$2:H2)>DAY($AN$4),"",$AN$3+COLUMNS($C$2:H2)-1) -> 45328 | I2: =IF(COLUMNS($C$2:I2)>DAY($AN$4),"",$AN$3+COLUMNS($C$2:I2)-1) -> 45329 | J2: =IF(COLUMNS($C$2:J2)>DAY($AN$4),"",$AN$3+COLUMNS($C$2:J2)-1) -> 45330 | ... AG2: =IF(COLUMNS($C$2:AG2)>DAY($AN$4),"",$AN$3+COLUMNS($C$2:AG2)-1) | AM2: Year | AN2: 2024
B3: Kaishav(Owner) | C3: p | D3: p | E3: p | F3: p | G3: p | H3: p | I3: p | J3: p | K3: p | L3: p | M3: p | N3: p | O3: p | P3: ab | Q3: p | R3: p | S3: p | T3: p | U3: p | V3: p | W3: p | X3: p | Y3: p | Z3: p | AA3: p | AB3: p | AC3: p | AD3: p | AE3: p | AH3: 50000 | AI3: =COUNTIF($C3:$AG3,"P") -> 28 | AJ3: =COUNTIF($C3:$AG3,"Ab") -> 1 | AK3: =COUNTIF($C3:$AG3,"L") -> 0 | AL3: =AH3/30*(AI3+AK3) -> 46666.667 | AM3: Starting Date | AN3: =DATE(AN2,MONTH(AN1&1),1) -> 45323
B4: Raman | C4: p | D4: p | E4: p | F4: p | G4: p | H4: ab | I4: ab | J4: p | K4: p | L4: p | M4: p | N4: p | O4: p | P4: p | Q4: p | R4: p | S4: p | T4: p | U4: p | V4: p | W4: p | X4: p | Y4: p | Z4: p | AA4: p | AB4: p | AC4: p | AD4: p | AE4: p | AH4: 15000 | AI4: =COUNTIF($C4:$AG4,"P") -> 27 | AJ4: =COUNTIF($C4:$AG4,"Ab") -> 2 | AK4: =COUNTIF($C4:$AG4,"L") -> 0 | AL4: =AH4/30*(AI4+AK4) -> 13500 | AM4: Ending Date | AN4: =EOMONTH(AN3,0) -> 45351
B5: Sohan | C5: p | D5: p | E5: p | F5: p | G5: p | H5: p | I5: p | J5: p | K5: p | L5: ab | M5: p | N5: p | O5: p | P5: p | Q5: p | R5: p | S5: p | T5: p | U5: p | V5: p | W5: p | X5: p | Y5: p | Z5: l | AA5: p | AB5: p | AC5: p | AD5: p | AE5: p | AH5: 18000 | AI5: =COUNTIF($C5:$AG5,"P") -> 27 | AJ5: =COUNTIF($C5:$AG5,"Ab") -> 1 | AK5: =COUNTIF($C5:$AG5,"L") -> 1 | AL5: =AH5/30*(AI5+AK5) -> 16800
B6: Tilak | C6: p | D6: p | E6: ab | F6: p | G6: p | H6: p | I6: p | J6: p | K6: p | L6: p | M6: p | N6: p | O6: p | P6: p | Q6: p | R6: p | S6: p | T6: p | U6: ab | V6: p | W6: p | X6: p | Y6: p | Z6: p | AA6: p | AB6: p | AC6: p | AD6: p | AE6: p | AH6: 10000 | AI6: =COUNTIF($C6:$AG6,"P") -> 27 | AJ6: =COUNTIF($C6:$AG6,"Ab") -> 2 | AK6: =COUNTIF($C6:$AG6,"L") -> 0 | AL6: =AH6/30*(AI6+AK6) -> 9000

Sheet Attendence (March)
C1: =TEXT(C2,"DDD") -> Fri | D1: =TEXT(D2,"DDD") -> Sat | E1: =TEXT(E2,"DDD") -> Sun | F1: =TEXT(F2,"DDD") -> Mon | G1: =TEXT(G2,"DDD") -> Tue | H1: =TEXT(H2,"DDD") -> Wed | I1: =TEXT(I2,"DDD") -> Thu | J1: =TEXT(J2,"DDD") -> Fri | ... AG1: =TEXT(AG2,"DDD") -> Sun | AH1: Monthly Salary(avg) | AI1: Present | AJ1: Absent | AK1: Leave | AL1: Net Salary | AM1: Month | AN1: March
B2: Employee Name | C2: =IF(COLUMNS($C$2:C2)>DAY($AN$4),"",$AN$3+COLUMNS($C$2:C2)-1) -> 45352 | D2: =IF(COLUMNS($C$2:D2)>DAY($AN$4),"",$AN$3+COLUMNS($C$2:D2)-1) -> 45353 | E2: =IF(COLUMNS($C$2:E2)>DAY($AN$4),"",$AN$3+COLUMNS($C$2:E2)-1) -> 45354 | F2: =IF(COLUMNS($C$2:F2)>DAY($AN$4),"",$AN$3+COLUMNS($C$2:F2)-1) -> 45355 | G2: =IF(COLUMNS($C$2:G2)>DAY($AN$4),"",$AN$3+COLUMNS($C$2:G2)-1) -> 45356 | H2: =IF(COLUMNS($C$2:H2)>DAY($AN$4),"",$AN$3+COLUMNS($C$2:H2)-1) -> 45357 | I2: =IF(COLUMNS($C$2:I2)>DAY($AN$4),"",$AN$3+COLUMNS($C$2:I2)-1) -> 45358 | J2: =IF(COLUMNS($C$2:J2)>DAY($AN$4),"",$AN$3+COLUMNS($C$2:J2)-1) -> 45359 | ... AG2: =IF(COLUMNS($C$2:AG2)>DAY($AN$4),"",$AN$3+COLUMNS($C$2:AG2)-1) -> 45382 | AM2: Year | AN2: 2024
B3: Kaishav(Owner) | C3: p | D3: p | E3: p | F3: p | G3: p | H3: p | I3: p | J3: p | K3: p | L3: p | M3: p | N3: p | O3: p | P3: p | Q3: p | R3: p | S3: p | T3: p | U3: ab | V3: p | W3: p | X3: p | Y3: p | Z3: p | AA3: p | AB3: p | AC3: p | AD3: p | AE3: ab | AF3: p | AG3: p | AH3: 50000 | AI3: =COUNTIF($C3:$AG3,"P") -> 29 | AJ3: =COUNTIF($C3:$AG3,"Ab") -> 2 | AK3: =COUNTIF($C3:$AG3,"L") -> 0 | AL3: =AH3/30*(AI3+AK3) -> 48333.333 | AM3: Starting Date | AN3: =DATE(AN2,MONTH(AN1&1),1) -> 45352
B4: Raman | C4: p | D4: p | E4: p | F4: ab | G4: p | H4: p | I4: p | J4: p | K4: p | L4: p | M4: p | N4: ab | O4: p | P4: p | Q4: p | R4: p | S4: p | T4: p | U4: p | V4: p | W4: p | X4: p | Y4: p | Z4: p | AA4: p | AB4: p | AC4: p | AD4: p | AE4: ab | AF4: p | AG4: p | AH4: 15000 | AI4: =COUNTIF($C4:$AG4,"P") -> 28 | AJ4: =COUNTIF($C4:$AG4,"Ab") -> 3 | AK4: =COUNTIF($C4:$AG4,"L") -> 0 | AL4: =AH4/30*(AI4+AK4) -> 14000 | AM4: Ending Date | AN4: =EOMONTH(AN3,0) -> 45382
B5: Sohan | C5: p | D5: p | E5: p | F5: p | G5: p | H5: p | I5: p | J5: p | K5: p | L5: p | M5: p | N5: ab | O5: p | P5: p | Q5: p | R5: p | S5: p | T5: p | U5: p | V5: p | W5: p | X5: p | Y5: p | Z5: p | AA5: p | AB5: p | AC5: p | AD5: p | AE5: p | AF5: p | AG5: p | AH5: 18000 | AI5: =COUNTIF($C5:$AG5,"P") -> 30 | AJ5: =COUNTIF($C5:$AG5,"Ab") -> 1 | AK5: =COUNTIF($C5:$AG5,"L") -> 0 | AL5: =AH5/30*(AI5+AK5) -> 18000
B6: Tilak | C6: p | D6: p | E6: p | F6: p | G6: p | H6: p | I6: p | J6: p | K6: p | L6: p | M6: p | N6: p | O6: p | P6: p | Q6: p | R6: p | S6: p | T6: p | U6: ab | V6: p | W6: p | X6: p | Y6: ab | Z6: p | AA6: p | AB6: p | AC6: p | AD6: p | AE6: p | AF6: p | AG6: p | AH6: 10000 | AI6: =COUNTIF($C6:$AG6,"P") -> 29 | AJ6: =COUNTIF($C6:$AG6,"Ab") -> 2 | AK6: =COUNTIF($C6:$AG6,"L") -> 0 | AL6: =AH6/30*(AI6+AK6) -> 9666.6667

Sheet Attendence (Aprail)
C1: =TEXT(C2,"DDD") -> #VALUE! | D1: =TEXT(D2,"DDD") -> #VALUE! | E1: =TEXT(E2,"DDD") -> #VALUE! | F1: =TEXT(F2,"DDD") -> #VALUE! | G1: =TEXT(G2,"DDD") -> #VALUE! | H1: =TEXT(H2,"DDD") -> #VALUE! | I1: =TEXT(I2,"DDD") -> #VALUE! | J1: =TEXT(J2,"DDD") -> #VALUE! | ... AF1: =TEXT(AF2,"DDD") -> #VALUE! | AH1: Monthly Salary(avg) | AI1: Present | AJ1: Absent | AK1: Leave | AL1: Net Salary | AM1: Month | AN1: Aprail
B2: Employee Name | C2: =IF(COLUMNS($C$2:C2)>DAY($AN$4),"",$AN$3+COLUMNS($C$2:C2)-1) -> #VALUE! | D2: =IF(COLUMNS($C$2:D2)>DAY($AN$4),"",$AN$3+COLUMNS($C$2:D2)-1) -> #VALUE! | E2: =IF(COLUMNS($C$2:E2)>DAY($AN$4),"",$AN$3+COLUMNS($C$2:E2)-1) -> #VALUE! | F2: =IF(COLUMNS($C$2:F2)>DAY($AN$4),"",$AN$3+COLUMNS($C$2:F2)-1) -> #VALUE! | G2: =IF(COLUMNS($C$2:G2)>DAY($AN$4),"",$AN$3+COLUMNS($C$2:G2)-1) -> #VALUE! | H2: =IF(COLUMNS($C$2:H2)>DAY($AN$4),"",$AN$3+COLUMNS($C$2:H2)-1) -> #VALUE! | I2: =IF(COLUMNS($C$2:I2)>DAY($AN$4),"",$AN$3+COLUMNS($C$2:I2)-1) -> #VALUE! | J2: =IF(COLUMNS($C$2:J2)>DAY($AN$4),"",$AN$3+COLUMNS($C$2:J2)-1) -> #VALUE! | ... AF2: =IF(COLUMNS($C$2:AF2)>DAY($AN$4),"",$AN$3+COLUMNS($C$2:AF2)-1) -> #VALUE! | AM2: Year | AN2: 2024
B3: Kaishav(Owner) | C3: p | D3: p | E3: p | F3: p | G3: p | H3: p | I3: p | J3: p | K3: p | L3: p | M3: p | N3: p | O3: p | P3: p | Q3: p | R3: p | S3: p | T3: p | U3: ab | V3: p | W3: p | X3: p | Y3: p | Z3: p | AA3: p | AB3: p | AC3: p | AD3: p | AE3: p | AF3: p | AH3: 50000 | AI3: =COUNTIF($C3:$AG3,"P") -> 29 | AJ3: =COUNTIF($C3:$AG3,"Ab") -> 1 | AK3: =COUNTIF($C3:$AG3,"L") -> 0 | AL3: =AH3/30*(AI3+AK3) -> 48333.333 | AM3: Starting Date | AN3: =DATE(AN2,MONTH(AN1&1),1) -> #VALUE!
B4: Raman | C4: p | D4: p | E4: p | F4: p | G4: p | H4: p | I4: p | J4: p | K4: ab | L4: p | M4: p | N4: p | O4: p | P4: p | Q4: ab | R4: p | S4: p | T4: p | U4: p | V4: p | W4: p | X4: p | Y4: p | Z4: p | AA4: p | AB4: p | AC4: p | AD4: p | AE4: p | AF4: p | AH4: 15000 | AI4: =COUNTIF($C4:$AG4,"P") -> 28 | AJ4: =COUNTIF($C4:$AG4,"Ab") -> 2 | AK4: =COUNTIF($C4:$AG4,"L") -> 0 | AL4: =AH4/30*(AI4+AK4) -> 14000 | AM4: Ending Date | AN4: =EOMONTH(AN3,0) -> #VALUE!
B5: Sohan | C5: p | D5: p | E5: p | F5: p | G5: p | H5: p | I5: p | J5: p | K5: p | L5: p | M5: p | N5: p | O5: p | P5: p | Q5: p | R5: p | S5: p | T5: p | U5: ab | V5: p | W5: p | X5: p | Y5: p | Z5: p | AA5: l | AB5: p | AC5: p | AD5: p | AE5: p | AF5: p | AH5: 18000 | AI5: =COUNTIF($C5:$AG5,"P") -> 28 | AJ5: =COUNTIF($C5:$AG5,"Ab") -> 1 | AK5: =COUNTIF($C5:$AG5,"L") -> 1 | AL5: =AH5/30*(AI5+AK5) -> 17400
B6: Tilak | C6: p | D6: p | E6: p | F6: p | G6: p | H6: p | I6: p | J6: p | K6: p | L6: p | M6: p | N6: p | O6: p | P6: p | Q6: ab | R6: p | S6: p | T6: p | U6: p | V6: p | W6: p | X6: p | Y6: p | Z6: p | AA6: p | AB6: p | AC6: p | AD6: p | AE6: p | AF6: p | AH6: 10000 | AI6: =COUNTIF($C6:$AG6,"P") -> 29 | AJ6: =COUNTIF($C6:$AG6,"Ab") -> 1 | AK6: =COUNTIF($C6:$AG6,"L") -> 0 | AL6: =AH6/30*(AI6+AK6) -> 9666.6667

Sheet Attendence (May)
C1: =TEXT(C2,"DDD") -> Wed | D1: =TEXT(D2,"DDD") -> Thu | E1: =TEXT(E2,"DDD") -> Fri | F1: =TEXT(F2,"DDD") -> Sat | G1: =TEXT(G2,"DDD") -> Sun | H1: =TEXT(H2,"DDD") -> Mon | I1: =TEXT(I2,"DDD") -> Tue | J1: =TEXT(J2,"DDD") -> Wed | ... AG1: =TEXT(AG2,"DDD") -> Fri | AH1: Monthly Salary(avg) | AI1: Present | AJ1: Absent | AK1: Leave | AL1: Net Salary | AM1: Month | AN1: May
B2: Employee Name | C2: =IF(COLUMNS($C$2:C2)>DAY($AN$4),"",$AN$3+COLUMNS($C$2:C2)-1) -> 45413 | D2: =IF(COLUMNS($C$2:D2)>DAY($AN$4),"",$AN$3+COLUMNS($C$2:D2)-1) -> 45414 | E2: =IF(COLUMNS($C$2:E2)>DAY($AN$4),"",$AN$3+COLUMNS($C$2:E2)-1) -> 45415 | F2: =IF(COLUMNS($C$2:F2)>DAY($AN$4),"",$AN$3+COLUMNS($C$2:F2)-1) -> 45416 | G2: =IF(COLUMNS($C$2:G2)>DAY($AN$4),"",$AN$3+COLUMNS($C$2:G2)-1) -> 45417 | H2: =IF(COLUMNS($C$2:H2)>DAY($AN$4),"",$AN$3+COLUMNS($C$2:H2)-1) -> 45418 | I2: =IF(COLUMNS($C$2:I2)>DAY($AN$4),"",$AN$3+COLUMNS($C$2:I2)-1) -> 45419 | J2: =IF(COLUMNS($C$2:J2)>DAY($AN$4),"",$AN$3+COLUMNS($C$2:J2)-1) -> 45420 | ... AG2: =IF(COLUMNS($C$2:AG2)>DAY($AN$4),"",$AN$3+COLUMNS($C$2:AG2)-1) -> 45443 | AM2: Year | AN2: 2024
B3: Kaishav(Owner) | C3: p | D3: p | E3: p | F3: p | G3: p | H3: p | I3: p | J3: p | K3: p | L3: p | M3: p | N3: p | O3: p | P3: p | Q3: p | R3: p | S3: p | T3: p | U3: p | V3: p | W3: p | X3: p | Y3: p | Z3: p | AA3: ab | AB3: p | AC3: p | AD3: p | AE3: p | AF3: p | AG3: p | AH3: 50000 | AI3: =COUNTIF($C3:$AG3,"P") -> 30 | AJ3: =COUNTIF($C3:$AG3,"Ab") -> 1 | AK3: =COUNTIF($C3:$AG3,"L") -> 0 | AL3: =AH3/30*(AI3+AK3) -> 50000 | AM3: Starting Date | AN3: =DATE(AN2,MONTH(AN1&1),1) -> 45413
B4: Raman | C4: p | D4: p | E4: p | F4: p | G4: p | H4: p | I4: p | J4: p | K4: ab | L4: p | M4: p | N4: p | O4: p | P4: p | Q4: p | R4: p | S4: p | T4: ab | U4: p | V4: p | W4: p | X4: p | Y4: p | Z4: p | AA4: ab | AB4: p | AC4: p | AD4: p | AE4: p | AF4: p | AG4: p | AH4: 15000 | AI4: =COUNTIF($C4:$AG4,"P") -> 28 | AJ4: =COUNTIF($C4:$AG4,"Ab") -> 3 | AK4: =COUNTIF($C4:$AG4,"L") -> 0 | AL4: =AH4/30*(AI4+AK4) -> 14000 | AM4: Ending Date | AN4: =EOMONTH(AN3,0) -> 45443
B5: Sohan | C5: p | D5: p | E5: p | F5: p | G5: p | H5: p | I5: p | J5: p | K5: p | L5: p | M5: p | N5: p | O5: p | P5: p | Q5: p | R5: p | S5: p | T5: p | U5: p | V5: p | W5: p | X5: p | Y5: p | Z5: p | AA5: p | AB5: p | AC5: p | AD5: p | AE5: p | AF5: p | AG5: p | AH5: 18000 | AI5: =COUNTIF($C5:$AG5,"P") -> 31 | AJ5: =COUNTIF($C5:$AG5,"Ab") -> 0 | AK5: =COUNTIF($C5:$AG5,"L") -> 0 | AL5: =AH5/30*(AI5+AK5) -> 18600
B6: Tilak | C6: p | D6: p | E6: p | F6: p | G6: p | H6: p | I6: p | J6: p | K6: p | L6: p | M6: p | N6: p | O6: p | P6: p | Q6: p | R6: p | S6: p | T6: ab | U6: p | V6: p | W6: p | X6: p | Y6: p | Z6: p | AA6: p | AB6: p | AC6: p | AD6: p | AE6: p | AF6: p | AG6: p | AH6: 10000 | AI6: =COUNTIF($C6:$AG6,"P") -> 30 | AJ6: =COUNTIF($C6:$AG6,"Ab") -> 1 | AK6: =COUNTIF($C6:$AG6,"L") -> 0 | AL6: =AH6/30*(AI6+AK6) -> 10000

Sheet Attendence (June)
C1: =TEXT(C2,"DDD") -> Sat | D1: =TEXT(D2,"DDD") -> Sun | E1: =TEXT(E2,"DDD") -> Mon | F1: =TEXT(F2,"DDD") -> Tue | G1: =TEXT(G2,"DDD") -> Wed | H1: =TEXT(H2,"DDD") -> Thu | I1: =TEXT(I2,"DDD") -> Fri | J1: =TEXT(J2,"DDD") -> Sat | ... AG1: =TEXT(AG2,"DDD") | AH1: Monthly Salary(avg) | AI1: Present | AJ1: Absent | AK1: Leave | AL1: Net Salary | AM1: Month | AN1: June
B2: Employee Name | C2: =IF(COLUMNS($C$2:C2)>DAY($AN$4),"",$AN$3+COLUMNS($C$2:C2)-1) -> 45444 | D2: =IF(COLUMNS($C$2:D2)>DAY($AN$4),"",$AN$3+COLUMNS($C$2:D2)-1) -> 45445 | E2: =IF(COLUMNS($C$2:E2)>DAY($AN$4),"",$AN$3+COLUMNS($C$2:E2)-1) -> 45446 | F2: =IF(COLUMNS($C$2:F2)>DAY($AN$4),"",$AN$3+COLUMNS($C$2:F2)-1) -> 45447 | G2: =IF(COLUMNS($C$2:G2)>DAY($AN$4),"",$AN$3+COLUMNS($C$2:G2)-1) -> 45448 | H2: =IF(COLUMNS($C$2:H2)>DAY($AN$4),"",$AN$3+COLUMNS($C$2:H2)-1) -> 45449 | I2: =IF(COLUMNS($C$2:I2)>DAY($AN$4),"",$AN$3+COLUMNS($C$2:I2)-1) -> 45450 | J2: =IF(COLUMNS($C$2:J2)>DAY($AN$4),"",$AN$3+COLUMNS($C$2:J2)-1) -> 45451 | ... AG2: =IF(COLUMNS($C$2:AG2)>DAY($AN$4),"",$AN$3+COLUMNS($C$2:AG2)-1) | AM2: Year | AN2: 2024
B3: Kaishav(Owner) | C3: p | D3: p | E3: p | F3: p | G3: p | H3: p | I3: p | J3: p | K3: p | L3: p | M3: p | N3: p | O3: p | P3: p | Q3: p | R3: p | S3: p | T3: p | U3: p | V3: p | W3: p | X3: ab | Y3: p | Z3: p | AA3: p | AB3: p | AC3: p | AD3: p | AE3: p | AF3: p | AH3: 50000 | AI3: =COUNTIF($C3:$AG3,"P") -> 29 | AJ3: =COUNTIF($C3:$AG3,"Ab") -> 1 | AK3: =COUNTIF($C3:$AG3,"L") -> 0 | AL3: =AH3/30*(AI3+AK3) -> 48333.333 | AM3: Starting Date | AN3: =DATE(AN2,MONTH(AN1&1),1) -> 45444
B4: Raman | C4: p | D4: ab | E4: p | F4: p | G4: p | H4: p | I4: p | J4: p | K4: p | L4: p | M4: p | N4: p | O4: p | P4: ab | Q4: p | R4: p | S4: p | T4: p | U4: p | V4: p | W4: p | X4: p | Y4: p | Z4: p | AA4: p | AB4: p | AC4: p | AD4: p | AE4: p | AF4: p | AH4: 15000 | AI4: =COUNTIF($C4:$AG4,"P") -> 28 | AJ4: =COUNTIF($C4:$AG4,"Ab") -> 2 | AK4: =COUNTIF($C4:$AG4,"L") -> 0 | AL4: =AH4/30*(AI4+AK4) -> 14000 | AM4: Ending Date | AN4: =EOMONTH(AN3,0) -> 45473
B5: Sohan | C5: p | D5: p | E5: p | F5: p | G5: p | H5: p | I5: p | J5: ab | K5: p | L5: p | M5: p | N5: p | O5: p | P5: p | Q5: p | R5: p | S5: p | T5: p | U5: p | V5: p | W5: p | X5: p | Y5: p | Z5: p | AA5: p | AB5: p | AC5: p | AD5: p | AE5: p | AF5: p | AH5: 18000 | AI5: =COUNTIF($C5:$AG5,"P") -> 29 | AJ5: =COUNTIF($C5:$AG5,"Ab") -> 1 | AK5: =COUNTIF($C5:$AG5,"L") -> 0 | AL5: =AH5/30*(AI5+AK5) -> 17400
B6: Tilak | C6: p | D6: p | E6: p | F6: p | G6: p | H6: p | I6: p | J6: ab | K6: p | L6: p | M6: p | N6: p | O6: p | P6: p | Q6: p | R6: p | S6: p | T6: p | U6: p | V6: p | W6: p | X6: ab | Y6: p | Z6: p | AA6: p | AB6: p | AC6: p | AD6: p | AE6: p | AF6: p | AH6: 10000 | AI6: =COUNTIF($C6:$AG6,"P") -> 28 | AJ6: =COUNTIF($C6:$AG6,"Ab") -> 2 | AK6: =COUNTIF($C6:$AG6,"L") -> 0 | AL6: =AH6/30*(AI6+AK6) -> 9333.3333

Sheet Attendence (July)
C1: =TEXT(C2,"DDD") -> Mon | D1: =TEXT(D2,"DDD") -> Tue | E1: =TEXT(E2,"DDD") -> Wed | F1: =TEXT(F2,"DDD") -> Thu | G1: =TEXT(G2,"DDD") -> Fri | H1: =TEXT(H2,"DDD") -> Sat | I1: =TEXT(I2,"DDD") -> Sun | J1: =TEXT(J2,"DDD") -> Mon | ... AG1: =TEXT(AG2,"DDD") -> Wed | AH1: Monthly Salary(avg) | AI1: Present | AJ1: Absent | AK1: Leave | AL1: Net Salary | AM1: Month | AN1: July
B2: Employee Name | C2: =IF(COLUMNS($C$2:C2)>DAY($AN$4),"",$AN$3+COLUMNS($C$2:C2)-1) -> 45474 | D2: =IF(COLUMNS($C$2:D2)>DAY($AN$4),"",$AN$3+COLUMNS($C$2:D2)-1) -> 45475 | E2: =IF(COLUMNS($C$2:E2)>DAY($AN$4),"",$AN$3+COLUMNS($C$2:E2)-1) -> 45476 | F2: =IF(COLUMNS($C$2:F2)>DAY($AN$4),"",$AN$3+COLUMNS($C$2:F2)-1) -> 45477 | G2: =IF(COLUMNS($C$2:G2)>DAY($AN$4),"",$AN$3+COLUMNS($C$2:G2)-1) -> 45478 | H2: =IF(COLUMNS($C$2:H2)>DAY($AN$4),"",$AN$3+COLUMNS($C$2:H2)-1) -> 45479 | I2: =IF(COLUMNS($C$2:I2)>DAY($AN$4),"",$AN$3+COLUMNS($C$2:I2)-1) -> 45480 | J2: =IF(COLUMNS($C$2:J2)>DAY($AN$4),"",$AN$3+COLUMNS($C$2:J2)-1) -> 45481 | ... AG2: =IF(COLUMNS($C$2:AG2)>DAY($AN$4),"",$AN$3+COLUMNS($C$2:AG2)-1) -> 45504 | AM2: Year | AN2: 2024
B3: Kaishav(Owner) | C3: p | D3: p | E3: p | F3: p | G3: p | H3: p | I3: ab | J3: p | K3: p | L3: p | M3: p | N3: p | O3: p | P3: p | Q3: p | R3: p | S3: p | T3: p | U3: p | V3: p | W3: p | X3: p | Y3: p | Z3: p | AA3: p | AB3: p | AC3: p | AD3: p | AE3: p | AF3: p | AG3: ab | AH3: 50000 | AI3: =COUNTIF($C3:$AG3,"P") -> 29 | AJ3: =COUNTIF($C3:$AG3,"Ab") -> 2 | AK3: =COUNTIF($C3:$AG3,"L") -> 0 | AL3: =AH3/30*(AI3+AK3) -> 48333.333 | AM3: Starting Date | AN3: =DATE(AN2,MONTH(AN1&1),1) -> 45474
B4: Raman | C4: p | D4: p | E4: p | F4: p | G4: p | H4: p | I4: p | J4: p | K4: p | L4: p | M4: p | N4: ab | O4: p | P4: p | Q4: p | R4: p | S4: p | T4: p | U4: p | V4: p | W4: p | X4: p | Y4: p | Z4: p | AA4: p | AB4: p | AC4: p | AD4: p | AE4: p | AF4: p | AG4: p | AH4: 15000 | AI4: =COUNTIF($C4:$AG4,"P") -> 30 | AJ4: =COUNTIF($C4:$AG4,"Ab") -> 1 | AK4: =COUNTIF($C4:$AG4,"L") -> 0 | AL4: =AH4/30*(AI4+AK4) -> 15000 | AM4: Ending Date | AN4: =EOMONTH(AN3,0) -> 45504
B5: Sohan | C5: p | D5: p | E5: p | F5: p | G5: p | H5: p | I5: p | J5: p | K5: p | L5: p | M5: p | N5: p | O5: p | P5: p | Q5: p | R5: p | S5: p | T5: p | U5: p | V5: p | W5: p | X5: p | Y5: ab | Z5: p | AA5: p | AB5: p | AC5: p | AD5: p | AE5: p | AF5: p | AG5: p | AH5: 18000 | AI5: =COUNTIF($C5:$AG5,"P") -> 30 | AJ5: =COUNTIF($C5:$AG5,"Ab") -> 1 | AK5: =COUNTIF($C5:$AG5,"L") -> 0 | AL5: =AH5/30*(AI5+AK5) -> 18000
B6: Tilak | C6: p | D6: p | E6: p | F6: p | G6: p | H6: p | I6: ab | J6: p | K6: p | L6: p | M6: p | N6: p | O6: p | P6: p | Q6: ab | R6: p | S6: p | T6: p | U6: p | V6: p | W6: p | X6: p | Y6: p | Z6: p | AA6: p | AB6: p | AC6: ab | AD6: p | AE6: p | AF6: p | AG6: p | AH6: 10000 | AI6: =COUNTIF($C6:$AG6,"P") -> 28 | AJ6: =COUNTIF($C6:$AG6,"Ab") -> 3 | AK6: =COUNTIF($C6:$AG6,"L") -> 0 | AL6: =AH6/30*(AI6+AK6) -> 9333.3333

Sheet Attendence (Aug)
C1: =TEXT(C2,"DDD") -> Thu | D1: =TEXT(D2,"DDD") -> Fri | E1: =TEXT(E2,"DDD") -> Sat | F1: =TEXT(F2,"DDD") -> Sun | G1: =TEXT(G2,"DDD") -> Mon | H1: =TEXT(H2,"DDD") -> Tue | I1: =TEXT(I2,"DDD") -> Wed | J1: =TEXT(J2,"DDD") -> Thu | ... AG1: =TEXT(AG2,"DDD") -> Sat | AH1: Monthly Salary(avg) | AI1: Present | AJ1: Absent | AK1: Leave | AL1: Net Salary | AM1: Month | AN1: August
B2: Employee Name | C2: =IF(COLUMNS($C$2:C2)>DAY($AN$4),"",$AN$3+COLUMNS($C$2:C2)-1) -> 45505 | D2: =IF(COLUMNS($C$2:D2)>DAY($AN$4),"",$AN$3+COLUMNS($C$2:D2)-1) -> 45506 | E2: =IF(COLUMNS($C$2:E2)>DAY($AN$4),"",$AN$3+COLUMNS($C$2:E2)-1) -> 45507 | F2: =IF(COLUMNS($C$2:F2)>DAY($AN$4),"",$AN$3+COLUMNS($C$2:F2)-1) -> 45508 | G2: =IF(COLUMNS($C$2:G2)>DAY($AN$4),"",$AN$3+COLUMNS($C$2:G2)-1) -> 45509 | H2: =IF(COLUMNS($C$2:H2)>DAY($AN$4),"",$AN$3+COLUMNS($C$2:H2)-1) -> 45510 | I2: =IF(COLUMNS($C$2:I2)>DAY($AN$4),"",$AN$3+COLUMNS($C$2:I2)-1) -> 45511 | J2: =IF(COLUMNS($C$2:J2)>DAY($AN$4),"",$AN$3+COLUMNS($C$2:J2)-1) -> 45512 | ... AG2: =IF(COLUMNS($C$2:AG2)>DAY($AN$4),"",$AN$3+COLUMNS($C$2:AG2)-1) -> 45535 | AM2: Year | AN2: 2024
B3: Kaishav(Owner) | C3: p | D3: p | E3: p | F3: ab | G3: p | H3: p | I3: p | J3: p | K3: p | L3: p | M3: p | N3: p | O3: p | P3: p | Q3: p | R3: p | S3: p | T3: p | U3: p | V3: p | W3: p | X3: p | Y3: p | Z3: p | AA3: p | AB3: p | AC3: p | AD3: p | AE3: p | AF3: p | AG3: p | AH3: 50000 | AI3: =COUNTIF($C3:$AG3,"P") -> 30 | AJ3: =COUNTIF($C3:$AG3,"Ab") -> 1 | AK3: =COUNTIF($C3:$AG3,"L") -> 0 | AL3: =AH3/30*(AI3+AK3) -> 50000 | AM3: Starting Date | AN3: =DATE(AN2,MONTH(AN1&1),1) -> 45505
B4: Raman | C4: p | D4: p | E4: p | F4: p | G4: p | H4: p | I4: p | J4: p | K4: p | L4: p | M4: ab | N4: p | O4: p | P4: p | Q4: p | R4: p | S4: p | T4: p | U4: p | V4: p | W4: p | X4: p | Y4: p | Z4: p | AA4: p | AB4: p | AC4: p | AD4: p | AE4: p | AF4: p | AG4: p | AH4: 15000 | AI4: =COUNTIF($C4:$AG4,"P") -> 30 | AJ4: =COUNTIF($C4:$AG4,"Ab") -> 1 | AK4: =COUNTIF($C4:$AG4,"L") -> 0 | AL4: =AH4/30*(AI4+AK4) -> 15000 | AM4: Ending Date | AN4: =EOMONTH(AN3,0) -> 45535
B5: Sohan | C5: p | D5: p | E5: p | F5: p | G5: p | H5: p | I5: p | J5: p | K5: p | L5: p | M5: p | N5: p | O5: p | P5: p | Q5: p | R5: p | S5: p | T5: p | U5: p | V5: p | W5: ab | X5: p | Y5: p | Z5: p | AA5: p | AB5: p | AC5: p | AD5: p | AE5: p | AF5: p | AG5: p | AH5: 18000 | AI5: =COUNTIF($C5:$AG5,"P") -> 30 | AJ5: =COUNTIF($C5:$AG5,"Ab") -> 1 | AK5: =COUNTIF($C5:$AG5,"L") -> 0 | AL5: =AH5/30*(AI5+AK5) -> 18000
B6: Tilak | C6: p | D6: p | E6: ab | F6: p | G6: p | H6: p | I6: p | J6: p | K6: l | L6: p | M6: p | N6: p | O6: p | P6: p | Q6: p | R6: p | S6: p | T6: p | U6: p | V6: p | W6: p | X6: p | Y6: p | Z6: p | AA6: p | AB6: p | AC6: p | AD6: p | AE6: p | AF6: p | AG6: ab | AH6: 10000 | AI6: =COUNTIF($C6:$AG6,"P") -> 28 | AJ6: =COUNTIF($C6:$AG6,"Ab") -> 2 | AK6: =COUNTIF($C6:$AG6,"L") -> 1 | AL6: =AH6/30*(AI6+AK6) -> 9666.6667

Sheet Attendence (Sep)
C1: =TEXT(C2,"DDD") -> Sun | D1: =TEXT(D2,"DDD") -> Mon | E1: =TEXT(E2,"DDD") -> Tue | F1: =TEXT(F2,"DDD") -> Wed | G1: =TEXT(G2,"DDD") -> Thu | H1: =TEXT(H2,"DDD") -> Fri | I1: =TEXT(I2,"DDD") -> Sat | J1: =TEXT(J2,"DDD") -> Sun | ... AG1: =TEXT(AG2,"DDD") | AH1: Monthly Salary(avg) | AI1: Present | AJ1: Absent | AK1: Leave | AL1: Net Salary | AM1: Month | AN1: September
B2: Employee Name | C2: =IF(COLUMNS($C$2:C2)>DAY($AN$4),"",$AN$3+COLUMNS($C$2:C2)-1) -> 45536 | D2: =IF(COLUMNS($C$2:D2)>DAY($AN$4),"",$AN$3+COLUMNS($C$2:D2)-1) -> 45537 | E2: =IF(COLUMNS($C$2:E2)>DAY($AN$4),"",$AN$3+COLUMNS($C$2:E2)-1) -> 45538 | F2: =IF(COLUMNS($C$2:F2)>DAY($AN$4),"",$AN$3+COLUMNS($C$2:F2)-1) -> 45539 | G2: =IF(COLUMNS($C$2:G2)>DAY($AN$4),"",$AN$3+COLUMNS($C$2:G2)-1) -> 45540 | H2: =IF(COLUMNS($C$2:H2)>DAY($AN$4),"",$AN$3+COLUMNS($C$2:H2)-1) -> 45541 | I2: =IF(COLUMNS($C$2:I2)>DAY($AN$4),"",$AN$3+COLUMNS($C$2:I2)-1) -> 45542 | J2: =IF(COLUMNS($C$2:J2)>DAY($AN$4),"",$AN$3+COLUMNS($C$2:J2)-1) -> 45543 | ... AG2: =IF(COLUMNS($C$2:AG2)>DAY($AN$4),"",$AN$3+COLUMNS($C$2:AG2)-1) | AM2: Year | AN2: 2024
B3: Kaishav(Owner) | C3: p | D3: p | E3: p | F3: p | G3: p | H3: p | I3: p | J3: p | K3: p | L3: p | M3: p | N3: p | O3: p | P3: p | Q3: p | R3: p | S3: p | T3: p | U3: p | V3: p | W3: p | X3: p | Y3: p | Z3: p | AA3: p | AB3: p | AC3: p | AD3: p | AE3: p | AF3: p | AH3: 50000 | AI3: =COUNTIF($C3:$AG3,"P") -> 30 | AJ3: =COUNTIF($C3:$AG3,"Ab") -> 0 | AK3: =COUNTIF($C3:$AG3,"L") -> 0 | AL3: =AH3/30*(AI3+AK3) -> 50000 | AM3: Starting Date | AN3: =DATE(AN2,MONTH(AN1&1),1) -> 45536
B4: Raman | C4: p | D4: p | E4: p | F4: p | G4: p | H4: p | I4: p | J4: p | K4: p | L4: p | M4: p | N4: p | O4: p | P4: p | Q4: p | R4: p | S4: p | T4: p | U4: p | V4: p | W4: p | X4: p | Y4: p | Z4: p | AA4: p | AB4: p | AC4: p | AD4: p | AE4: p | AF4: p | AH4: 15000 | AI4: =COUNTIF($C4:$AG4,"P") -> 30 | AJ4: =COUNTIF($C4:$AG4,"Ab") -> 0 | AK4: =COUNTIF($C4:$AG4,"L") -> 0 | AL4: =AH4/30*(AI4+AK4) -> 15000 | AM4: Ending Date | AN4: =EOMONTH(AN3,0) -> 45565
B5: Sohan | C5: p | D5: p | E5: p | F5: p | G5: p | H5: p | I5: p | J5: p | K5: p | L5: p | M5: p | N5: p | O5: p | P5: p | Q5: p | R5: p | S5: p | T5: p | U5: p | V5: p | W5: p | X5: p | Y5: p | Z5: p | AA5: p | AB5: p | AC5: p | AD5: p | AE5: p | AF5: p | AH5: 18000 | AI5: =COUNTIF($C5:$AG5,"P") -> 30 | AJ5: =COUNTIF($C5:$AG5,"Ab") -> 0 | AK5: =COUNTIF($C5:$AG5,"L") -> 0 | AL5: =AH5/30*(AI5+AK5) -> 18000
B6: Tilak | C6: p | D6: p | E6: p | F6: p | G6: p | H6: p | I6: p | J6: p | K6: p | L6: p | M6: p | N6: p | O6: p | P6: p | Q6: p | R6: p | S6: p | T6: p | U6: p | V6: p | W6: p | X6: p | Y6: p | Z6: p | AA6: p | AB6: p | AC6: p | AD6: p | AE6: p | AF6: p | AH6: 10000 | AI6: =COUNTIF($C6:$AG6,"P") -> 30 | AJ6: =COUNTIF($C6:$AG6,"Ab") -> 0 | AK6: =COUNTIF($C6:$AG6,"L") -> 0 | AL6: =AH6/30*(AI6+AK6) -> 10000

Sheet Attendence (Oct)
C1: =TEXT(C2,"DDD") -> Tue | D1: =TEXT(D2,"DDD") -> Wed | E1: =TEXT(E2,"DDD") -> Thu | F1: =TEXT(F2,"DDD") -> Fri | G1: =TEXT(G2,"DDD") -> Sat | H1: =TEXT(H2,"DDD") -> Sun | I1: =TEXT(I2,"DDD") -> Mon | J1: =TEXT(J2,"DDD") -> Tue | ... AG1: =TEXT(AG2,"DDD") -> Thu | AH1: Monthly Salary(avg) | AI1: Present | AJ1: Absent | AK1: Leave | AL1: Net Salary | AM1: Month | AN1: October
B2: Employee Name | C2: =IF(COLUMNS($C$2:C2)>DAY($AN$4),"",$AN$3+COLUMNS($C$2:C2)-1) -> 45566 | D2: =IF(COLUMNS($C$2:D2)>DAY($AN$4),"",$AN$3+COLUMNS($C$2:D2)-1) -> 45567 | E2: =IF(COLUMNS($C$2:E2)>DAY($AN$4),"",$AN$3+COLUMNS($C$2:E2)-1) -> 45568 | F2: =IF(COLUMNS($C$2:F2)>DAY($AN$4),"",$AN$3+COLUMNS($C$2:F2)-1) -> 45569 | G2: =IF(COLUMNS($C$2:G2)>DAY($AN$4),"",$AN$3+COLUMNS($C$2:G2)-1) -> 45570 | H2: =IF(COLUMNS($C$2:H2)>DAY($AN$4),"",$AN$3+COLUMNS($C$2:H2)-1) -> 45571 | I2: =IF(COLUMNS($C$2:I2)>DAY($AN$4),"",$AN$3+COLUMNS($C$2:I2)-1) -> 45572 | J2: =IF(COLUMNS($C$2:J2)>DAY($AN$4),"",$AN$3+COLUMNS($C$2:J2)-1) -> 45573 | ... AG2: =IF(COLUMNS($C$2:AG2)>DAY($AN$4),"",$AN$3+COLUMNS($C$2:AG2)-1) -> 45596 | AM2: Year | AN2: 2024
B3: Kaishav(Owner) | C3: p | D3: p | E3: p | F3: p | G3: p | H3: p | I3: p | J3: p | K3: p | L3: p | M3: p | N3: p | O3: p | P3: p | Q3: p | R3: p | S3: p | T3: p | U3: p | V3: p | W3: p | AH3: 50000 | AI3: =COUNTIF($C3:$AG3,"P") -> 21 | AJ3: =COUNTIF($C3:$AG3,"Ab") -> 0 | AK3: =COUNTIF($C3:$AG3,"L") -> 0 | AL3: =AH3/30*(AI3+AK3) -> 35000 | AM3: Starting Date | AN3: =DATE(AN2,MONTH(AN1&1),1) -> 45566
B4: Raman | C4: p | D4: p | E4: p | F4: p | G4: p | H4: p | I4: p | J4: p | K4: p | L4: p | M4: p | N4: p | O4: p | P4: p | Q4: p | R4: p | S4: p | T4: p | U4: p | V4: p | W4: p | AH4: 15000 | AI4: =COUNTIF($C4:$AG4,"P") -> 21 | AJ4: =COUNTIF($C4:$AG4,"Ab") -> 0 | AK4: =COUNTIF($C4:$AG4,"L") -> 0 | AL4: =AH4/30*(AI4+AK4) -> 10500 | AM4: Ending Date | AN4: =EOMONTH(AN3,0) -> 45596
B5: Sohan | C5: p | D5: p | E5: p | F5: p | G5: p | H5: p | I5: p | J5: p | K5: p | L5: p | M5: p | N5: p | O5: p | P5: p | Q5: p | R5: p | S5: p | T5: p | U5: p | V5: p | W5: p | AH5: 18000 | AI5: =COUNTIF($C5:$AG5,"P") -> 21 | AJ5: =COUNTIF($C5:$AG5,"Ab") -> 0 | AK5: =COUNTIF($C5:$AG5,"L") -> 0 | AL5: =AH5/30*(AI5+AK5) -> 12600
B6: Tilak | C6: p | D6: p | E6: p | F6: p | G6: p | H6: p | I6: p | J6: p | K6: p | L6: p | M6: p | N6: p | O6: p | P6: p | Q6: p | R6: p | S6: p | T6: p | U6: p | V6: p | W6: p | AH6: 10000 | AI6: =COUNTIF($C6:$AG6,"P") -> 21 | AJ6: =COUNTIF($C6:$AG6,"Ab") -> 0 | AK6: =COUNTIF($C6:$AG6,"L") -> 0 | AL6: =AH6/30*(AI6+AK6) -> 7000

Sheet Attendence (Nov)
C1: =TEXT(C2,"DDD") -> Fri | D1: =TEXT(D2,"DDD") -> Sat | E1: =TEXT(E2,"DDD") -> Sun | F1: =TEXT(F2,"DDD") -> Mon | G1: =TEXT(G2,"DDD") -> Tue | H1: =TEXT(H2,"DDD") -> Wed | I1: =TEXT(I2,"DDD") -> Thu | J1: =TEXT(J2,"DDD") -> Fri | ... AG1: =TEXT(AG2,"DDD") | AH1: Monthly Salary(avg) | AI1: Present | AJ1: Absent | AK1: Leave | AL1: Net Salary | AM1: Month | AN1: November
B2: Employee Name | C2: =IF(COLUMNS($C$2:C2)>DAY($AN$4),"",$AN$3+COLUMNS($C$2:C2)-1) -> 45597 | D2: =IF(COLUMNS($C$2:D2)>DAY($AN$4),"",$AN$3+COLUMNS($C$2:D2)-1) -> 45598 | E2: =IF(COLUMNS($C$2:E2)>DAY($AN$4),"",$AN$3+COLUMNS($C$2:E2)-1) -> 45599 | F2: =IF(COLUMNS($C$2:F2)>DAY($AN$4),"",$AN$3+COLUMNS($C$2:F2)-1) -> 45600 | G2: =IF(COLUMNS($C$2:G2)>DAY($AN$4),"",$AN$3+COLUMNS($C$2:G2)-1) -> 45601 | H2: =IF(COLUMNS($C$2:H2)>DAY($AN$4),"",$AN$3+COLUMNS($C$2:H2)-1) -> 45602 | I2: =IF(COLUMNS($C$2:I2)>DAY($AN$4),"",$AN$3+COLUMNS($C$2:I2)-1) -> 45603 | J2: =IF(COLUMNS($C$2:J2)>DAY($AN$4),"",$AN$3+COLUMNS($C$2:J2)-1) -> 45604 | ... AG2: =IF(COLUMNS($C$2:AG2)>DAY($AN$4),"",$AN$3+COLUMNS($C$2:AG2)-1) | AM2: Year | AN2: 2024
B3: Kaishav(Owner) | AH3: 50000 | AI3: =COUNTIF($C3:$AG3,"P") -> 0 | AJ3: =COUNTIF($C3:$AG3,"Ab") -> 0 | AK3: =COUNTIF($C3:$AG3,"L") -> 0 | AL3: =AH3/30*(AI3+AK3) -> 0 | AM3: Starting Date | AN3: =DATE(AN2,MONTH(AN1&1),1) -> 45597
B4: Raman | AH4: 15000 | AI4: =COUNTIF($C4:$AG4,"P") -> 0 | AJ4: =COUNTIF($C4:$AG4,"Ab") -> 0 | AK4: =COUNTIF($C4:$AG4,"L") -> 0 | AL4: =AH4/30*(AI4+AK4) -> 0 | AM4: Ending Date | AN4: =EOMONTH(AN3,0) -> 45626
B5: Sohan | AH5: 18000 | AI5: =COUNTIF($C5:$AG5,"P") -> 0 | AJ5: =COUNTIF($C5:$AG5,"Ab") -> 0 | AK5: =COUNTIF($C5:$AG5,"L") -> 0 | AL5: =AH5/30*(AI5+AK5) -> 0
B6: Tilak | AH6: 10000 | AI6: =COUNTIF($C6:$AG6,"P") -> 0 | AJ6: =COUNTIF($C6:$AG6,"Ab") -> 0 | AK6: =COUNTIF($C6:$AG6,"L") -> 0 | AL6: =AH6/30*(AI6+AK6) -> 0

Sheet Attendence (Dec)
C1: =TEXT(C2,"DDD") -> Sun | D1: =TEXT(D2,"DDD") -> Mon | E1: =TEXT(E2,"DDD") -> Tue | F1: =TEXT(F2,"DDD") -> Wed | G1: =TEXT(G2,"DDD") -> Thu | H1: =TEXT(H2,"DDD") -> Fri | I1: =TEXT(I2,"DDD") -> Sat | J1: =TEXT(J2,"DDD") -> Sun | ... AG1: =TEXT(AG2,"DDD") -> Tue | AH1: Monthly Salary(avg) | AI1: Present | AJ1: Absent | AK1: Leave | AL1: Net Salary | AM1: Month | AN1: December
B2: Employee Name | C2: =IF(COLUMNS($C$2:C2)>DAY($AN$4),"",$AN$3+COLUMNS($C$2:C2)-1) -> 45627 | D2: =IF(COLUMNS($C$2:D2)>DAY($AN$4),"",$AN$3+COLUMNS($C$2:D2)-1) -> 45628 | E2: =IF(COLUMNS($C$2:E2)>DAY($AN$4),"",$AN$3+COLUMNS($C$2:E2)-1) -> 45629 | F2: =IF(COLUMNS($C$2:F2)>DAY($AN$4),"",$AN$3+COLUMNS($C$2:F2)-1) -> 45630 | G2: =IF(COLUMNS($C$2:G2)>DAY($AN$4),"",$AN$3+COLUMNS($C$2:G2)-1) -> 45631 | H2: =IF(COLUMNS($C$2:H2)>DAY($AN$4),"",$AN$3+COLUMNS($C$2:H2)-1) -> 45632 | I2: =IF(COLUMNS($C$2:I2)>DAY($AN$4),"",$AN$3+COLUMNS($C$2:I2)-1) -> 45633 | J2: =IF(COLUMNS($C$2:J2)>DAY($AN$4),"",$AN$3+COLUMNS($C$2:J2)-1) -> 45634 | ... AG2: =IF(COLUMNS($C$2:AG2)>DAY($AN$4),"",$AN$3+COLUMNS($C$2:AG2)-1) -> 45657 | AM2: Year | AN2: 2024
B3: Kaishav(Owner) | AH3: 50000 | AI3: =COUNTIF($C3:$AG3,"P") -> 0 | AJ3: =COUNTIF($C3:$AG3,"Ab") -> 0 | AK3: =COUNTIF($C3:$AG3,"L") -> 0 | AL3: =AH3/30*(AI3+AK3) -> 0 | AM3: Starting Date | AN3: =DATE(AN2,MONTH(AN1&1),1) -> 45627
B4: Raman | AH4: 15000 | AI4: =COUNTIF($C4:$AG4,"P") -> 0 | AJ4: =COUNTIF($C4:$AG4,"Ab") -> 0 | AK4: =COUNTIF($C4:$AG4,"L") -> 0 | AL4: =AH4/30*(AI4+AK4) -> 0 | AM4: Ending Date | AN4: =EOMONTH(AN3,0) -> 45657
B5: Sohan | AH5: 18000 | AI5: =COUNTIF($C5:$AG5,"P") -> 0 | AJ5: =COUNTIF($C5:$AG5,"Ab") -> 0 | AK5: =COUNTIF($C5:$AG5,"L") -> 0 | AL5: =AH5/30*(AI5+AK5) -> 0
B6: Tilak | AH6: 10000 | AI6: =COUNTIF($C6:$AG6,"P") -> 0 | AJ6: =COUNTIF($C6:$AG6,"Ab") -> 0 | AK6: =COUNTIF($C6:$AG6,"L") -> 0 | AL6: =AH6/30*(AI6+AK6) -> 0

Sheet Graph

Sheet Sheet1
A1: Months | B1: Net Income | D1: Months | E1: Quantity Sold | H1: Product Name | I1: Iodex
A2: January | B2: ='Daily Sales(JAN)'!AP16 -> 190232.33 | D2: January | E2: =SUM('Daily Sales(JAN)'!AH3:AH57) -> 9418
A3: February | B3: =Februray!AP16 -> 182466.33 | D3: February | E3: =SUM(Februray!AH3:AH57) -> 8890 | H3: Values
A4: March | B4: =March!AP16 -> 193515 | D4: March | E4: =SUM(March!AH3:AH57) -> 9348 | H4: Sum of Jan(1) | I4: 190
A5: April | B5: =Aprail!AP16 -> 180992 | D5: April | E5: =SUM(Aprail!AH3:AH57) -> 8955 | H5: Sum of Feb(2) | I5: 129
A6: May | B6: =May!AP16 -> 188268 | D6: May | E6: =SUM(May!AH3:AH57) -> 9428 | H6: Sum of Mar(3) | I6: 176
A7: June | B7: =June!AP16 -> 184470.33 | D7: June | E7: =SUM(June!AH3:AH57) -> 9096 | H7: Sum of Apr(4) | I7: 171
A8: July | B8: =July!AP16 -> 195375.33 | D8: July | E8: =SUM(July!AH3:AH57) -> 9618 | H8: Sum of May(5) | I8: 179
A9: August | B9: =August!AP16 -> 192313.33 | D9: August | E9: =SUM(August!AH3:AH57) -> 9419 | H9: Sum of Jun(6) | I9: 160
A10: September | B10: =September!AP16 -> 177662 | D10: September | E10: =SUM(September!AH3:AH57) -> 9147 | H10: Sum of Jul(7) | I10: 168
A11: October | B11: =October!AP16 -> -73780 | D11: October | E11: =SUM(October!AH3:AH57) -> 83 | H11: Sum of Aug(8) | I11: 160
A12: November | B12: =November!AP16 -> -8680 | D12: November | E12: =SUM(November!AH3:AH57) -> 83 | H12: Sum of Sep(9) | I12: 186
A13: December | B13: =December!AP16 -> -8680 | D13: December | E13: =SUM(December!AH3:AH57) -> 83

Sheet HELP
